Workbook
Name Mapped_Owner: 'Mapped Opponent'!$B$4:$C$28

Sheet AllData
A1: Season | B1: Date | C1: Owner | D1: Team Name | E1: Team - Year | F1: QB | G1: Top RB | H1: Top WR | I1: TE | J1: Current Owner | K1: This Year | L1: Reg Season Finish | M1: Playoff Finish | N1: Finish | O1: Games Played | P1: Wins | Q1: Losses | R1: Final Points For | S1: Final Points Against | T1: City | U1: State | V1: ZIP | W1: Buy In | X1: $ Won | Y1: Profit | Z1: Championships | AA1: Playoff Appearances | AB1: Win Last Game? | AC1: Wins_PointsSort | AD1: Reg Season #1s | AE1: Reg Season Top Points | AF1: Power Rank Wins | AG1: Power Rank Losses | AH1: Power Rank GP | AI1: Rules | AJ1: Regular Season Pts Rank | AK1: Points For Index | AL1: Points Against Index | AM1: Weekly Top 6 Scores
A2: 2009 | B2: 39814 | C2: Hudspeath | D2: Cutler's Year | E2: =D2&" - "&A2 -> Cutler's Year - 2009 | F2: Tom Brady | G2: Ryan Grant | H2: Vincent Jackson | I2: Kellen Winslow | J2: Current Owner | L2: 2 | M2: 1 | N2: =M2 -> 1 | O2: 13 | P2: 9 | Q2: =13-P2 -> 4 | R2: 1329 | S2: 1234 | T2: Bloomington | U2: Indiana | V2: 47405 | W2: 25 | X2: 100 | Y2: =X2-W2 -> 75 | Z2: =IF(M2=1,1,0) -> 1 | AA2: =if(L2<7,1,0) -> 1 | AC2: =P2*100+R2/4 -> 1232.25 | AD2: =if(L2=1,1,0) -> 0 | AF2: =sumifs('WL Matrix 2'!T:T,'WL Matrix 2'!B:B,A2,'WL Matrix 2'!C:C,C2,'WL Matrix 2'!M:M,"Regular Season") -> 0 | AI2: No PPR | AJ2: =rank(R2,$R$2:$R$13) -> 2 | AK2: =R2/ averageif($A:$A,A2,R:R) -> 1.0749528 | AL2: =S2/averageif($A:$A,A2,S:S) -> 0.99817998 | AM2: =sumifs('WL Matrix 2'!T:T,'WL Matrix 2'!B:B,A2,'WL Matrix 2'!C:C,C2,'WL Matrix 2'!M:M,"Regular Season") -> 0
A3: 2009 | B3: 39814 | C3: Katz | D3: ak47 | E3: =D3&" - "&A3 -> ak47 - 2009 | F3: Kurt Warner | G3: Maurice Jones-Drew | H3: Steve Smith | I3: Dallas Clark | J3: Retired Owner | L3: 8 | M3: 2 | N3: =M3 -> 2 | O3: 13 | P3: 6 | Q3: =13-P3 -> 7 | R3: 1209 | S3: 1263 | T3: Bloomington | U3: Indiana | V3: 47405 | W3: 25 | X3: 60 | Y3: =X3-W3 -> 35 | Z3: =IF(M3=1,1,0) -> 0 | AA3: =if(L3<7,1,0) -> 0 | AC3: =P3*100+R3/4 -> 902.25 | AD3: =if(L3=1,1,0) -> 0 | AF3: =sumifs('WL Matrix 2'!T:T,'WL Matrix 2'!B:B,A3,'WL Matrix 2'!C:C,C3,'WL Matrix 2'!M:M,"Regular Season") -> 0 | AI3: No PPR | AJ3: =rank(R3,$R$2:$R$13) -> 9 | AK3: =R3/ averageif($A:$A,A3,R:R) -> 0.97789161 | AL3: =S3/averageif($A:$A,A3,S:S) -> 1.021638 | AM3: =sumifs('WL Matrix 2'!T:T,'WL Matrix 2'!B:B,A3,'WL Matrix 2'!C:C,C3,'WL Matrix 2'!M:M,"Regular Season") -> 0
A4: 2009 | B4: 39814 | C4: Tayski | D4: Brett Favre | E4: =D4&" - "&A4 -> Brett Favre - 2009 | F4: Drew Brees | G4: Joseph Addai | H4: DeSean Jackson | I4: Greg Olsen | J4: Current Owner | L4: 5 | M4: 3 | N4: =M4 -> 3 | O4: 13 | P4: 8 | Q4: =13-P4 -> 5 | R4: 1248 | S4: 1206 | T4: Bloomington | U4: Indiana | V4: 47405 | W4: 25 | X4: 25 | Y4: =X4-W4 -> 0 | Z4: =IF(M4=1,1,0) -> 0 | AA4: =if(L4<7,1,0) -> 1 | AC4: =P4*100+R4/4 -> 1112 | AD4: =if(L4=1,1,0) -> 0 | AF4: =sumifs('WL Matrix 2'!T:T,'WL Matrix 2'!B:B,A4,'WL Matrix 2'!C:C,C4,'WL Matrix 2'!M:M,"Regular Season") -> 0 | AI4: No PPR | AJ4: =rank(R4,$R$2:$R$13) -> 6 | AK4: =R4/ averageif($A:$A,A4,R:R) -> 1.0094365 | AL4: =S4/averageif($A:$A,A4,S:S) -> 0.97553084 | AM4: =sumifs('WL Matrix 2'!T:T,'WL Matrix 2'!B:B,A4,'WL Matrix 2'!C:C,C4,'WL Matrix 2'!M:M,"Regular Season") -> 0
A5: 2009 | B5: 39814 | C5: Salty | D5: Salt on My Knob | E5: =D5&" - "&A5 -> Salt on My Knob - 2009 | F5: Carson Palmer | G5: Laurence Maroney | H5: Andre Johnson | I5: Tony Gonzalez | J5: Current Owner | L5: 3 | M5: 4 | N5: =M5 -> 4 | O5: 13 | P5: 8 | Q5: =13-P5 -> 5 | R5: 1362 | S5: 1229 | T5: Bloomington | U5: Indiana | V5: 47405 | W5: 25 | X5: 40 | Y5: =X5-W5 -> 15 | Z5: =IF(M5=1,1,0) -> 0 | AA5: =if(L5<7,1,0) -> 1 | AC5: =P5*100+R5/4 -> 1140.5 | AD5: =if(L5=1,1,0) -> 0 | AE5: 1 | AF5: =sumifs('WL Matrix 2'!T:T,'WL Matrix 2'!B:B,A5,'WL Matrix 2'!C:C,C5,'WL Matrix 2'!M:M,"Regular Season") -> 0 | AI5: No PPR | AJ5: =rank(R5,$R$2:$R$13) -> 1 | AK5: =R5/ averageif($A:$A,A5,R:R) -> 1.1016446 | AL5: =S5/averageif($A:$A,A5,S:S) -> 0.99413549 | AM5: =sumifs('WL Matrix 2'!T:T,'WL Matrix 2'!B:B,A5,'WL Matrix 2'!C:C,C5,'WL Matrix 2'!M:M,"Regular Season") -> 0
A6: 2009 | B6: 39814 | C6: Rooney/Jackson | D6: Dawg's Gotta Eat | E6: =D6&" - "&A6 -> Dawg's Gotta Eat - 2009 | F6: Aaron Rodgers | G6: Adrian Peterson | H6: Calvin Johnson | I6: Visanthe Shiancoe | J6: Current Owner | L6: 4 | M6: 5 | N6: =M6 -> 5 | O6: 13 | P6: 8 | Q6: =13-P6 -> 5 | R6: 1327 | S6: 1179 | T6: Bloomington | U6: Indiana | V6: 47405 | W6: 25 | Y6: =X6-W6 -> -25 | Z6: =IF(M6=1,1,0) -> 0 | AA6: =if(L6<7,1,0) -> 1 | AC6: =P6*100+R6/4 -> 1131.75 | AD6: =if(L6=1,1,0) -> 0 | AF6: =sumifs('WL Matrix 2'!T:T,'WL Matrix 2'!B:B,A6,'WL Matrix 2'!C:C,C6,'WL Matrix 2'!M:M,"Regular Season") -> 0 | AI6: No PPR | AJ6: =rank(R6,$R$2:$R$13) -> 3 | AK6: =R6/ averageif($A:$A,A6,R:R) -> 1.0733351 | AL6: =S6/averageif($A:$A,A6,S:S) -> 0.9536906 | AM6: =sumifs('WL Matrix 2'!T:T,'WL Matrix 2'!B:B,A6,'WL Matrix 2'!C:C,C6,'WL Matrix 2'!M:M,"Regular Season") -> 0
A7: 2009 | B7: 39814 | C7: Tennyson | D7: Rob Brochocinco | E7: =D7&" - "&A7 -> Rob Brochocinco - 2009 | F7: Matt Ryan | G7: Jamaal Charles | H7: Reggie Wayne | I7: Fred Davis | J7: Retired Owner | L7: 6 | M7: 6 | N7: =M7 -> 6 | O7: 13 | P7: 6 | Q7: =13-P7 -> 7 | R7: 1251 | S7: 1334 | T7: Bloomington | U7: Indiana | V7: 47405 | W7: 25 | Y7: =X7-W7 -> -25 | Z7: =IF(M7=1,1,0) -> 0 | AA7: =if(L7<7,1,0) -> 1 | AC7: =P7*100+R7/4 -> 912.75 | AD7: =if(L7=1,1,0) -> 0 | AF7: =sumifs('WL Matrix 2'!T:T,'WL Matrix 2'!B:B,A7,'WL Matrix 2'!C:C,C7,'WL Matrix 2'!M:M,"Regular Season") -> 0 | AI7: No PPR | AJ7: =rank(R7,$R$2:$R$13) -> 5 | AK7: =R7/ averageif($A:$A,A7,R:R) -> 1.011863 | AL7: =S7/averageif($A:$A,A7,S:S) -> 1.0790698 | AM7: =sumifs('WL Matrix 2'!T:T,'WL Matrix 2'!B:B,A7,'WL Matrix 2'!C:C,C7,'WL Matrix 2'!M:M,"Regular Season") -> 0
A8: 2009 | B8: 39814 | C8: Fellows | D8: Frat Stars | E8: =D8&" - "&A8 -> Frat Stars - 2009 | F8: Brett Favre | G8: Michael Turner | H8: Santonio Holmes | I8: Jermichael Finley | J8: Retired Owner | L8: 1 | M8: 7 | N8: =M8 -> 7 | O8: 13 | P8: 10 | Q8: =13-P8 -> 3 | R8: 1317 | S8: 1206 | T8: Bloomington | U8: Indiana | V8: 47405 | W8: 25 | X8: 75 | Y8: =X8-W8 -> 50 | Z8: =IF(M8=1,1,0) -> 0 | AA8: =if(L8<7,1,0) -> 1 | AC8: =P8*100+R8/4 -> 1329.25 | AD8: =if(L8=1,1,0) -> 1 | AF8: =sumifs('WL Matrix 2'!T:T,'WL Matrix 2'!B:B,A8,'WL Matrix 2'!C:C,C8,'WL Matrix 2'!M:M,"Regular Season") -> 0 | AI8: No PPR | AJ8: =rank(R8,$R$2:$R$13) -> 4 | AK8: =R8/ averageif($A:$A,A8,R:R) -> 1.0652467 | AL8: =S8/averageif($A:$A,A8,S:S) -> 0.97553084 | AM8: =sumifs('WL Matrix 2'!T:T,'WL Matrix 2'!B:B,A8,'WL Matrix 2'!C:C,C8,'WL Matrix 2'!M:M,"Regular Season") -> 0
A9: 2009 | B9: 39814 | C9: Burgess | D9: Bro and Sixteen | E9: =D9&" - "&A9 -> Bro and Sixteen - 2009 | F9: Philip Rivers | G9: Thomas Jones | H9: Larry Fitzgerald | I9: Vernon Davis | J9: Retired Owner | L9: 7 | M9: 8 | N9: =M9 -> 8 | O9: 13 | P9: 6 | Q9: =13-P9 -> 7 | R9: 1238 | S9: 1170 | T9: Bloomington | U9: Indiana | V9: 47405 | W9: 25 | Y9: =X9-W9 -> -25 | Z9: =IF(M9=1,1,0) -> 0 | AA9: =if(L9<7,1,0) -> 0 | AC9: =P9*100+R9/4 -> 909.5 | AD9: =if(L9=1,1,0) -> 0 | AF9: =sumifs('WL Matrix 2'!T:T,'WL Matrix 2'!B:B,A9,'WL Matrix 2'!C:C,C9,'WL Matrix 2'!M:M,"Regular Season") -> 0 | AI9: No PPR | AJ9: =rank(R9,$R$2:$R$13) -> 7 | AK9: =R9/ averageif($A:$A,A9,R:R) -> 1.0013481 | AL9: =S9/averageif($A:$A,A9,S:S) -> 0.94641052 | AM9: =sumifs('WL Matrix 2'!T:T,'WL Matrix 2'!B:B,A9,'WL Matrix 2'!C:C,C9,'WL Matrix 2'!M:M,"Regular Season") -> 0
A10: 2009 | B10: 39814 | C10: Guckien | D10: Roon's Raging Broner | E10: =D10&" - "&A10 -> Roon's Raging Broner - 2009 | F10: Joe Flacco | G10: Frank Gore | H10: Miles Austin | I10: Dustin Keller | J10: Retired Owner | L10: 9 | M10: 9 | N10: =M10 -> 9 | O10: 13 | P10: 5 | Q10: =13-P10 -> 8 | R10: 1163 | S10: 1246 | T10: Bloomington | U10: Indiana | V10: 47405 | W10: 25 | Y10: =X10-W10 -> -25 | Z10: =IF(M10=1,1,0) -> 0 | AA10: =if(L10<7,1,0) -> 0 | AC10: =P10*100+R10/4 -> 790.75 | AD10: =if(L10=1,1,0) -> 0 | AF10: =sumifs('WL Matrix 2'!T:T,'WL Matrix 2'!B:B,A10,'WL Matrix 2'!C:C,C10,'WL Matrix 2'!M:M,"Regular Season") -> 0 | AI10: No PPR | AJ10: =rank(R10,$R$2:$R$13) -> 10 | AK10: =R10/ averageif($A:$A,A10,R:R) -> 0.94068482 | AL10: =S10/averageif($A:$A,A10,S:S) -> 1.0078868 | AM10: =sumifs('WL Matrix 2'!T:T,'WL Matrix 2'!B:B,A10,'WL Matrix 2'!C:C,C10,'WL Matrix 2'!M:M,"Regular Season") -> 0
A11: 2009 | B11: 39814 | C11: Pierson | D11: LiveTheDream01 | E11: =D11&" - "&A11 -> LiveTheDream01 - 2009 | F11: Peyton Manning | G11: Ricky Williams | H11: Sidney Rice | I11: Antonio Gates | J11: Current Owner | L11: 12 | M11: 12 | N11: =M11 -> 12 | O11: 13 | P11: 3 | Q11: =13-P11 -> 10 | R11: 1049 | S11: 1216 | T11: Bloomington | U11: Indiana | V11: 47405 | W11: 25 | Y11: =X11-W11 -> -25 | Z11: =IF(M11=1,1,0) -> 0 | AA11: =if(L11<7,1,0) -> 0 | AC11: =P11*100+R11/4 -> 562.25 | AD11: =if(L11=1,1,0) -> 0 | AF11: =sumifs('WL Matrix 2'!T:T,'WL Matrix 2'!B:B,A11,'WL Matrix 2'!C:C,C11,'WL Matrix 2'!M:M,"Regular Season") -> 0 | AI11: No PPR | AJ11: =rank(R11,$R$2:$R$13) -> 12 | AK11: =R11/ averageif($A:$A,A11,R:R) -> 0.84847668 | AL11: =S11/averageif($A:$A,A11,S:S) -> 0.98361982 | AM11: =sumifs('WL Matrix 2'!T:T,'WL Matrix 2'!B:B,A11,'WL Matrix 2'!C:C,C11,'WL Matrix 2'!M:M,"Regular Season") -> 0
A12: 2009 | B12: 39814 | C12: Shep | D12: Broseph | E12: =D12&" - "&A12 -> Broseph - 2009 | F12: Matt Schaub | G12: Chris Johnson | H12: Roddy White | I12: Zach Miller | J12: Current Owner | L12: 11 | M12: 11 | N12: =M12 -> 11 | O12: 13 | P12: 4 | Q12: =13-P12 -> 9 | R12: 1126 | S12: 1232 | T12: Bloomington | U12: Indiana | V12: 47405 | W12: 25 | Y12: =X12-W12 -> -25 | Z12: =IF(M12=1,1,0) -> 0 | AA12: =if(L12<7,1,0) -> 0 | AC12: =P12*100+R12/4 -> 681.5 | AD12: =if(L12=1,1,0) -> 0 | AF12: =sumifs('WL Matrix 2'!T:T,'WL Matrix 2'!B:B,A12,'WL Matrix 2'!C:C,C12,'WL Matrix 2'!M:M,"Regular Season") -> 0 | AI12: No PPR | AJ12: =rank(R12,$R$2:$R$13) -> 11 | AK12: =R12/ averageif($A:$A,A12,R:R) -> 0.91075762 | AL12: =S12/averageif($A:$A,A12,S:S) -> 0.99656218 | AM12: =sumifs('WL Matrix 2'!T:T,'WL Matrix 2'!B:B,A12,'WL Matrix 2'!C:C,C12,'WL Matrix 2'!M:M,"Regular Season") -> 0
A13: 2009 | B13: 39814 | C13: Austin Marshall | D13: N*gros | E13: =D13&" - "&A13 -> N*gros - 2009 | F13: Donovan McNabb | G13: Jonathan Stewart | H13: Steve Smith | I13: Jason Witten | J13: Retired Owner | L13: 10 | M13: 10 | N13: =M13 -> 10 | O13: 13 | P13: 5 | Q13: =13-P13 -> 8 | R13: 1217 | S13: 1320 | T13: Bloomington | U13: Indiana | V13: 47405 | W13: 25 | Y13: =X13-W13 -> -25 | Z13: =IF(M13=1,1,0) -> 0 | AA13: =if(L13<7,1,0) -> 0 | AC13: =P13*100+R13/4 -> 804.25 | AD13: =if(L13=1,1,0) -> 0 | AF13: =sumifs('WL Matrix 2'!T:T,'WL Matrix 2'!B:B,A13,'WL Matrix 2'!C:C,C13,'WL Matrix 2'!M:M,"Regular Season") -> 0 | AI13: No PPR | AJ13: =rank(R13,$R$2:$R$13) -> 8 | AK13: =R13/ averageif($A:$A,A13,R:R) -> 0.98436236 | AL13: =S13/averageif($A:$A,A13,S:S) -> 1.0677452 | AM13: =sumifs('WL Matrix 2'!T:T,'WL Matrix 2'!B:B,A13,'WL Matrix 2'!C:C,C13,'WL Matrix 2'!M:M,"Regular Season") -> 0
A14: 2010 | B14: 40179 | C14: Mac | D14: Bieber Fever | E14: =D14&" - "&A14 -> Bieber Fever - 2010 | F14: Michael Vick | G14: Peyton Hillis | H14: Mike Wallace | I14: Rob Gronkowski | J14: Retired Owner | L14: 6 | M14: 1 | N14: =M14 -> 1 | O14: 13 | P14: 6 | Q14: =13-P14 -> 7 | R14: 1224 | S14: 1139 | T14: Bloomington | U14: Indiana | V14: 47405 | W14: 25 | X14: 100 | Y14: =X14-W14 -> 75 | Z14: =IF(M14=1,1,0) -> 1 | AA14: =if(L14<7,1,0) -> 1 | AC14: =P14*100+R14/4 -> 906 | AD14: =if(L14=1,1,0) -> 0 | AF14: =sumifs('WL Matrix 2'!T:T,'WL Matrix 2'!B:B,A14,'WL Matrix 2'!C:C,C14,'WL Matrix 2'!M:M,"Regular Season") -> 0 | AI14: No PPR | AJ14: =rank(R14,$R$14:$R$25) -> 3 | AK14: =R14/ averageif($A:$A,A14,R:R) -> 1.0554757 | AL14: =S14/averageif($A:$A,A14,S:S) -> 0.98210821 | AM14: =sumifs('WL Matrix 2'!T:T,'WL Matrix 2'!B:B,A14,'WL Matrix 2'!C:C,C14,'WL Matrix 2'!M:M,"Regular Season") -> 0
A15: 2010 | B15: 40179 | C15: Hudspeath | D15: Cutler's Year | E15: =D15&" - "&A15 -> Cutler's Year - 2010 | F15: Phillip Rivers | G15: Maurice Jones-Drew | H15: Roddy White | I15: Tony Gonzalez | J15: Current Owner | L15: 1 | M15: 2 | N15: =M15 -> 2 | O15: 13 | P15: 11 | Q15: =13-P15 -> 2 | R15: 1334 | S15: 1068 | T15: Bloomington | U15: Indiana | V15: 47406 | W15: 25 | X15: =60+40+75 -> 175 | Y15: =X15-W15 -> 150 | Z15: =IF(M15=1,1,0) -> 0 | AA15: =if(L15<7,1,0) -> 1 | AC15: =P15*100+R15/4 -> 1433.5 | AD15: =if(L15=1,1,0) -> 1 | AE15: 1 | AF15: =sumifs('WL Matrix 2'!T:T,'WL Matrix 2'!B:B,A15,'WL Matrix 2'!C:C,C15,'WL Matrix 2'!M:M,"Regular Season") -> 0 | AI15: No PPR | AJ15: =rank(R15,$R$14:$R$25) -> 1 | AK15: =R15/ averageif($A:$A,A15,R:R) -> 1.1503306 | AL15: =S15/averageif($A:$A,A15,S:S) -> 0.92088812 | AM15: =sumifs('WL Matrix 2'!T:T,'WL Matrix 2'!B:B,A15,'WL Matrix 2'!C:C,C15,'WL Matrix 2'!M:M,"Regular Season") -> 0
A16: 2010 | B16: 40179 | C16: KnardDawg | D16: Buckeyes | E16: =D16&" - "&A16 -> Buckeyes - 2010 | F16: Carson Palmer | G16: Adrian Peterson | H16: Dwayne Bowe | I16: Zach Miller | J16: Current Owner | L16: 2 | M16: 3 | N16: =M16 -> 3 | O16: 13 | P16: 8 | Q16: =13-P16 -> 5 | R16: 1221 | S16: 1128 | T16: Bloomington | U16: Indiana | V16: 47406 | W16: 25 | X16: 25 | Y16: =X16-W16 -> 0 | Z16: =IF(M16=1,1,0) -> 0 | AA16: =if(L16<7,1,0) -> 1 | AC16: =P16*100+R16/4 -> 1105.25 | AD16: =if(L16=1,1,0) -> 0 | AF16: =sumifs('WL Matrix 2'!T:T,'WL Matrix 2'!B:B,A16,'WL Matrix 2'!C:C,C16,'WL Matrix 2'!M:M,"Regular Season") -> 0 | AI16: No PPR | AJ16: =rank(R16,$R$14:$R$25) -> 4 | AK16: =R16/ averageif($A:$A,A16,R:R) -> 1.0528888 | AL16: =S16/averageif($A:$A,A16,S:S) -> 0.97262341 | AM16: =sumifs('WL Matrix 2'!T:T,'WL Matrix 2'!B:B,A16,'WL Matrix 2'!C:C,C16,'WL Matrix 2'!M:M,"Regular Season") -> 0
A17: 2010 | B17: 40179 | C17: Tayski | D17: Fahv-Ray is My Padre | E17: =D17&" - "&A17 -> Fahv-Ray is My Padre - 2010 | F17: Matt Schaub | G17: Arian Foster | H17: Calvin Johnson | I17: Dustin Keller | J17: Current Owner | L17: 4 | M17: 4 | N17: =M17 -> 4 | O17: 13 | P17: 7 | Q17: =13-P17 -> 6 | R17: 1138 | S17: 1249 | T17: Bloomington | U17: Indiana | V17: 47406 | W17: 25 | Y17: =X17-W17 -> -25 | Z17: =IF(M17=1,1,0) -> 0 | AA17: =if(L17<7,1,0) -> 1 | AC17: =P17*100+R17/4 -> 984.5 | AD17: =if(L17=1,1,0) -> 0 | AF17: =sumifs('WL Matrix 2'!T:T,'WL Matrix 2'!B:B,A17,'WL Matrix 2'!C:C,C17,'WL Matrix 2'!M:M,"Regular Season") -> 0 | AI17: No PPR | AJ17: =rank(R17,$R$14:$R$25) -> 7 | AK17: =R17/ averageif($A:$A,A17,R:R) -> 0.98131647 | AL17: =S17/averageif($A:$A,A17,S:S) -> 1.0769562 | AM17: =sumifs('WL Matrix 2'!T:T,'WL Matrix 2'!B:B,A17,'WL Matrix 2'!C:C,C17,'WL Matrix 2'!M:M,"Regular Season") -> 0
A18: 2010 | B18: 40179 | C18: Salty | D18: Salt 'N' Peppers | E18: =D18&" - "&A18 -> Salt 'N' Peppers - 2010 | F18: Drew Brees | G18: Jamaal Charles | H18: Stevie Johnson | I18: Kellen Winslow | J18: Current Owner | L18: 3 | M18: 5 | N18: =M18 -> 5 | O18: 13 | P18: 7 | Q18: =13-P18 -> 6 | R18: 1237 | S18: 1157 | T18: Bloomington | U18: Indiana | V18: 47406 | W18: 25 | Y18: =X18-W18 -> -25 | Z18: =IF(M18=1,1,0) -> 0 | AA18: =if(L18<7,1,0) -> 1 | AC18: =P18*100+R18/4 -> 1009.25 | AD18: =if(L18=1,1,0) -> 0 | AF18: =sumifs('WL Matrix 2'!T:T,'WL Matrix 2'!B:B,A18,'WL Matrix 2'!C:C,C18,'WL Matrix 2'!M:M,"Regular Season") -> 0 | AI18: No PPR | AJ18: =rank(R18,$R$14:$R$25) -> 2 | AK18: =R18/ averageif($A:$A,A18,R:R) -> 1.0666858 | AL18: =S18/averageif($A:$A,A18,S:S) -> 0.9976288 | AM18: =sumifs('WL Matrix 2'!T:T,'WL Matrix 2'!B:B,A18,'WL Matrix 2'!C:C,C18,'WL Matrix 2'!M:M,"Regular Season") -> 0
A19: 2010 | B19: 40179 | C19: Cock | D19: Acochalypto | E19: =D19&" - "&A19 -> Acochalypto - 2010 | F19: Joe Flacco | G19: Ahmad Bradshaw | H19: Larry Fitzgerald | I19: Aaron Hernandez | J19: Current Owner | L19: 5 | M19: 6 | N19: =M19 -> 6 | O19: 13 | P19: 7 | Q19: =13-P19 -> 6 | R19: 1087 | S19: 1135 | T19: Bloomington | U19: Indiana | V19: 47406 | W19: 25 | Y19: =X19-W19 -> -25 | Z19: =IF(M19=1,1,0) -> 0 | AA19: =if(L19<7,1,0) -> 1 | AC19: =P19*100+R19/4 -> 971.75 | AD19: =if(L19=1,1,0) -> 0 | AF19: =sumifs('WL Matrix 2'!T:T,'WL Matrix 2'!B:B,A19,'WL Matrix 2'!C:C,C19,'WL Matrix 2'!M:M,"Regular Season") -> 0 | AI19: No PPR | AJ19: =rank(R19,$R$14:$R$25) -> 10 | AK19: =R19/ averageif($A:$A,A19,R:R) -> 0.93733832 | AL19: =S19/averageif($A:$A,A19,S:S) -> 0.97865919 | AM19: =sumifs('WL Matrix 2'!T:T,'WL Matrix 2'!B:B,A19,'WL Matrix 2'!C:C,C19,'WL Matrix 2'!M:M,"Regular Season") -> 0
A20: 2010 | B20: 40179 | C20: Pierson | D20: Deny Till You Die | E20: =D20&" - "&A20 -> Deny Till You Die - 2010 | F20: Eli Manning | G20: Chris Johnson | H20: Brandon Lloyd | I20: Greg Olsen | J20: Current Owner | L20: 7 | M20: 7 | N20: =M20 -> 7 | O20: 13 | P20: 5 | Q20: =13-P20 -> 8 | R20: 1130 | S20: 1153 | T20: Bloomington | U20: Indiana | V20: 47406 | W20: 25 | Y20: =X20-W20 -> -25 | Z20: =IF(M20=1,1,0) -> 0 | AA20: =if(L20<7,1,0) -> 0 | AC20: =P20*100+R20/4 -> 782.5 | AD20: =if(L20=1,1,0) -> 0 | AF20: =sumifs('WL Matrix 2'!T:T,'WL Matrix 2'!B:B,A20,'WL Matrix 2'!C:C,C20,'WL Matrix 2'!M:M,"Regular Season") -> 0 | AI20: No PPR | AJ20: =rank(R20,$R$14:$R$25) -> 8 | AK20: =R20/ averageif($A:$A,A20,R:R) -> 0.97441794 | AL20: =S20/averageif($A:$A,A20,S:S) -> 0.99417978 | AM20: =sumifs('WL Matrix 2'!T:T,'WL Matrix 2'!B:B,A20,'WL Matrix 2'!C:C,C20,'WL Matrix 2'!M:M,"Regular Season") -> 0
A21: 2010 | B21: 40179 | C21: Shep | D21: America's Team | E21: =D21&" - "&A21 -> America's Team - 2010 | F21: Peyton Manning | G21: BenJarvus Green-Ellis | H21: Braylon Edwards | I21: Jason Witten | J21: Current Owner | L21: 8 | M21: 8 | N21: =M21 -> 8 | O21: 13 | P21: 6 | Q21: =13-P21 -> 7 | R21: 1085 | S21: 1131 | T21: Bloomington | U21: Indiana | V21: 47406 | W21: 25 | Y21: =X21-W21 -> -25 | Z21: =IF(M21=1,1,0) -> 0 | AA21: =if(L21<7,1,0) -> 0 | AC21: =P21*100+R21/4 -> 871.25 | AD21: =if(L21=1,1,0) -> 0 | AF21: =sumifs('WL Matrix 2'!T:T,'WL Matrix 2'!B:B,A21,'WL Matrix 2'!C:C,C21,'WL Matrix 2'!M:M,"Regular Season") -> 0 | AI21: No PPR | AJ21: =rank(R21,$R$14:$R$25) -> 11 | AK21: =R21/ averageif($A:$A,A21,R:R) -> 0.93561368 | AL21: =S21/averageif($A:$A,A21,S:S) -> 0.97521017 | AM21: =sumifs('WL Matrix 2'!T:T,'WL Matrix 2'!B:B,A21,'WL Matrix 2'!C:C,C21,'WL Matrix 2'!M:M,"Regular Season") -> 0
A22: 2010 | B22: 40179 | C22: Buser | D22: Milledgevile Knights | E22: =D22&" - "&A22 -> Milledgevile Knights - 2010 | F22: Tom Brady | G22: Rashard Mendenhall | H22: DeSean Jackson | I22: Brandon Pettigrew | J22: Current Owner | L22: 9 | M22: 9 | N22: =M22 -> 9 | O22: 13 | P22: 5 | Q22: =13-P22 -> 8 | R22: 1163 | S22: 1214 | T22: Bloomington | U22: Indiana | V22: 47406 | W22: 25 | Y22: =X22-W22 -> -25 | Z22: =IF(M22=1,1,0) -> 0 | AA22: =if(L22<7,1,0) -> 0 | AC22: =P22*100+R22/4 -> 790.75 | AD22: =if(L22=1,1,0) -> 0 | AF22: =sumifs('WL Matrix 2'!T:T,'WL Matrix 2'!B:B,A22,'WL Matrix 2'!C:C,C22,'WL Matrix 2'!M:M,"Regular Season") -> 0 | AI22: No PPR | AJ22: =rank(R22,$R$14:$R$25) -> 5 | AK22: =R22/ averageif($A:$A,A22,R:R) -> 1.0028744 | AL22: =S22/averageif($A:$A,A22,S:S) -> 1.0467773 | AM22: =sumifs('WL Matrix 2'!T:T,'WL Matrix 2'!B:B,A22,'WL Matrix 2'!C:C,C22,'WL Matrix 2'!M:M,"Regular Season") -> 0
A23: 2010 | B23: 40179 | C23: Hobbs | D23: Ham Sobbs | E23: =D23&" - "&A23 -> Ham Sobbs - 2010 | F23: Jay Cutler | G23: Mike Tolbert | H23: Andre Johnson | I23: Vernon Davis | J23: Retired Owner | L23: 10 | M23: 10 | N23: =M23 -> 10 | O23: 13 | P23: 6 | Q23: =13-P23 -> 7 | R23: 1109 | S23: 1266 | T23: Bloomington | U23: Indiana | V23: 47405 | W23: 25 | Y23: =X23-W23 -> -25 | Z23: =IF(M23=1,1,0) -> 0 | AA23: =if(L23<7,1,0) -> 0 | AC23: =P23*100+R23/4 -> 877.25 | AD23: =if(L23=1,1,0) -> 0 | AF23: =sumifs('WL Matrix 2'!T:T,'WL Matrix 2'!B:B,A23,'WL Matrix 2'!C:C,C23,'WL Matrix 2'!M:M,"Regular Season") -> 0 | AI23: No PPR | AJ23: =rank(R23,$R$14:$R$25) -> 9 | AK23: =R23/ averageif($A:$A,A23,R:R) -> 0.95630928 | AL23: =S23/averageif($A:$A,A23,S:S) -> 1.0916146 | AM23: =sumifs('WL Matrix 2'!T:T,'WL Matrix 2'!B:B,A23,'WL Matrix 2'!C:C,C23,'WL Matrix 2'!M:M,"Regular Season") -> 0
A24: 2010 | B24: 40179 | C24: Rooney/Jackson | D24: The Dawgfather | E24: =D24&" - "&A24 -> The Dawgfather - 2010 | F24: Aaron Rodgers | G24: Ray Rice | H24: Jeremy Maclin | I24: Jacob Tamme | J24: Current Owner | L24: 11 | M24: 11 | N24: =M24 -> 11 | O24: 13 | P24: 5 | Q24: =13-P24 -> 8 | R24: 1155 | S24: 1227 | T24: Bloomington | U24: Indiana | V24: 47406 | W24: 25 | Y24: =X24-W24 -> -25 | Z24: =IF(M24=1,1,0) -> 0 | AA24: =if(L24<7,1,0) -> 0 | AC24: =P24*100+R24/4 -> 788.75 | AD24: =if(L24=1,1,0) -> 0 | AF24: =sumifs('WL Matrix 2'!T:T,'WL Matrix 2'!B:B,A24,'WL Matrix 2'!C:C,C24,'WL Matrix 2'!M:M,"Regular Season") -> 0 | AI24: No PPR | AJ24: =rank(R24,$R$14:$R$25) -> 6 | AK24: =R24/ averageif($A:$A,A24,R:R) -> 0.99597586 | AL24: =S24/averageif($A:$A,A24,S:S) -> 1.0579866 | AM24: =sumifs('WL Matrix 2'!T:T,'WL Matrix 2'!B:B,A24,'WL Matrix 2'!C:C,C24,'WL Matrix 2'!M:M,"Regular Season") -> 0
A25: 2010 | B25: 40179 | C25: Fellows | D25: Frat Stars II | E25: =D25&" - "&A25 -> Frat Stars II - 2010 | F25: Josh Freeman | G25: Brandon Jacobs | H25: Miles Austin | I25: Antonio Gates | J25: Retired Owner | L25: 12 | M25: 12 | N25: =M25 -> 12 | O25: 13 | P25: 5 | Q25: =13-P25 -> 8 | R25: 1033 | S25: 1050 | T25: Bloomington | U25: Indiana | V25: 47406 | W25: 25 | Y25: =X25-W25 -> -25 | Z25: =IF(M25=1,1,0) -> 0 | AA25: =if(L25<7,1,0) -> 0 | AC25: =P25*100+R25/4 -> 758.25 | AD25: =if(L25=1,1,0) -> 0 | AF25: =sumifs('WL Matrix 2'!T:T,'WL Matrix 2'!B:B,A25,'WL Matrix 2'!C:C,C25,'WL Matrix 2'!M:M,"Regular Season") -> 0 | AI25: No PPR | AJ25: =rank(R25,$R$14:$R$25) -> 12 | AK25: =R25/ averageif($A:$A,A25,R:R) -> 0.89077321 | AL25: =S25/averageif($A:$A,A25,S:S) -> 0.90536754 | AM25: =sumifs('WL Matrix 2'!T:T,'WL Matrix 2'!B:B,A25,'WL Matrix 2'!C:C,C25,'WL Matrix 2'!M:M,"Regular Season") -> 0
A26: 2011 | B26: 40544 | C26: Buser | D26: Yes We Cam | E26: =D26&" - "&A26 -> Yes We Cam - 2011 | F26: Cam Newton | G26: Chris Johnson | H26: Marques Colston | I26: Brent Celek | J26: Current Owner | L26: 2 | M26: 1 | N26: =M26 -> 1 | O26: 13 | P26: 9 | Q26: =13-P26 -> 4 | R26: 1229 | S26: 1308 | T26: London | U26: England | V26: London | W26: 25 | X26: 100 | Y26: =X26-W26 -> 75 | Z26: =IF(M26=1,1,0) -> 1 | AA26: =if(L26<7,1,0) -> 1 | AC26: =P26*100+R26/4 -> 1207.25 | AD26: =if(L26=1,1,0) -> 0 | AF26: =sumifs('WL Matrix 2'!T:T,'WL Matrix 2'!B:B,A26,'WL Matrix 2'!C:C,C26,'WL Matrix 2'!M:M,"Regular Season") -> 89 | AG26: =11*O26-AF26 -> 54 | AI26: No PPR | AJ26: =rank(R26,$R$26:$R$37) -> 4 | AK26: =R26/ averageif($A:$A,A26,R:R) -> 1.0676126 | AL26: =S26/averageif($A:$A,A26,S:S) -> 1.114377 | AM26: =sumifs('WL Matrix 2'!T:T,'WL Matrix 2'!B:B,A26,'WL Matrix 2'!C:C,C26,'WL Matrix 2'!M:M,"Regular Season") -> 89
A27: 2011 | B27: 40544 | C27: T-How | D27: Kibbles 'n Fitz | E27: =D27&" - "&A27 -> Kibbles 'n Fitz - 2011 | F27: Tono Romo | G27: Michael Turner | H27: Larry Fitzgerald | I27: Kellen Winslow | J27: Current Owner | L27: 4 | M27: 2 | N27: =M27 -> 2 | O27: 13 | P27: 8 | Q27: =13-P27 -> 5 | R27: 1100 | S27: 1114 | T27: Barcelona | U27: Spain | V27: Barcelona | W27: 25 | X27: 60 | Y27: =X27-W27 -> 35 | Z27: =IF(M27=1,1,0) -> 0 | AA27: =if(L27<7,1,0) -> 1 | AC27: =P27*100+R27/4 -> 1075 | AD27: =if(L27=1,1,0) -> 0 | AF27: =sumifs('WL Matrix 2'!T:T,'WL Matrix 2'!B:B,A27,'WL Matrix 2'!C:C,C27,'WL Matrix 2'!M:M,"Regular Season") -> 69 | AG27: =11*O27-AF27 -> 74 | AI27: No PPR | AJ27: =rank(R27,$R$26:$R$37) -> 9 | AK27: =R27/ averageif($A:$A,A27,R:R) -> 0.95555234 | AL27: =S27/averageif($A:$A,A27,S:S) -> 0.94909478 | AM27: =sumifs('WL Matrix 2'!T:T,'WL Matrix 2'!B:B,A27,'WL Matrix 2'!C:C,C27,'WL Matrix 2'!M:M,"Regular Season") -> 69
A28: 2011 | B28: 40544 | C28: Pierson | D28: Gambling Man | E28: =D28&" - "&A28 -> Gambling Man - 2011 | F28: Phillip Rivers | G28: Arian Foster | H28: Wes Welker | I28: Rob Gronkowski | J28: Current Owner | L28: 1 | M28: 3 | N28: =M28 -> 3 | O28: 13 | P28: 9 | Q28: =13-P28 -> 4 | R28: 1247 | S28: 1105 | T28: Bloomington | U28: Indiana | V28: 47406 | W28: 25 | X28: 100 | Y28: =X28-W28 -> 75 | Z28: =IF(M28=1,1,0) -> 0 | AA28: =if(L28<7,1,0) -> 1 | AC28: =P28*100+R28/4 -> 1211.75 | AD28: =if(L28=1,1,0) -> 1 | AF28: =sumifs('WL Matrix 2'!T:T,'WL Matrix 2'!B:B,A28,'WL Matrix 2'!C:C,C28,'WL Matrix 2'!M:M,"Regular Season") -> 88 | AG28: =11*O28-AF28 -> 55 | AI28: No PPR | AJ28: =rank(R28,$R$26:$R$37) -> 2 | AK28: =R28/ averageif($A:$A,A28,R:R) -> 1.0832489 | AL28: =S28/averageif($A:$A,A28,S:S) -> 0.94142705 | AM28: =sumifs('WL Matrix 2'!T:T,'WL Matrix 2'!B:B,A28,'WL Matrix 2'!C:C,C28,'WL Matrix 2'!M:M,"Regular Season") -> 88
A29: 2011 | B29: 40544 | C29: Salty | D29: Salt Bake City | E29: =D29&" - "&A29 -> Salt Bake City - 2011 | F29: Matthew Stafford | G29: Ray Rice | H29: Vincent Jackson | I29: Jason Witten | J29: Current Owner | L29: 3 | M29: 4 | N29: =M29 -> 4 | O29: 13 | P29: 8 | Q29: =13-P29 -> 5 | R29: 1308 | S29: 1090 | T29: London | U29: England | V29: London | W29: 25 | X29: 40 | Y29: =X29-W29 -> 15 | Z29: =IF(M29=1,1,0) -> 0 | AA29: =if(L29<7,1,0) -> 1 | AC29: =P29*100+R29/4 -> 1127 | AD29: =if(L29=1,1,0) -> 0 | AE29: 1 | AF29: =sumifs('WL Matrix 2'!T:T,'WL Matrix 2'!B:B,A29,'WL Matrix 2'!C:C,C29,'WL Matrix 2'!M:M,"Regular Season") -> 97 | AG29: =11*O29-AF29 -> 46 | AI29: No PPR | AJ29: =rank(R29,$R$26:$R$37) -> 1 | AK29: =R29/ averageif($A:$A,A29,R:R) -> 1.1362386 | AL29: =S29/averageif($A:$A,A29,S:S) -> 0.9286475 | AM29: =sumifs('WL Matrix 2'!T:T,'WL Matrix 2'!B:B,A29,'WL Matrix 2'!C:C,C29,'WL Matrix 2'!M:M,"Regular Season") -> 97
A30: 2011 | B30: 40544 | C30: Hudspeath | D30: Cutler's Year | E30: =D30&" - "&A30 -> Cutler's Year - 2011 | F30: Drew Brees | G30: Rashard Mendenhall | H30: Roddy White | I30: Tony Gonzalez | J30: Current Owner | L30: 6 | M30: 5 | N30: =M30 -> 5 | O30: 13 | P30: 7 | Q30: =13-P30 -> 6 | R30: 1227 | S30: 1236 | T30: Barcelona | U30: Spain | V30: Barcelona | W30: 25 | Y30: =X30-W30 -> -25 | Z30: =IF(M30=1,1,0) -> 0 | AA30: =if(L30<7,1,0) -> 1 | AC30: =P30*100+R30/4 -> 1006.75 | AD30: =if(L30=1,1,0) -> 0 | AF30: =sumifs('WL Matrix 2'!T:T,'WL Matrix 2'!B:B,A30,'WL Matrix 2'!C:C,C30,'WL Matrix 2'!M:M,"Regular Season") -> 84 | AG30: =11*O30-AF30 -> 59 | AI30: No PPR | AJ30: =rank(R30,$R$26:$R$37) -> 5 | AK30: =R30/ averageif($A:$A,A30,R:R) -> 1.0658752 | AL30: =S30/averageif($A:$A,A30,S:S) -> 1.0530351 | AM30: =sumifs('WL Matrix 2'!T:T,'WL Matrix 2'!B:B,A30,'WL Matrix 2'!C:C,C30,'WL Matrix 2'!M:M,"Regular Season") -> 84
A31: 2011 | B31: 40544 | C31: Shep | D31: Show me Your TDs | E31: =D31&" - "&A31 -> Show me Your TDs - 2011 | F31: Joe Flacco | G31: Reggie Bush | H31: Hakeem Nicks | I31: Jimmy Graham | J31: Current Owner | L31: 5 | M31: 6 | N31: =M31 -> 6 | O31: 13 | P31: 7 | Q31: =13-P31 -> 6 | R31: 1233 | S31: 1195 | T31: Bloomington | U31: Indiana | V31: 47406 | W31: 25 | Y31: =X31-W31 -> -25 | Z31: =IF(M31=1,1,0) -> 0 | AA31: =if(L31<7,1,0) -> 1 | AC31: =P31*100+R31/4 -> 1008.25 | AD31: =if(L31=1,1,0) -> 0 | AF31: =sumifs('WL Matrix 2'!T:T,'WL Matrix 2'!B:B,A31,'WL Matrix 2'!C:C,C31,'WL Matrix 2'!M:M,"Regular Season") -> 85 | AG31: =11*O31-AF31 -> 58 | AI31: No PPR | AJ31: =rank(R31,$R$26:$R$37) -> 3 | AK31: =R31/ averageif($A:$A,A31,R:R) -> 1.0710873 | AL31: =S31/averageif($A:$A,A31,S:S) -> 1.0181044 | AM31: =sumifs('WL Matrix 2'!T:T,'WL Matrix 2'!B:B,A31,'WL Matrix 2'!C:C,C31,'WL Matrix 2'!M:M,"Regular Season") -> 85
A32: 2011 | B32: 40544 | C32: Guckien | D32: The McRB is Back! | E32: =D32&" - "&A32 -> The McRB is Back! - 2011 | F32: Kevin Kolb | G32: LeSean McCoy | H32: Calvin Johnson | I32: Owen Daniels | J32: Retired Owner | L32: 7 | M32: 7 | N32: =M32 -> 7 | O32: 13 | P32: 7 | Q32: =13-P32 -> 6 | R32: 1193 | S32: 1161 | T32: Bloomington | U32: Indiana | V32: 47406 | W32: 25 | Y32: =X32-W32 -> -25 | Z32: =IF(M32=1,1,0) -> 0 | AA32: =if(L32<7,1,0) -> 0 | AC32: =P32*100+R32/4 -> 998.25 | AD32: =if(L32=1,1,0) -> 0 | AF32: =sumifs('WL Matrix 2'!T:T,'WL Matrix 2'!B:B,A32,'WL Matrix 2'!C:C,C32,'WL Matrix 2'!M:M,"Regular Season") -> 74 | AG32: =11*O32-AF32 -> 69 | AI32: No PPR | AJ32: =rank(R32,$R$26:$R$37) -> 6 | AK32: =R32/ averageif($A:$A,A32,R:R) -> 1.0363399 | AL32: =S32/averageif($A:$A,A32,S:S) -> 0.98913738 | AM32: =sumifs('WL Matrix 2'!T:T,'WL Matrix 2'!B:B,A32,'WL Matrix 2'!C:C,C32,'WL Matrix 2'!M:M,"Regular Season") -> 74
A33: 2011 | B33: 40544 | C33: KnardDawg | D33: Tat Five | E33: =D33&" - "&A33 -> Tat Five - 2011 | F33: Tom Brady | G33: Frank Gore | H33: Victor Cruz | I33: Vernon Davis | J33: Current Owner | L33: 8 | M33: 8 | N33: =M33 -> 8 | O33: 13 | P33: 6 | Q33: =13-P33 -> 7 | R33: 1148 | S33: 1146 | T33: Bloomington | U33: Indiana | V33: 47406 | W33: 25 | Y33: =X33-W33 -> -25 | Z33: =IF(M33=1,1,0) -> 0 | AA33: =if(L33<7,1,0) -> 0 | AC33: =P33*100+R33/4 -> 887 | AD33: =if(L33=1,1,0) -> 0 | AF33: =sumifs('WL Matrix 2'!T:T,'WL Matrix 2'!B:B,A33,'WL Matrix 2'!C:C,C33,'WL Matrix 2'!M:M,"Regular Season") -> 72 | AG33: =11*O33-AF33 -> 71 | AI33: No PPR | AJ33: =rank(R33,$R$26:$R$37) -> 8 | AK33: =R33/ averageif($A:$A,A33,R:R) -> 0.99724917 | AL33: =S33/averageif($A:$A,A33,S:S) -> 0.97635783 | AM33: =sumifs('WL Matrix 2'!T:T,'WL Matrix 2'!B:B,A33,'WL Matrix 2'!C:C,C33,'WL Matrix 2'!M:M,"Regular Season") -> 72
A34: 2011 | B34: 40544 | C34: Rooney/Jackson | D34: Clay Rodge | E34: =D34&" - "&A34 -> Clay Rodge - 2011 | F34: Aaron Rodgers | G34: Pierre Thomas | H34: Julio Jones | I34: Jermichael Finley | J34: Current Owner | L34: 9 | M34: 9 | N34: =M34 -> 9 | O34: 13 | P34: 5 | Q34: =13-P34 -> 8 | R34: 1151 | S34: 1194 | T34: Bloomington | U34: Indiana | V34: 47406 | W34: 25 | Y34: =X34-W34 -> -25 | Z34: =IF(M34=1,1,0) -> 0 | AA34: =if(L34<7,1,0) -> 0 | AC34: =P34*100+R34/4 -> 787.75 | AD34: =if(L34=1,1,0) -> 0 | AF34: =sumifs('WL Matrix 2'!T:T,'WL Matrix 2'!B:B,A34,'WL Matrix 2'!C:C,C34,'WL Matrix 2'!M:M,"Regular Season") -> 66 | AG34: =11*O34-AF34 -> 77 | AI34: No PPR | AJ34: =rank(R34,$R$26:$R$37) -> 7 | AK34: =R34/ averageif($A:$A,A34,R:R) -> 0.99985522 | AL34: =S34/averageif($A:$A,A34,S:S) -> 1.0172524 | AM34: =sumifs('WL Matrix 2'!T:T,'WL Matrix 2'!B:B,A34,'WL Matrix 2'!C:C,C34,'WL Matrix 2'!M:M,"Regular Season") -> 66
A35: 2011 | B35: 40544 | C35: Cock | D35: It's My Vick In A Box | E35: =D35&" - "&A35 -> It's My Vick In A Box - 2011 | F35: Ben Roethlisberger | G35: Marshawn Lynch | H35: Nate Burleson | I35: Antonio Gates | J35: Current Owner | L35: 10 | M35: 10 | N35: =M35 -> 10 | O35: 13 | P35: 5 | Q35: =13-P35 -> 8 | R35: 1037 | S35: 1187 | T35: Bloomington | U35: Indiana | V35: 47406 | W35: 25 | Y35: =X35-W35 -> -25 | Z35: =IF(M35=1,1,0) -> 0 | AA35: =if(L35<7,1,0) -> 0 | AC35: =P35*100+R35/4 -> 759.25 | AD35: =if(L35=1,1,0) -> 0 | AF35: =sumifs('WL Matrix 2'!T:T,'WL Matrix 2'!B:B,A35,'WL Matrix 2'!C:C,C35,'WL Matrix 2'!M:M,"Regular Season") -> 50 | AG35: =11*O35-AF35 -> 93 | AI35: No PPR | AJ35: =rank(R35,$R$26:$R$37) -> 11 | AK35: =R35/ averageif($A:$A,A35,R:R) -> 0.90082525 | AL35: =S35/averageif($A:$A,A35,S:S) -> 1.0112886 | AM35: =sumifs('WL Matrix 2'!T:T,'WL Matrix 2'!B:B,A35,'WL Matrix 2'!C:C,C35,'WL Matrix 2'!M:M,"Regular Season") -> 50
A36: 2011 | B36: 40544 | C36: Fellows | D36: Yo Adrian | E36: =D36&" - "&A36 -> Yo Adrian - 2011 | F36: Tim Tebow | G36: Ryan Mathews | H36: Andre Johnson | I36: Brandon Pettigrew | J36: Retired Owner | L36: 11 | M36: 11 | N36: =M36 -> 11 | O36: 13 | P36: 4 | Q36: =13-P36 -> 9 | R36: 1067 | S36: 1188 | T36: Bloomington | U36: Indiana | V36: 47406 | W36: 25 | Y36: =X36-W36 -> -25 | Z36: =IF(M36=1,1,0) -> 0 | AA36: =if(L36<7,1,0) -> 0 | AC36: =P36*100+R36/4 -> 666.75 | AD36: =if(L36=1,1,0) -> 0 | AF36: =sumifs('WL Matrix 2'!T:T,'WL Matrix 2'!B:B,A36,'WL Matrix 2'!C:C,C36,'WL Matrix 2'!M:M,"Regular Season") -> 59 | AG36: =11*O36-AF36 -> 84 | AI36: No PPR | AJ36: =rank(R36,$R$26:$R$37) -> 10 | AK36: =R36/ averageif($A:$A,A36,R:R) -> 0.92688577 | AL36: =S36/averageif($A:$A,A36,S:S) -> 1.0121406 | AM36: =sumifs('WL Matrix 2'!T:T,'WL Matrix 2'!B:B,A36,'WL Matrix 2'!C:C,C36,'WL Matrix 2'!M:M,"Regular Season") -> 59
A37: 2011 | B37: 40544 | C37: Tayski | D37: Team Weis | E37: =D37&" - "&A37 -> Team Weis - 2011 | F37: Matt Schaub | G37: Maurice Jones-Drew | H37: Jeremy Maclin | I37: Aaron Hernandez | J37: Current Owner | L37: 12 | M37: 12 | N37: =M37 -> 12 | O37: 13 | P37: 3 | Q37: =13-P37 -> 10 | R37: 874 | S37: 1161 | T37: Milan | U37: Italy | V37: Milan | W37: 25 | Y37: =X37-W37 -> -25 | Z37: =IF(M37=1,1,0) -> 0 | AA37: =if(L37<7,1,0) -> 0 | AC37: =P37*100+R37/4 -> 518.5 | AD37: =if(L37=1,1,0) -> 0 | AF37: =sumifs('WL Matrix 2'!T:T,'WL Matrix 2'!B:B,A37,'WL Matrix 2'!C:C,C37,'WL Matrix 2'!M:M,"Regular Season") -> 25 | AG37: =11*O37-AF37 -> 118 | AI37: No PPR | AJ37: =rank(R37,$R$26:$R$37) -> 12 | AK37: =R37/ averageif($A:$A,A37,R:R) -> 0.75922977 | AL37: =S37/averageif($A:$A,A37,S:S) -> 0.98913738 | AM37: =sumifs('WL Matrix 2'!T:T,'WL Matrix 2'!B:B,A37,'WL Matrix 2'!C:C,C37,'WL Matrix 2'!M:M,"Regular Season") -> 25
A38: 2012 | B38: 40909 | C38: KnardDawg | D38: For Shurmur | E38: =D38&" - "&A38 -> For Shurmur - 2012 | F38: Matt Ryan | G38: Marshawn Lynch | H38: AJ Green | I38: Aaron Hernandez | J38: Current Owner | L38: 2 | M38: 1 | N38: =M38 -> 1 | O38: 13 | P38: 9 | Q38: =13-P38 -> 4 | R38: 1245 | S38: 1147 | T38: Bloomington | U38: Indiana | V38: 47405 | W38: 50 | X38: 200 | Y38: =X38-W38 -> 150 | Z38: =IF(M38=1,1,0) -> 1 | AA38: =if(L38<7,1,0) -> 1 | AC38: =P38*100+R38/4 -> 1211.25 | AD38: =if(L38=1,1,0) -> 0 | AF38: =sumifs('WL Matrix 2'!T:T,'WL Matrix 2'!B:B,A38,'WL Matrix 2'!C:C,C38,'WL Matrix 2'!M:M,"Regular Season") -> 87 | AG38: =11*O38-AF38 -> 56 | AI38: No PPR | AJ38: =rank(R38,$R$38:$R$49) -> 2 | AK38: =R38/ averageif($A:$A,A38,R:R) -> 1.0454864 | AL38: =S38/averageif($A:$A,A38,S:S) -> 0.96325845 | AM38: =sumifs('WL Matrix 2'!T:T,'WL Matrix 2'!B:B,A38,'WL Matrix 2'!C:C,C38,'WL Matrix 2'!M:M,"Regular Season") -> 87
A39: 2012 | B39: 40909 | C39: Shep | D39: Rexual Feeling | E39: =D39&" - "&A39 -> Rexual Feeling - 2012 | F39: Ben Roethlisberger | G39: DeMarco Murrary | H39: Julio Jones | I39: Owen Daniels | J39: Current Owner | L39: 1 | M39: 2 | N39: =M39 -> 2 | O39: 13 | P39: 10 | Q39: =13-P39 -> 3 | R39: 1271 | S39: 1084 | T39: Bloomington | U39: Indiana | V39: 47408 | W39: 50 | X39: =150+100+100 -> 350 | Y39: =X39-W39 -> 300 | Z39: =IF(M39=1,1,0) -> 0 | AA39: =if(L39<7,1,0) -> 1 | AC39: =P39*100+R39/4 -> 1317.75 | AD39: =if(L39=1,1,0) -> 1 | AE39: 1 | AF39: =sumifs('WL Matrix 2'!T:T,'WL Matrix 2'!B:B,A39,'WL Matrix 2'!C:C,C39,'WL Matrix 2'!M:M,"Regular Season") -> 90 | AG39: =11*O39-AF39 -> 53 | AI39: No PPR | AJ39: =rank(R39,$R$38:$R$49) -> 1 | AK39: =R39/ averageif($A:$A,A39,R:R) -> 1.0673198 | AL39: =S39/averageif($A:$A,A39,S:S) -> 0.91035062 | AM39: =sumifs('WL Matrix 2'!T:T,'WL Matrix 2'!B:B,A39,'WL Matrix 2'!C:C,C39,'WL Matrix 2'!M:M,"Regular Season") -> 90
A40: 2012 | B40: 40909 | C40: Buser | D40: Yes We Camden Cutler | E40: =D40&" - "&A40 -> Yes We Camden Cutler - 2012 | F40: Cam Newton | G40: Doug Martin | H40: Steve Smith | I40: Jason Witten | J40: Current Owner | L40: 3 | M40: 3 | N40: =M40 -> 3 | O40: 13 | P40: 8 | Q40: =13-P40 -> 5 | R40: 1239 | S40: 1228 | T40: Bloomington | U40: Indiana | V40: 47408 | W40: 50 | X40: 50 | Y40: =X40-W40 -> 0 | Z40: =IF(M40=1,1,0) -> 0 | AA40: =if(L40<7,1,0) -> 1 | AC40: =P40*100+R40/4 -> 1109.75 | AD40: =if(L40=1,1,0) -> 0 | AF40: =sumifs('WL Matrix 2'!T:T,'WL Matrix 2'!B:B,A40,'WL Matrix 2'!C:C,C40,'WL Matrix 2'!M:M,"Regular Season") -> 83 | AG40: =11*O40-AF40 -> 60 | AI40: No PPR | AJ40: =rank(R40,$R$38:$R$49) -> 3 | AK40: =R40/ averageif($A:$A,A40,R:R) -> 1.0404479 | AL40: =S40/averageif($A:$A,A40,S:S) -> 1.0312828 | AM40: =sumifs('WL Matrix 2'!T:T,'WL Matrix 2'!B:B,A40,'WL Matrix 2'!C:C,C40,'WL Matrix 2'!M:M,"Regular Season") -> 83
A41: 2012 | B41: 40909 | C41: Fellows | D41: Ken WhizinCnt | E41: =D41&" - "&A41 -> Ken WhizinCnt - 2012 | F41: Eli Manning | G41: Jamaal Charles | H41: Hakeem Nicks | I41: Antonio Gates | J41: Retired Owner | L41: 6 | M41: 4 | N41: =M41 -> 4 | O41: 13 | P41: 7 | Q41: =13-P41 -> 6 | R41: 1130 | S41: 1160 | T41: Bloomington | U41: Indiana | V41: 47408 | W41: 50 | Y41: =X41-W41 -> -50 | Z41: =IF(M41=1,1,0) -> 0 | AA41: =if(L41<7,1,0) -> 1 | AC41: =P41*100+R41/4 -> 982.5 | AD41: =if(L41=1,1,0) -> 0 | AF41: =sumifs('WL Matrix 2'!T:T,'WL Matrix 2'!B:B,A41,'WL Matrix 2'!C:C,C41,'WL Matrix 2'!M:M,"Regular Season") -> 79 | AG41: =11*O41-AF41 -> 64 | AI41: No PPR | AJ41: =rank(R41,$R$38:$R$49) -> 10 | AK41: =R41/ averageif($A:$A,A41,R:R) -> 0.94891533 | AL41: =S41/averageif($A:$A,A41,S:S) -> 0.97417594 | AM41: =sumifs('WL Matrix 2'!T:T,'WL Matrix 2'!B:B,A41,'WL Matrix 2'!C:C,C41,'WL Matrix 2'!M:M,"Regular Season") -> 79
A42: 2012 | B42: 40909 | C42: Rooney/Jackson | D42: BaughwitdaBaugh | E42: =D42&" - "&A42 -> BaughwitdaBaugh - 2012 | F42: Aaron Rodgers | G42: Matt Forte | H42: Victor Cruz | I42: Jermaine Gresham | J42: Current Owner | L42: 5 | M42: 5 | N42: =M42 -> 5 | O42: 13 | P42: 6 | Q42: =13-P42 -> 7 | R42: 1213 | S42: 1161 | T42: Bloomington | U42: Indiana | V42: 47404 | W42: 50 | Y42: =X42-W42 -> -50 | Z42: =IF(M42=1,1,0) -> 0 | AA42: =if(L42<7,1,0) -> 1 | AC42: =P42*100+R42/4 -> 903.25 | AD42: =if(L42=1,1,0) -> 0 | AF42: =sumifs('WL Matrix 2'!T:T,'WL Matrix 2'!B:B,A42,'WL Matrix 2'!C:C,C42,'WL Matrix 2'!M:M,"Regular Season") -> 57 | AG42: =11*O42-AF42 -> 86 | AI42: No PPR | AJ42: =rank(R42,$R$38:$R$49) -> 4 | AK42: =R42/ averageif($A:$A,A42,R:R) -> 1.0186144 | AL42: =S42/averageif($A:$A,A42,S:S) -> 0.97501575 | AM42: =sumifs('WL Matrix 2'!T:T,'WL Matrix 2'!B:B,A42,'WL Matrix 2'!C:C,C42,'WL Matrix 2'!M:M,"Regular Season") -> 57
A43: 2012 | B43: 40909 | C43: Pierson | D43: Jack Del RimJob | E43: =D43&" - "&A43 -> Jack Del RimJob - 2012 | F43: Colin Kaepernick | G43: Arian Foster | H43: Andre Johnson | I43: Vernon Davis | J43: Current Owner | L43: 4 | M43: 6 | N43: =M43 -> 6 | O43: 13 | P43: 8 | Q43: =13-P43 -> 5 | R43: 1207 | S43: 1155 | T43: Bloomington | U43: Indiana | V43: 47406 | W43: 50 | Y43: =X43-W43 -> -50 | Z43: =IF(M43=1,1,0) -> 0 | AA43: =if(L43<7,1,0) -> 1 | AC43: =P43*100+R43/4 -> 1101.75 | AD43: =if(L43=1,1,0) -> 0 | AF43: =sumifs('WL Matrix 2'!T:T,'WL Matrix 2'!B:B,A43,'WL Matrix 2'!C:C,C43,'WL Matrix 2'!M:M,"Regular Season") -> 78 | AG43: =11*O43-AF43 -> 65 | AI43: No PPR | AJ43: =rank(R43,$R$38:$R$49) -> 6 | AK43: =R43/ averageif($A:$A,A43,R:R) -> 1.0135759 | AL43: =S43/averageif($A:$A,A43,S:S) -> 0.96997691 | AM43: =sumifs('WL Matrix 2'!T:T,'WL Matrix 2'!B:B,A43,'WL Matrix 2'!C:C,C43,'WL Matrix 2'!M:M,"Regular Season") -> 78
A44: 2012 | B44: 40909 | C44: Tayski | D44: Bunch of Mularkey | E44: =D44&" - "&A44 -> Bunch of Mularkey - 2012 | F44: Peyton Manning | G44: Michael Turner | H44: Calvin Johnson | I44: Tony Gonzalez | J44: Current Owner | L44: 7 | M44: 7 | N44: =M44 -> 7 | O44: 13 | P44: 6 | Q44: =13-P44 -> 7 | R44: 1182 | S44: 1211 | T44: Bloomington | U44: Indiana | V44: 47406 | W44: 50 | Y44: =X44-W44 -> -50 | Z44: =IF(M44=1,1,0) -> 0 | AA44: =if(L44<7,1,0) -> 0 | AC44: =P44*100+R44/4 -> 895.5 | AD44: =if(L44=1,1,0) -> 0 | AF44: =sumifs('WL Matrix 2'!T:T,'WL Matrix 2'!B:B,A44,'WL Matrix 2'!C:C,C44,'WL Matrix 2'!M:M,"Regular Season") -> 72 | AG44: =11*O44-AF44 -> 71 | AI44: No PPR | AJ44: =rank(R44,$R$38:$R$49) -> 8 | AK44: =R44/ averageif($A:$A,A44,R:R) -> 0.99258223 | AL44: =S44/averageif($A:$A,A44,S:S) -> 1.0170061 | AM44: =sumifs('WL Matrix 2'!T:T,'WL Matrix 2'!B:B,A44,'WL Matrix 2'!C:C,C44,'WL Matrix 2'!M:M,"Regular Season") -> 72
A45: 2012 | B45: 40909 | C45: Cock | D45: All You Need is Lovie | E45: =D45&" - "&A45 -> All You Need is Lovie - 2012 | F45: Tom Brady | G45: Stevan Ridley | H45: Demaryious Thomas | I45: Jimmy Graham | J45: Current Owner | L45: 8 | M45: 8 | N45: =M45 -> 8 | O45: 13 | P45: 5 | Q45: =13-P45 -> 8 | R45: 1209 | S45: 1252 | T45: Bloomington | U45: Indiana | V45: 47404 | W45: 50 | Y45: =X45-W45 -> -50 | Z45: =IF(M45=1,1,0) -> 0 | AA45: =if(L45<7,1,0) -> 0 | AC45: =P45*100+R45/4 -> 802.25 | AD45: =if(L45=1,1,0) -> 0 | AF45: =sumifs('WL Matrix 2'!T:T,'WL Matrix 2'!B:B,A45,'WL Matrix 2'!C:C,C45,'WL Matrix 2'!M:M,"Regular Season") -> 74 | AG45: =11*O45-AF45 -> 69 | AI45: No PPR | AJ45: =rank(R45,$R$38:$R$49) -> 5 | AK45: =R45/ averageif($A:$A,A45,R:R) -> 1.0152554 | AL45: =S45/averageif($A:$A,A45,S:S) -> 1.0514382 | AM45: =sumifs('WL Matrix 2'!T:T,'WL Matrix 2'!B:B,A45,'WL Matrix 2'!C:C,C45,'WL Matrix 2'!M:M,"Regular Season") -> 74
A46: 2012 | B46: 40909 | C46: Riley | D46: Stache of the Walrus | E46: =D46&" - "&A46 -> Stache of the Walrus - 2012 | F46: Phillip Rivers | G46: Adrian Peterson | H46: Dez Bryant | I46: Jermichael Finley | J46: Current Owner | L46: 9 | M46: 9 | N46: =M46 -> 9 | O46: 13 | P46: 5 | Q46: =13-P46 -> 8 | R46: 1194 | S46: 1211 | T46: Bloomington | U46: Indiana | V46: 47408 | W46: 50 | Y46: =X46-W46 -> -50 | Z46: =IF(M46=1,1,0) -> 0 | AA46: =if(L46<7,1,0) -> 0 | AC46: =P46*100+R46/4 -> 798.5 | AD46: =if(L46=1,1,0) -> 0 | AF46: =sumifs('WL Matrix 2'!T:T,'WL Matrix 2'!B:B,A46,'WL Matrix 2'!C:C,C46,'WL Matrix 2'!M:M,"Regular Season") -> 0 | AG46: =11*O46-AF46 -> 143 | AI46: No PPR | AJ46: =rank(R46,$R$38:$R$49) -> 7 | AK46: =R46/ averageif($A:$A,A46,R:R) -> 1.0026592 | AL46: =S46/averageif($A:$A,A46,S:S) -> 1.0170061 | AM46: =sumifs('WL Matrix 2'!T:T,'WL Matrix 2'!B:B,A46,'WL Matrix 2'!C:C,C46,'WL Matrix 2'!M:M,"Regular Season") -> 0
A47: 2012 | B47: 40909 | C47: Salty | D47: Crennelingus | E47: =D47&" - "&A47 -> Crennelingus - 2012 | F47: Drew Brees | G47: Ahmad Bradshaw | H47: Brandon Marshall | I47: Benjamin Watson | J47: Current Owner | L47: 10 | M47: 10 | N47: =M47 -> 10 | O47: 13 | P47: 4 | Q47: =13-P47 -> 9 | R47: 1119 | S47: 1306 | T47: Bloomington | U47: Indiana | V47: 47405 | W47: 50 | Y47: =X47-W47 -> -50 | Z47: =IF(M47=1,1,0) -> 0 | AA47: =if(L47<7,1,0) -> 0 | AC47: =P47*100+R47/4 -> 679.75 | AD47: =if(L47=1,1,0) -> 0 | AF47: =sumifs('WL Matrix 2'!T:T,'WL Matrix 2'!B:B,A47,'WL Matrix 2'!C:C,C47,'WL Matrix 2'!M:M,"Regular Season") -> 57 | AG47: =11*O47-AF47 -> 86 | AI47: No PPR | AJ47: =rank(R47,$R$38:$R$49) -> 11 | AK47: =R47/ averageif($A:$A,A47,R:R) -> 0.9396781 | AL47: =S47/averageif($A:$A,A47,S:S) -> 1.0967877 | AM47: =sumifs('WL Matrix 2'!T:T,'WL Matrix 2'!B:B,A47,'WL Matrix 2'!C:C,C47,'WL Matrix 2'!M:M,"Regular Season") -> 57
A48: 2012 | B48: 40909 | C48: T-How | D48: Good Luck Chuck | E48: =D48&" - "&A48 -> Good Luck Chuck - 2012 | F48: Tony Romo | G48: Ray Rice | H48: Mike Wallace | I48: Rob Gronkowski | J48: Current Owner | L48: 11 | M48: 11 | N48: =M48 -> 11 | O48: 13 | P48: 5 | Q48: =13-P48 -> 8 | R48: 1175 | S48: 1177 | T48: Bloomington | U48: Indiana | V48: 47408 | W48: 50 | Y48: =X48-W48 -> -50 | Z48: =IF(M48=1,1,0) -> 0 | AA48: =if(L48<7,1,0) -> 0 | AC48: =P48*100+R48/4 -> 793.75 | AD48: =if(L48=1,1,0) -> 0 | AF48: =sumifs('WL Matrix 2'!T:T,'WL Matrix 2'!B:B,A48,'WL Matrix 2'!C:C,C48,'WL Matrix 2'!M:M,"Regular Season") -> 60 | AG48: =11*O48-AF48 -> 83 | AI48: No PPR | AJ48: =rank(R48,$R$38:$R$49) -> 9 | AK48: =R48/ averageif($A:$A,A48,R:R) -> 0.98670399 | AL48: =S48/averageif($A:$A,A48,S:S) -> 0.98845266 | AM48: =sumifs('WL Matrix 2'!T:T,'WL Matrix 2'!B:B,A48,'WL Matrix 2'!C:C,C48,'WL Matrix 2'!M:M,"Regular Season") -> 60
A49: 2012 | B49: 40909 | C49: Hudspeath | D49: Cutler's Year | E49: =D49&" - "&A49 -> Cutler's Year - 2012 | F49: Matthew Stafford | G49: Stephen Jackson | H49: Roddy White | I49: Greg Olsen | J49: Current Owner | L49: 12 | M49: 12 | N49: =M49 -> 12 | O49: 13 | P49: 5 | Q49: =13-P49 -> 8 | R49: 1106 | S49: 1197 | T49: Bloomington | U49: Indiana | V49: 47405 | W49: 50 | Y49: =X49-W49 -> -50 | Z49: =IF(M49=1,1,0) -> 0 | AA49: =if(L49<7,1,0) -> 0 | AC49: =P49*100+R49/4 -> 776.5 | AD49: =if(L49=1,1,0) -> 0 | AF49: =sumifs('WL Matrix 2'!T:T,'WL Matrix 2'!B:B,A49,'WL Matrix 2'!C:C,C49,'WL Matrix 2'!M:M,"Regular Season") -> 56 | AG49: =11*O49-AF49 -> 87 | AI49: No PPR | AJ49: =rank(R49,$R$38:$R$49) -> 12 | AK49: =R49/ averageif($A:$A,A49,R:R) -> 0.92876137 | AL49: =S49/averageif($A:$A,A49,S:S) -> 1.0052488 | AM49: =sumifs('WL Matrix 2'!T:T,'WL Matrix 2'!B:B,A49,'WL Matrix 2'!C:C,C49,'WL Matrix 2'!M:M,"Regular Season") -> 56
A50: 2013 | B50: 41275 | C50: Buser | D50: Gag on My Woodhead | E50: =D50&" - "&A50 -> Gag on My Woodhead - 2013 | F50: Phillip Rivers | G50: Jamaal Charles | H50: Torrey Smith | I50: Jimmy Graham | J50: Current Owner | L50: 5 | M50: 1 | N50: =M50 -> 1 | O50: 13 | P50: 7 | Q50: =13-P50 -> 6 | R50: 1270 | S50: 1276 | T50: Chicago | U50: Illinois | V50: 60613 | W50: 50 | X50: 225 | Y50: =X50-W50 -> 175 | Z50: =IF(M50=1,1,0) -> 1 | AA50: =if(L50<7,1,0) -> 1 | AC50: =P50*100+R50/4 -> 1017.5 | AD50: =if(L50=1,1,0) -> 0 | AF50: =sumifs('WL Matrix 2'!T:T,'WL Matrix 2'!B:B,A50,'WL Matrix 2'!C:C,C50,'WL Matrix 2'!M:M,"Regular Season") -> 79 | AG50: =11*O50-AF50 -> 64 | AI50: No PPR | AJ50: =rank(R50,$R$50:$R$61) -> 2 | AK50: =R50/ averageif($A:$A,A50,R:R) -> 1.0524862 | AL50: =S50/averageif($A:$A,A50,S:S) -> 1.0575316 | AM50: =sumifs('WL Matrix 2'!T:T,'WL Matrix 2'!B:B,A50,'WL Matrix 2'!C:C,C50,'WL Matrix 2'!M:M,"Regular Season") -> 79
A51: 2013 | B51: 41275 | C51: Tayski | D51: Bunch of Csonka | E51: =D51&" - "&A51 -> Bunch of Csonka - 2013 | F51: Russell Wilson | G51: Matt Forte | H51: Dez Bryant | I51: Vernon Davis | J51: Current Owner | L51: 2 | M51: 2 | N51: =M51 -> 2 | O51: 13 | P51: 8 | Q51: =13-P51 -> 5 | R51: 1262 | S51: 1226 | T51: Chicago | U51: Illinois | V51: 60613 | W51: 50 | X51: 125 | Y51: =X51-W51 -> 75 | Z51: =IF(M51=1,1,0) -> 0 | AA51: =if(L51<7,1,0) -> 1 | AC51: =P51*100+R51/4 -> 1115.5 | AD51: =if(L51=1,1,0) -> 0 | AF51: =sumifs('WL Matrix 2'!T:T,'WL Matrix 2'!B:B,A51,'WL Matrix 2'!C:C,C51,'WL Matrix 2'!M:M,"Regular Season") -> 81 | AG51: =11*O51-AF51 -> 62 | AI51: No PPR | AJ51: =rank(R51,$R$50:$R$61) -> 4 | AK51: =R51/ averageif($A:$A,A51,R:R) -> 1.0458564 | AL51: =S51/averageif($A:$A,A51,S:S) -> 1.0160923 | AM51: =sumifs('WL Matrix 2'!T:T,'WL Matrix 2'!B:B,A51,'WL Matrix 2'!C:C,C51,'WL Matrix 2'!M:M,"Regular Season") -> 81
A52: 2013 | B52: 41275 | C52: Rooney/Jackson | D52: Sam McGuffie | E52: =D52&" - "&A52 -> Sam McGuffie - 2013 | F52: Peyton Manning | G52: Marshawn Lynch | H52: Demaryious Thomas | I52: Martellus Bennett | J52: Current Owner | L52: 6 | M52: 3 | N52: =M52 -> 3 | O52: 13 | P52: 7 | Q52: =13-P52 -> 6 | R52: 1269 | S52: 1128 | T52: Mequon | U52: Wisconsin | V52: 53097 | W52: 50 | X52: 50 | Y52: =X52-W52 -> 0 | Z52: =IF(M52=1,1,0) -> 0 | AA52: =if(L52<7,1,0) -> 1 | AC52: =P52*100+R52/4 -> 1017.25 | AD52: =if(L52=1,1,0) -> 0 | AF52: =sumifs('WL Matrix 2'!T:T,'WL Matrix 2'!B:B,A52,'WL Matrix 2'!C:C,C52,'WL Matrix 2'!M:M,"Regular Season") -> 82 | AG52: =11*O52-AF52 -> 61 | AI52: No PPR | AJ52: =rank(R52,$R$50:$R$61) -> 3 | AK52: =R52/ averageif($A:$A,A52,R:R) -> 1.0516575 | AL52: =S52/averageif($A:$A,A52,S:S) -> 0.93487119 | AM52: =sumifs('WL Matrix 2'!T:T,'WL Matrix 2'!B:B,A52,'WL Matrix 2'!C:C,C52,'WL Matrix 2'!M:M,"Regular Season") -> 82
A53: 2013 | B53: 41275 | C53: Hudspeath | D53: Cutler's Year | E53: =D53&" - "&A53 -> Cutler's Year - 2013 | F53: Aaron Rodgers | G53: Adrian Peterson | H53: Antonio Brown | I53: Jared Cook | J53: Current Owner | L53: 1 | M53: 4 | N53: =M53 -> 4 | O53: 13 | P53: 9 | Q53: =13-P53 -> 4 | R53: 1220 | S53: 1182 | T53: Long Grove | U53: Illinois | V53: 60049 | W53: 50 | X53: 100 | Y53: =X53-W53 -> 50 | Z53: =IF(M53=1,1,0) -> 0 | AA53: =if(L53<7,1,0) -> 1 | AC53: =P53*100+R53/4 -> 1205 | AD53: =if(L53=1,1,0) -> 1 | AF53: =sumifs('WL Matrix 2'!T:T,'WL Matrix 2'!B:B,A53,'WL Matrix 2'!C:C,C53,'WL Matrix 2'!M:M,"Regular Season") -> 80 | AG53: =11*O53-AF53 -> 63 | AI53: No PPR | AJ53: =rank(R53,$R$50:$R$61) -> 5 | AK53: =R53/ averageif($A:$A,A53,R:R) -> 1.0110497 | AL53: =S53/averageif($A:$A,A53,S:S) -> 0.97962566 | AM53: =sumifs('WL Matrix 2'!T:T,'WL Matrix 2'!B:B,A53,'WL Matrix 2'!C:C,C53,'WL Matrix 2'!M:M,"Regular Season") -> 80
A54: 2013 | B54: 41275 | C54: Riley | D54: High on the Hoge | E54: =D54&" - "&A54 -> High on the Hoge - 2013 | F54: Andrew Luck | G54: Knowshon Moreno | H54: AJ Green | I54: Tony Gonzalez | J54: Current Owner | L54: 4 | M54: 5 | N54: =M54 -> 5 | O54: 13 | P54: 7 | Q54: =13-P54 -> 6 | R54: 1339 | S54: 1180 | T54: Chicago | U54: Illinois | V54: 60613 | W54: 50 | X54: 100 | Y54: =X54-W54 -> 50 | Z54: =IF(M54=1,1,0) -> 0 | AA54: =if(L54<7,1,0) -> 1 | AC54: =P54*100+R54/4 -> 1034.75 | AD54: =if(L54=1,1,0) -> 0 | AE54: 1 | AF54: =sumifs('WL Matrix 2'!T:T,'WL Matrix 2'!B:B,A54,'WL Matrix 2'!C:C,C54,'WL Matrix 2'!M:M,"Regular Season") -> 96 | AG54: =11*O54-AF54 -> 47 | AI54: No PPR | AJ54: =rank(R54,$R$50:$R$61) -> 1 | AK54: =R54/ averageif($A:$A,A54,R:R) -> 1.1096685 | AL54: =S54/averageif($A:$A,A54,S:S) -> 0.97796809 | AM54: =sumifs('WL Matrix 2'!T:T,'WL Matrix 2'!B:B,A54,'WL Matrix 2'!C:C,C54,'WL Matrix 2'!M:M,"Regular Season") -> 96
A55: 2013 | B55: 41275 | C55: Cock | D55: Alstott's Ascot | E55: =D55&" - "&A55 -> Alstott's Ascot - 2013 | F55: Cam Newton | G55: Ryan Mathews | H55: Calvin Johnson | I55: Jason Witten | J55: Current Owner | L55: 3 | M55: 6 | N55: =M55 -> 6 | O55: 13 | P55: 8 | Q55: =13-P55 -> 5 | R55: 1189 | S55: 1154 | T55: Chicago | U55: Illinois | V55: 60614 | W55: 50 | Y55: =X55-W55 -> -50 | Z55: =IF(M55=1,1,0) -> 0 | AA55: =if(L55<7,1,0) -> 1 | AC55: =P55*100+R55/4 -> 1097.25 | AD55: =if(L55=1,1,0) -> 0 | AF55: =sumifs('WL Matrix 2'!T:T,'WL Matrix 2'!B:B,A55,'WL Matrix 2'!C:C,C55,'WL Matrix 2'!M:M,"Regular Season") -> 76 | AG55: =11*O55-AF55 -> 67 | AI55: No PPR | AJ55: =rank(R55,$R$50:$R$61) -> 7 | AK55: =R55/ averageif($A:$A,A55,R:R) -> 0.98535912 | AL55: =S55/averageif($A:$A,A55,S:S) -> 0.95641964 | AM55: =sumifs('WL Matrix 2'!T:T,'WL Matrix 2'!B:B,A55,'WL Matrix 2'!C:C,C55,'WL Matrix 2'!M:M,"Regular Season") -> 76
A56: 2013 | B56: 41275 | C56: Salty | D56: Goings South | E56: =D56&" - "&A56 -> Goings South - 2013 | F56: Tom Brady | G56: Reggie Bush | H56: Victor Cruz | I56: Rob Gronkowski | J56: Current Owner | L56: 7 | M56: 7 | N56: =M56 -> 7 | O56: 13 | P56: 6 | Q56: =13-P56 -> 7 | R56: 1194 | S56: 1156 | T56: Chicago | U56: Illinois | V56: 60614 | W56: 50 | Y56: =X56-W56 -> -50 | Z56: =IF(M56=1,1,0) -> 0 | AA56: =if(L56<7,1,0) -> 0 | AC56: =P56*100+R56/4 -> 898.5 | AD56: =if(L56=1,1,0) -> 0 | AF56: =sumifs('WL Matrix 2'!T:T,'WL Matrix 2'!B:B,A56,'WL Matrix 2'!C:C,C56,'WL Matrix 2'!M:M,"Regular Season") -> 64 | AG56: =11*O56-AF56 -> 79 | AI56: No PPR | AJ56: =rank(R56,$R$50:$R$61) -> 6 | AK56: =R56/ averageif($A:$A,A56,R:R) -> 0.98950276 | AL56: =S56/averageif($A:$A,A56,S:S) -> 0.95807722 | AM56: =sumifs('WL Matrix 2'!T:T,'WL Matrix 2'!B:B,A56,'WL Matrix 2'!C:C,C56,'WL Matrix 2'!M:M,"Regular Season") -> 64
A57: 2013 | B57: 41275 | C57: Fellows | D57: Moose Cock | E57: =D57&" - "&A57 -> Moose Cock - 2013 | F57: Robert Griffin III | G57: Chris Johnson | H57: Josh Gordon | I57: Julius Thomas | J57: Retired Owner | L57: 8 | M57: 8 | N57: =M57 -> 8 | O57: 13 | P57: 6 | Q57: =13-P57 -> 7 | R57: 1168 | S57: 1213 | T57: Indianapolis | U57: Indiana | V57: 46201 | W57: 50 | Y57: =X57-W57 -> -50 | Z57: =IF(M57=1,1,0) -> 0 | AA57: =if(L57<7,1,0) -> 0 | AC57: =P57*100+R57/4 -> 892 | AD57: =if(L57=1,1,0) -> 0 | AF57: =sumifs('WL Matrix 2'!T:T,'WL Matrix 2'!B:B,A57,'WL Matrix 2'!C:C,C57,'WL Matrix 2'!M:M,"Regular Season") -> 63 | AG57: =11*O57-AF57 -> 80 | AI57: No PPR | AJ57: =rank(R57,$R$50:$R$61) -> 8 | AK57: =R57/ averageif($A:$A,A57,R:R) -> 0.9679558 | AL57: =S57/averageif($A:$A,A57,S:S) -> 1.005318 | AM57: =sumifs('WL Matrix 2'!T:T,'WL Matrix 2'!B:B,A57,'WL Matrix 2'!C:C,C57,'WL Matrix 2'!M:M,"Regular Season") -> 63
A58: 2013 | B58: 41275 | C58: T-How | D58: Hope U Get sypHllis | E58: =D58&" - "&A58 -> Hope U Get sypHllis - 2013 | F58: Matthew Stafford | G58: Danny Woodhead | H58: Hakeem Nicks | I58: Greg Olsen | J58: Current Owner | L58: 9 | M58: 9 | N58: =M58 -> 9 | O58: 13 | P58: 6 | Q58: =13-P58 -> 7 | R58: 1156 | S58: 1162 | T58: Chicago | U58: Illinois | V58: 60613 | W58: 50 | Y58: =X58-W58 -> -50 | Z58: =IF(M58=1,1,0) -> 0 | AA58: =if(L58<7,1,0) -> 0 | AC58: =P58*100+R58/4 -> 889 | AD58: =if(L58=1,1,0) -> 0 | AF58: =sumifs('WL Matrix 2'!T:T,'WL Matrix 2'!B:B,A58,'WL Matrix 2'!C:C,C58,'WL Matrix 2'!M:M,"Regular Season") -> 61 | AG58: =11*O58-AF58 -> 82 | AI58: No PPR | AJ58: =rank(R58,$R$50:$R$61) -> 10 | AK58: =R58/ averageif($A:$A,A58,R:R) -> 0.95801105 | AL58: =S58/averageif($A:$A,A58,S:S) -> 0.96304993 | AM58: =sumifs('WL Matrix 2'!T:T,'WL Matrix 2'!B:B,A58,'WL Matrix 2'!C:C,C58,'WL Matrix 2'!M:M,"Regular Season") -> 61
A59: 2013 | B59: 41275 | C59: KnardDawg | D59: Diesel Upheaval | E59: =D59&" - "&A59 -> Diesel Upheaval - 2013 | F59: Drew Brees | G59: Eddie Lacy | H59: Larry Fitzgerald | I59: Coby Fleener | J59: Current Owner | L59: 10 | M59: 10 | N59: =M59 -> 10 | O59: 13 | P59: 6 | Q59: =13-P59 -> 7 | R59: 1106 | S59: 1221 | T59: Chicago | U59: Illinois | V59: 60657 | W59: 50 | Y59: =X59-W59 -> -50 | Z59: =IF(M59=1,1,0) -> 0 | AA59: =if(L59<7,1,0) -> 0 | AC59: =P59*100+R59/4 -> 876.5 | AD59: =if(L59=1,1,0) -> 0 | AF59: =sumifs('WL Matrix 2'!T:T,'WL Matrix 2'!B:B,A59,'WL Matrix 2'!C:C,C59,'WL Matrix 2'!M:M,"Regular Season") -> 52 | AG59: =11*O59-AF59 -> 91 | AI59: No PPR | AJ59: =rank(R59,$R$50:$R$61) -> 12 | AK59: =R59/ averageif($A:$A,A59,R:R) -> 0.91657459 | AL59: =S59/averageif($A:$A,A59,S:S) -> 1.0119483 | AM59: =sumifs('WL Matrix 2'!T:T,'WL Matrix 2'!B:B,A59,'WL Matrix 2'!C:C,C59,'WL Matrix 2'!M:M,"Regular Season") -> 52
A60: 2013 | B60: 41275 | C60: Shep | D60: John David Crow | E60: =D60&" - "&A60 -> John David Crow - 2013 | F60: Colin Kaepernick | G60: DeMarco Murray | H60: Eric Decker | I60: Jordan Cameron | J60: Current Owner | L60: 11 | M60: 11 | N60: =M60 -> 11 | O60: 13 | P60: 4 | Q60: =13-P60 -> 9 | R60: 1158 | S60: 1344 | T60: Indianapolis | U60: Indiana | V60: 46201 | W60: 50 | Y60: =X60-W60 -> -50 | Z60: =IF(M60=1,1,0) -> 0 | AA60: =if(L60<7,1,0) -> 0 | AC60: =P60*100+R60/4 -> 689.5 | AD60: =if(L60=1,1,0) -> 0 | AF60: =sumifs('WL Matrix 2'!T:T,'WL Matrix 2'!B:B,A60,'WL Matrix 2'!C:C,C60,'WL Matrix 2'!M:M,"Regular Season") -> 63 | AG60: =11*O60-AF60 -> 80 | AI60: No PPR | AJ60: =rank(R60,$R$50:$R$61) -> 9 | AK60: =R60/ averageif($A:$A,A60,R:R) -> 0.95966851 | AL60: =S60/averageif($A:$A,A60,S:S) -> 1.1138891 | AM60: =sumifs('WL Matrix 2'!T:T,'WL Matrix 2'!B:B,A60,'WL Matrix 2'!C:C,C60,'WL Matrix 2'!M:M,"Regular Season") -> 63
A61: 2013 | B61: 41275 | C61: Pierson | D61: Mark van LickMyCornHole | E61: =D61&" - "&A61 -> Mark van LickMyCornHole - 2013 | F61: Ben Roethlisberger | G61: Ray Rice | H61: Brandon Marshall | I61: Charles Clay | J61: Current Owner | L61: 12 | M61: 12 | N61: =M61 -> 12 | O61: 13 | P61: 4 | Q61: =13-P61 -> 9 | R61: 1149 | S61: 1237 | T61: Chicago | U61: Illinois | V61: 60613 | W61: 50 | Y61: =X61-W61 -> -50 | Z61: =IF(M61=1,1,0) -> 0 | AA61: =if(L61<7,1,0) -> 0 | AC61: =P61*100+R61/4 -> 687.25 | AD61: =if(L61=1,1,0) -> 0 | AF61: =sumifs('WL Matrix 2'!T:T,'WL Matrix 2'!B:B,A61,'WL Matrix 2'!C:C,C61,'WL Matrix 2'!M:M,"Regular Season") -> 62 | AG61: =11*O61-AF61 -> 81 | AI61: No PPR | AJ61: =rank(R61,$R$50:$R$61) -> 11 | AK61: =R61/ averageif($A:$A,A61,R:R) -> 0.95220994 | AL61: =S61/averageif($A:$A,A61,S:S) -> 1.0252089 | AM61: =sumifs('WL Matrix 2'!T:T,'WL Matrix 2'!B:B,A61,'WL Matrix 2'!C:C,C61,'WL Matrix 2'!M:M,"Regular Season") -> 62
A62: 2014 | B62: 41640 | C62: Buser | D62: Carnival Cruzers | E62: =D62&" - "&A62 -> Carnival Cruzers - 2014 | F62: Tony Romo | G62: Frank Gore | H62: Andre Johnson | I62: Coby Fleener | J62: Current Owner | L62: 11 | M62: 11 | N62: =M62 -> 11 | O62: 13 | P62: 4 | Q62: 9 | R62: 1047 | S62: 1294 | T62: Chicago | U62: Illinois | V62: 60614 | W62: 50 | Y62: =X62-W62 -> -50 | Z62: =IF(M62=1,1,0) -> 0 | AA62: =if(L62<7,1,0) -> 0 | AC62: =P62*100+R62/4 -> 661.75 | AD62: =if(L62=1,1,0) -> 0 | AF62: =sumifs('WL Matrix 2'!T:T,'WL Matrix 2'!B:B,A62,'WL Matrix 2'!C:C,C62,'WL Matrix 2'!M:M,"Regular Season") -> 45 | AG62: =11*O62-AF62 -> 98 | AI62: No PPR | AJ62: =rank(R62,$R$62:$R$73) -> 11 | AK62: =R62/ averageif($A:$A,A62,R:R) -> 0.84886156 | AL62: =S62/averageif($A:$A,A62,S:S) -> 1.0536744 | AM62: =sumifs('WL Matrix 2'!T:T,'WL Matrix 2'!B:B,A62,'WL Matrix 2'!C:C,C62,'WL Matrix 2'!M:M,"Regular Season") -> 45
A63: 2014 | B63: 41640 | C63: Tayski | D63: ForTe Pay | E63: =D63&" - "&A63 -> ForTe Pay - 2014 | F63: Russell Wilson | G63: Matt Forte | H63: Antonio Brown | I63: Vernon Davis | J63: Current Owner | L63: 3 | M63: 3 | N63: =M63 -> 3 | O63: 13 | P63: 9 | Q63: 4 | R63: 1388 | S63: 1221 | T63: Chicago | U63: Illinois | V63: 60614 | W63: 50 | X63: 50 | Y63: =X63-W63 -> 0 | Z63: =IF(M63=1,1,0) -> 0 | AA63: =if(L63<7,1,0) -> 1 | AC63: =P63*100+R63/4 -> 1247 | AD63: =if(L63=1,1,0) -> 0 | AF63: =sumifs('WL Matrix 2'!T:T,'WL Matrix 2'!B:B,A63,'WL Matrix 2'!C:C,C63,'WL Matrix 2'!M:M,"Regular Season") -> 95 | AG63: =11*O63-AF63 -> 48 | AI63: No PPR | AJ63: =rank(R63,$R$62:$R$73) -> 3 | AK63: =R63/ averageif($A:$A,A63,R:R) -> 1.1253294 | AL63: =S63/averageif($A:$A,A63,S:S) -> 0.9942322 | AM63: =sumifs('WL Matrix 2'!T:T,'WL Matrix 2'!B:B,A63,'WL Matrix 2'!C:C,C63,'WL Matrix 2'!M:M,"Regular Season") -> 95
A64: 2014 | B64: 41640 | C64: Rooney/Jackson | D64: Justin Tucker Must Die | E64: =D64&" - "&A64 -> Justin Tucker Must Die - 2014 | F64: Aaron Rodgers | G64: LeSean McCoy | H64: Eric Decker | I64: Zach Ertz | J64: Current Owner | L64: 8 | M64: 8 | N64: =M64 -> 8 | O64: 13 | P64: 5 | Q64: 8 | R64: 1153 | S64: 1244 | T64: Chicago | U64: Illinois | V64: 60647 | W64: 50 | Y64: =X64-W64 -> -50 | Z64: =IF(M64=1,1,0) -> 0 | AA64: =if(L64<7,1,0) -> 0 | AC64: =P64*100+R64/4 -> 788.25 | AD64: =if(L64=1,1,0) -> 0 | AF64: =sumifs('WL Matrix 2'!T:T,'WL Matrix 2'!B:B,A64,'WL Matrix 2'!C:C,C64,'WL Matrix 2'!M:M,"Regular Season") -> 52 | AG64: =11*O64-AF64 -> 91 | AI64: No PPR | AJ64: =rank(R64,$R$62:$R$73) -> 8 | AK64: =R64/ averageif($A:$A,A64,R:R) -> 0.9348017 | AL64: =S64/averageif($A:$A,A64,S:S) -> 1.0129606 | AM64: =sumifs('WL Matrix 2'!T:T,'WL Matrix 2'!B:B,A64,'WL Matrix 2'!C:C,C64,'WL Matrix 2'!M:M,"Regular Season") -> 52
A65: 2014 | B65: 41640 | C65: Hudspeath | D65: Cutler's Year | E65: =D65&" - "&A65 -> Cutler's Year - 2014 | F65: Peyton Manning | G65: Lamar Miller | H65: Mike Evans | I65: Jimmy Graham | J65: Current Owner | L65: 1 | M65: 4 | N65: =M65 -> 4 | O65: 13 | P65: 11 | Q65: 2 | R65: 1392 | S65: 1278 | T65: Chicago | U65: Illinois | V65: 60618 | W65: 50 | X65: 100 | Y65: =X65-W65 -> 50 | Z65: =IF(M65=1,1,0) -> 0 | AA65: =if(L65<7,1,0) -> 1 | AC65: =P65*100+R65/4 -> 1448 | AD65: =if(L65=1,1,0) -> 1 | AF65: =sumifs('WL Matrix 2'!T:T,'WL Matrix 2'!B:B,A65,'WL Matrix 2'!C:C,C65,'WL Matrix 2'!M:M,"Regular Season") -> 103 | AG65: =11*O65-AF65 -> 40 | AI65: No PPR | AJ65: =rank(R65,$R$62:$R$73) -> 2 | AK65: =R65/ averageif($A:$A,A65,R:R) -> 1.1285724 | AL65: =S65/averageif($A:$A,A65,S:S) -> 1.040646 | AM65: =sumifs('WL Matrix 2'!T:T,'WL Matrix 2'!B:B,A65,'WL Matrix 2'!C:C,C65,'WL Matrix 2'!M:M,"Regular Season") -> 103
A66: 2014 | B66: 41640 | C66: Riley | D66: Praters Gonna Prate | E66: =D66&" - "&A66 -> Praters Gonna Prate - 2014 | F66: Andrew Luck | G66: Marshawn Lynch | H66: TY Hilton | I66: Antonio Gates | J66: Current Owner | L66: 2 | M66: 1 | N66: =M66 -> 1 | O66: 13 | P66: 10 | Q66: 3 | R66: 1414 | S66: 1153 | T66: Chicago | U66: Illinois | V66: 60614 | W66: 50 | X66: 325 | Y66: =X66-W66 -> 275 | Z66: =IF(M66=1,1,0) -> 1 | AA66: =if(L66<7,1,0) -> 1 | AC66: =P66*100+R66/4 -> 1353.5 | AD66: =if(L66=1,1,0) -> 0 | AE66: 1 | AF66: =sumifs('WL Matrix 2'!T:T,'WL Matrix 2'!B:B,A66,'WL Matrix 2'!C:C,C66,'WL Matrix 2'!M:M,"Regular Season") -> 101 | AG66: =11*O66-AF66 -> 42 | AI66: No PPR | AJ66: =rank(R66,$R$62:$R$73) -> 1 | AK66: =R66/ averageif($A:$A,A66,R:R) -> 1.146409 | AL66: =S66/averageif($A:$A,A66,S:S) -> 0.93886137 | AM66: =sumifs('WL Matrix 2'!T:T,'WL Matrix 2'!B:B,A66,'WL Matrix 2'!C:C,C66,'WL Matrix 2'!M:M,"Regular Season") -> 101
A67: 2014 | B67: 41640 | C67: Cock | D67: Jc Livin | E67: =D67&" - "&A67 -> Jc Livin - 2014 | F67: Ben Roethlisberger | G67: Jamaal Charles | H67: Brandon Marshall | I67: Larry Donnell | J67: Current Owner | L67: 9 | M67: 9 | N67: =M67 -> 9 | O67: 13 | P67: 4 | Q67: 9 | R67: 1099 | S67: 1325 | T67: Chicago | U67: Illinois | V67: 60647 | W67: 50 | Y67: =X67-W67 -> -50 | Z67: =IF(M67=1,1,0) -> 0 | AA67: =if(L67<7,1,0) -> 0 | AC67: =P67*100+R67/4 -> 674.75 | AD67: =if(L67=1,1,0) -> 0 | AF67: =sumifs('WL Matrix 2'!T:T,'WL Matrix 2'!B:B,A67,'WL Matrix 2'!C:C,C67,'WL Matrix 2'!M:M,"Regular Season") -> 47 | AG67: =11*O67-AF67 -> 96 | AI67: No PPR | AJ67: =rank(R67,$R$62:$R$73) -> 9 | AK67: =R67/ averageif($A:$A,A67,R:R) -> 0.89102088 | AL67: =S67/averageif($A:$A,A67,S:S) -> 1.078917 | AM67: =sumifs('WL Matrix 2'!T:T,'WL Matrix 2'!B:B,A67,'WL Matrix 2'!C:C,C67,'WL Matrix 2'!M:M,"Regular Season") -> 47
A68: 2014 | B68: 41640 | C68: Salty | D68: Weekend at Bernard's | E68: =D68&" - "&A68 -> Weekend at Bernard's - 2014 | F68: Drew Brees | G68: Giovani Bernard | H68: Alshon Jeffery | I68: Julius Thomas | J68: Current Owner | L68: 7 | M68: 7 | N68: =M68 -> 7 | O68: 13 | P68: 6 | Q68: 7 | R68: 1281 | S68: 1126 | T68: Chicago | U68: Illinois | V68: 60647 | W68: 50 | Y68: =X68-W68 -> -50 | Z68: =IF(M68=1,1,0) -> 0 | AA68: =if(L68<7,1,0) -> 0 | AC68: =P68*100+R68/4 -> 920.25 | AD68: =if(L68=1,1,0) -> 0 | AF68: =sumifs('WL Matrix 2'!T:T,'WL Matrix 2'!B:B,A68,'WL Matrix 2'!C:C,C68,'WL Matrix 2'!M:M,"Regular Season") -> 78 | AG68: =11*O68-AF68 -> 65 | AI68: No PPR | AJ68: =rank(R68,$R$62:$R$73) -> 6 | AK68: =R68/ averageif($A:$A,A68,R:R) -> 1.0385785 | AL68: =S68/averageif($A:$A,A68,S:S) -> 0.91687589 | AM68: =sumifs('WL Matrix 2'!T:T,'WL Matrix 2'!B:B,A68,'WL Matrix 2'!C:C,C68,'WL Matrix 2'!M:M,"Regular Season") -> 78
A69: 2014 | B69: 41640 | C69: Fellows | D69: Deztiny's Child | E69: =D69&" - "&A69 -> Deztiny's Child - 2014 | F69: Matt Ryan | G69: Mark Ingram | H69: Demaryious Thomas | I69: Martellus Bennett | J69: Retired Owner | L69: 4 | M69: 5 | N69: =M69 -> 5 | O69: 13 | P69: 8 | Q69: 5 | R69: 1353 | S69: 1237 | T69: Indianapolis | U69: Indiana | V69: 46201 | W69: 50 | Y69: =X69-W69 -> -50 | Z69: =IF(M69=1,1,0) -> 0 | AA69: =if(L69<7,1,0) -> 1 | AC69: =P69*100+R69/4 -> 1138.25 | AD69: =if(L69=1,1,0) -> 0 | AF69: =sumifs('WL Matrix 2'!T:T,'WL Matrix 2'!B:B,A69,'WL Matrix 2'!C:C,C69,'WL Matrix 2'!M:M,"Regular Season") -> 94 | AG69: =11*O69-AF69 -> 49 | AI69: No PPR | AJ69: =rank(R69,$R$62:$R$73) -> 4 | AK69: =R69/ averageif($A:$A,A69,R:R) -> 1.0969529 | AL69: =S69/averageif($A:$A,A69,S:S) -> 1.0072606 | AM69: =sumifs('WL Matrix 2'!T:T,'WL Matrix 2'!B:B,A69,'WL Matrix 2'!C:C,C69,'WL Matrix 2'!M:M,"Regular Season") -> 94
A70: 2014 | B70: 41640 | C70: T-How | D70: Games with Gerhart | E70: =D70&" - "&A70 -> Games with Gerhart - 2014 | F70: Ryan Tannehill | G70: Fred Jackson | H70: Calvin Johnson | I70: Jason Witten | J70: Current Owner | L70: 12 | M70: 12 | N70: =M70 -> 12 | O70: 13 | P70: 2 | Q70: 11 | R70: 1004 | S70: 1227 | T70: Chicago | U70: Illinois | V70: 60614 | W70: 50 | Y70: =X70-W70 -> -50 | Z70: =IF(M70=1,1,0) -> 0 | AA70: =if(L70<7,1,0) -> 0 | AC70: =P70*100+R70/4 -> 451 | AD70: =if(L70=1,1,0) -> 0 | AF70: =sumifs('WL Matrix 2'!T:T,'WL Matrix 2'!B:B,A70,'WL Matrix 2'!C:C,C70,'WL Matrix 2'!M:M,"Regular Season") -> 36 | AG70: =11*O70-AF70 -> 107 | AI70: No PPR | AJ70: =rank(R70,$R$62:$R$73) -> 12 | AK70: =R70/ averageif($A:$A,A70,R:R) -> 0.81399905 | AL70: =S70/averageif($A:$A,A70,S:S) -> 0.99911787 | AM70: =sumifs('WL Matrix 2'!T:T,'WL Matrix 2'!B:B,A70,'WL Matrix 2'!C:C,C70,'WL Matrix 2'!M:M,"Regular Season") -> 36
A71: 2014 | B71: 41640 | C71: KnardDawg | D71: Pryor Convictions | E71: =D71&" - "&A71 -> Pryor Convictions - 2014 | F71: Matthew Stafford | G71: Ben Tate | H71: AJ Green | I71: Rob Gronkowski | J71: Current Owner | L71: 10 | M71: 10 | N71: =M71 -> 10 | O71: 13 | P71: 4 | Q71: 9 | R71: 1087 | S71: 1217 | T71: Chicago | U71: Illinois | V71: 60614 | W71: 50 | Y71: =X71-W71 -> -50 | Z71: =IF(M71=1,1,0) -> 0 | AA71: =if(L71<7,1,0) -> 0 | AC71: =P71*100+R71/4 -> 671.75 | AD71: =if(L71=1,1,0) -> 0 | AF71: =sumifs('WL Matrix 2'!T:T,'WL Matrix 2'!B:B,A71,'WL Matrix 2'!C:C,C71,'WL Matrix 2'!M:M,"Regular Season") -> 43 | AG71: =11*O71-AF71 -> 100 | AI71: No PPR | AJ71: =rank(R71,$R$62:$R$73) -> 10 | AK71: =R71/ averageif($A:$A,A71,R:R) -> 0.8812918 | AL71: =S71/averageif($A:$A,A71,S:S) -> 0.9909751 | AM71: =sumifs('WL Matrix 2'!T:T,'WL Matrix 2'!B:B,A71,'WL Matrix 2'!C:C,C71,'WL Matrix 2'!M:M,"Regular Season") -> 43
A72: 2014 | B72: 41640 | C72: Shep | D72: Tom and the High Fives | E72: =D72&" - "&A72 -> Tom and the High Fives - 2014 | F72: Tom Brady | G72: Arian Foster | H72: Julio Jones | I72: Jordan Reed | J72: Current Owner | L72: 6 | M72: 6 | N72: =M72 -> 6 | O72: 13 | P72: 7 | Q72: 6 | R72: 1245 | S72: 1178 | T72: Fishers | U72: Indiana | V72: 46037 | W72: 50 | Y72: =X72-W72 -> -50 | Z72: =IF(M72=1,1,0) -> 0 | AA72: =if(L72<7,1,0) -> 1 | AC72: =P72*100+R72/4 -> 1011.25 | AD72: =if(L72=1,1,0) -> 0 | AF72: =sumifs('WL Matrix 2'!T:T,'WL Matrix 2'!B:B,A72,'WL Matrix 2'!C:C,C72,'WL Matrix 2'!M:M,"Regular Season") -> 76 | AG72: =11*O72-AF72 -> 67 | AI72: No PPR | AJ72: =rank(R72,$R$62:$R$73) -> 7 | AK72: =R72/ averageif($A:$A,A72,R:R) -> 1.0093913 | AL72: =S72/averageif($A:$A,A72,S:S) -> 0.95921829 | AM72: =sumifs('WL Matrix 2'!T:T,'WL Matrix 2'!B:B,A72,'WL Matrix 2'!C:C,C72,'WL Matrix 2'!M:M,"Regular Season") -> 76
A73: 2014 | B73: 41640 | C73: Pierson | D73: My Girl Chloe Trestman | E73: =D73&" - "&A73 -> My Girl Chloe Trestman - 2014 | F73: Philip Rivers | G73: DeMarco Murray | H73: Jordy Nelson | I73: Greg Olsen | J73: Current Owner | L73: 5 | M73: 2 | N73: =M73 -> 2 | O73: 13 | P73: 8 | Q73: 5 | R73: 1338 | S73: 1237 | T73: Arlington Heights | U73: Illinois | V73: 60004 | W73: 50 | X73: 125 | Y73: =X73-W73 -> 75 | Z73: =IF(M73=1,1,0) -> 0 | AA73: =if(L73<7,1,0) -> 1 | AC73: =P73*100+R73/4 -> 1134.5 | AD73: =if(L73=1,1,0) -> 0 | AF73: =sumifs('WL Matrix 2'!T:T,'WL Matrix 2'!B:B,A73,'WL Matrix 2'!C:C,C73,'WL Matrix 2'!M:M,"Regular Season") -> 89 | AG73: =11*O73-AF73 -> 54 | AI73: No PPR | AJ73: =rank(R73,$R$62:$R$73) -> 5 | AK73: =R73/ averageif($A:$A,A73,R:R) -> 1.0847916 | AL73: =S73/averageif($A:$A,A73,S:S) -> 1.0072606 | AM73: =sumifs('WL Matrix 2'!T:T,'WL Matrix 2'!B:B,A73,'WL Matrix 2'!C:C,C73,'WL Matrix 2'!M:M,"Regular Season") -> 89
A74: 2015 | B74: 42005 | C74: Buser | D74: Hyde and Seek | E74: =D74&" - "&A74 -> Hyde and Seek - 2015 | F74: Eli Manning | G74: Carlos Hyde | H74: DeAndre Hopkins | I74: Rob Gronkowski | J74: Current Owner | L74: 3 | M74: 5 | N74: =M74 -> 5 | O74: 13 | P74: 8 | Q74: 5 | R74: 1221 | S74: 1125.8 | T74: Chicago | U74: Illinois | V74: 60614 | W74: 69 | Y74: =X74-W74 -> -69 | Z74: =IF(M74=1,1,0) -> 0 | AA74: =if(L74<7,1,0) -> 1 | AC74: =P74*100+R74/4 -> 1105.25 | AD74: =if(L74=1,1,0) -> 0 | AF74: =sumifs('WL Matrix 2'!T:T,'WL Matrix 2'!B:B,A74,'WL Matrix 2'!C:C,C74,'WL Matrix 2'!M:M,"Regular Season") -> 75 | AG74: =11*O74-AF74 -> 68 | AI74: No PPR | AJ74: =rank(R74,$R$74:$R$85) -> 5 | AK74: =R74/ averageif($A:$A,A74,R:R) -> 1.014822 | AL74: =S74/averageif($A:$A,A74,S:S) -> 0.93569098 | AM74: =sumifs('WL Matrix 2'!T:T,'WL Matrix 2'!B:B,A74,'WL Matrix 2'!C:C,C74,'WL Matrix 2'!M:M,"Regular Season") -> 75
A75: 2015 | B75: 42005 | C75: Tayski | D75: Late Nite LeSean | E75: =D75&" - "&A75 -> Late Nite LeSean - 2015 | F75: Philip Rivers | G75: LeSean McCoy | H75: Julio Jones | I75: Jordan Reed | J75: Current Owner | L75: 8 | M75: 8 | N75: =M75 -> 8 | O75: 13 | P75: 6 | Q75: 7 | R75: 1313 | S75: 1299 | T75: Nashville | U75: Tennessee | V75: 37115 | W75: 69 | Y75: =X75-W75 -> -69 | Z75: =IF(M75=1,1,0) -> 0 | AA75: =if(L75<7,1,0) -> 0 | AC75: =P75*100+R75/4 -> 928.25 | AD75: =if(L75=1,1,0) -> 0 | AF75: =sumifs('WL Matrix 2'!T:T,'WL Matrix 2'!B:B,A75,'WL Matrix 2'!C:C,C75,'WL Matrix 2'!M:M,"Regular Season") -> 87 | AG75: =11*O75-AF75 -> 56 | AI75: No PPR | AJ75: =rank(R75,$R$74:$R$85) -> 2 | AK75: =R75/ averageif($A:$A,A75,R:R) -> 1.0912869 | AL75: =S75/averageif($A:$A,A75,S:S) -> 1.0796434 | AM75: =sumifs('WL Matrix 2'!T:T,'WL Matrix 2'!B:B,A75,'WL Matrix 2'!C:C,C75,'WL Matrix 2'!M:M,"Regular Season") -> 87
A76: 2015 | B76: 42005 | C76: Rooney/Jackson | D76: Super Bowl 4 Stafford's Baby | E76: =D76&" - "&A76 -> Super Bowl 4 Stafford's Baby - 2015 | F76: Matthew Stafford | G76: Todd Gurley | H76: Larry Fitzgerald | I76: Richard Rodgers | J76: Current Owner | L76: 11 | M76: 11 | N76: =M76 -> 11 | O76: 13 | P76: 4 | Q76: 9 | R76: 1003 | S76: 1210 | T76: Chicago | U76: Illinois | V76: 60647 | W76: 69 | Y76: =X76-W76 -> -69 | Z76: =IF(M76=1,1,0) -> 0 | AA76: =if(L76<7,1,0) -> 0 | AC76: =P76*100+R76/4 -> 650.75 | AD76: =if(L76=1,1,0) -> 0 | AF76: =sumifs('WL Matrix 2'!T:T,'WL Matrix 2'!B:B,A76,'WL Matrix 2'!C:C,C76,'WL Matrix 2'!M:M,"Regular Season") -> 34 | AG76: =11*O76-AF76 -> 109 | AI76: No PPR | AJ76: =rank(R76,$R$74:$R$85) -> 12 | AK76: =R76/ averageif($A:$A,A76,R:R) -> 0.83363347 | AL76: =S76/averageif($A:$A,A76,S:S) -> 1.0056725 | AM76: =sumifs('WL Matrix 2'!T:T,'WL Matrix 2'!B:B,A76,'WL Matrix 2'!C:C,C76,'WL Matrix 2'!M:M,"Regular Season") -> 34
A77: 2015 | B77: 42005 | C77: Hudspeath | D77: Cutler's Year | E77: =D77&" - "&A77 -> Cutler's Year - 2015 | F77: Drew Brees | G77: Matt Forte | H77: Randall Cobb | I77: Jimmy Graham | J77: Current Owner | L77: 4 | M77: 2 | N77: =M77 -> 2 | O77: 13 | P77: 8 | Q77: 5 | R77: 1190 | S77: 1160 | T77: Chicago | U77: Illinois | V77: 60618 | W77: 69 | X77: =170 -> 170 | Y77: =X77-W77 -> 101 | Z77: =IF(M77=1,1,0) -> 0 | AA77: =if(L77<7,1,0) -> 1 | AC77: =P77*100+R77/4 -> 1097.5 | AD77: =if(L77=1,1,0) -> 0 | AF77: =sumifs('WL Matrix 2'!T:T,'WL Matrix 2'!B:B,A77,'WL Matrix 2'!C:C,C77,'WL Matrix 2'!M:M,"Regular Season") -> 70 | AG77: =11*O77-AF77 -> 73 | AI77: No PPR | AJ77: =rank(R77,$R$74:$R$85) -> 7 | AK77: =R77/ averageif($A:$A,A77,R:R) -> 0.98905666 | AL77: =S77/averageif($A:$A,A77,S:S) -> 0.96411578 | AM77: =sumifs('WL Matrix 2'!T:T,'WL Matrix 2'!B:B,A77,'WL Matrix 2'!C:C,C77,'WL Matrix 2'!M:M,"Regular Season") -> 70
A78: 2015 | B78: 42005 | C78: Riley | D78: Prater Tots | E78: =D78&" - "&A78 -> Prater Tots - 2015 | F78: Andrew Luck | G78: Devonta Freeman | H78: TY Hilton | I78: Antonio Gates | J78: Current Owner | L78: 10 | M78: 10 | N78: =M78 -> 10 | O78: 13 | P78: 5 | Q78: 8 | R78: 1208 | S78: 1265 | T78: Chicago | U78: Illinois | V78: 60610 | W78: 69 | Y78: =X78-W78 -> -69 | Z78: =IF(M78=1,1,0) -> 0 | AA78: =if(L78<7,1,0) -> 0 | AC78: =P78*100+R78/4 -> 802 | AD78: =if(L78=1,1,0) -> 0 | AF78: =sumifs('WL Matrix 2'!T:T,'WL Matrix 2'!B:B,A78,'WL Matrix 2'!C:C,C78,'WL Matrix 2'!M:M,"Regular Season") -> 71 | AG78: =11*O78-AF78 -> 72 | AI78: No PPR | AJ78: =rank(R78,$R$74:$R$85) -> 6 | AK78: =R78/ averageif($A:$A,A78,R:R) -> 1.0040172 | AL78: =S78/averageif($A:$A,A78,S:S) -> 1.0513849 | AM78: =sumifs('WL Matrix 2'!T:T,'WL Matrix 2'!B:B,A78,'WL Matrix 2'!C:C,C78,'WL Matrix 2'!M:M,"Regular Season") -> 71
A79: 2015 | B79: 42005 | C79: Cock | D79: The Chicago White Cochs | E79: =D79&" - "&A79 -> The Chicago White Cochs - 2015 | F79: Russell Wilson | G79: Mark Ingram | H79: Allen Hurns | I79: Eric Ebron | J79: Current Owner | L79: 12 | M79: 12 | N79: =M79 -> 12 | O79: 13 | P79: 3 | Q79: 10 | R79: 1108 | S79: 1206 | T79: Chicago | U79: Illinois | V79: 60614 | W79: 69 | Y79: =X79-W79 -> -69 | Z79: =IF(M79=1,1,0) -> 0 | AA79: =if(L79<7,1,0) -> 0 | AC79: =P79*100+R79/4 -> 577 | AD79: =if(L79=1,1,0) -> 0 | AF79: =sumifs('WL Matrix 2'!T:T,'WL Matrix 2'!B:B,A79,'WL Matrix 2'!C:C,C79,'WL Matrix 2'!M:M,"Regular Season") -> 56 | AG79: =11*O79-AF79 -> 87 | AI79: No PPR | AJ79: =rank(R79,$R$74:$R$85) -> 11 | AK79: =R79/ averageif($A:$A,A79,R:R) -> 0.92090317 | AL79: =S79/averageif($A:$A,A79,S:S) -> 1.002348 | AM79: =sumifs('WL Matrix 2'!T:T,'WL Matrix 2'!B:B,A79,'WL Matrix 2'!C:C,C79,'WL Matrix 2'!M:M,"Regular Season") -> 56
A80: 2015 | B80: 42005 | C80: Salty | D80: Can't KelCe Me | E80: =D80&" - "&A80 -> Can't KelCe Me - 2015 | F80: Aaron Rodgers | G80: Adrian Peterson | H80: Brandon Marshall | I80: Travis Kelce | J80: Current Owner | L80: 2 | M80: 3 | N80: =M80 -> 3 | O80: 13 | P80: 8 | Q80: 5 | R80: 1382 | S80: 1225.3 | T80: Los Angeles | U80: California | V80: 90210 | W80: 69 | X80: =138+69 -> 207 | Y80: =X80-W80 -> 138 | Z80: =IF(M80=1,1,0) -> 0 | AA80: =if(L80<7,1,0) -> 1 | AC80: =P80*100+R80/4 -> 1145.5 | AD80: =if(L80=1,1,0) -> 0 | AE80: 1 | AF80: =sumifs('WL Matrix 2'!T:T,'WL Matrix 2'!B:B,A80,'WL Matrix 2'!C:C,C80,'WL Matrix 2'!M:M,"Regular Season") -> 98 | AG80: =11*O80-AF80 -> 45 | AI80: No PPR | AJ80: =rank(R80,$R$74:$R$85) -> 1 | AK80: =R80/ averageif($A:$A,A80,R:R) -> 1.1486355 | AL80: =S80/averageif($A:$A,A80,S:S) -> 1.0183888 | AM80: =sumifs('WL Matrix 2'!T:T,'WL Matrix 2'!B:B,A80,'WL Matrix 2'!C:C,C80,'WL Matrix 2'!M:M,"Regular Season") -> 98
A81: 2015 | B81: 42005 | C81: Fellows | D81: Bang Bang Chickn n Shrimp | E81: =D81&" - "&A81 -> Bang Bang Chickn n Shrimp - 2015 | F81: Carson Palmer | G81: Lamar Miller | H81: Calvin Johnson | I81: Delanie Walker | J81: Retired Owner | L81: 5 | M81: 6 | N81: =M81 -> 6 | O81: 13 | P81: 7 | Q81: 6 | R81: 1235 | S81: 1245 | T81: Austin | U81: Texas | V81: 73301 | W81: 69 | Y81: =X81-W81 -> -69 | Z81: =IF(M81=1,1,0) -> 0 | AA81: =if(L81<7,1,0) -> 1 | AC81: =P81*100+R81/4 -> 1008.75 | AD81: =if(L81=1,1,0) -> 0 | AF81: =sumifs('WL Matrix 2'!T:T,'WL Matrix 2'!B:B,A81,'WL Matrix 2'!C:C,C81,'WL Matrix 2'!M:M,"Regular Season") -> 80 | AG81: =11*O81-AF81 -> 63 | AI81: No PPR | AJ81: =rank(R81,$R$74:$R$85) -> 4 | AK81: =R81/ averageif($A:$A,A81,R:R) -> 1.026458 | AL81: =S81/averageif($A:$A,A81,S:S) -> 1.0347622 | AM81: =sumifs('WL Matrix 2'!T:T,'WL Matrix 2'!B:B,A81,'WL Matrix 2'!C:C,C81,'WL Matrix 2'!M:M,"Regular Season") -> 80
A82: 2015 | B82: 42005 | C82: T-How | D82: Umphrey's McPhee | E82: =D82&" - "&A82 -> Umphrey's McPhee - 2015 | F82: Tom Brady | G82: Latavius Murray | H82: Antonio Brown | I82: Jason Witten | J82: Current Owner | L82: 1 | M82: 4 | N82: =M82 -> 4 | O82: 13 | P82: 9 | Q82: 4 | R82: 1251 | S82: 1155 | T82: Chicago | U82: Illinois | V82: 60610 | W82: 69 | X82: 138 | Y82: =X82-W82 -> 69 | Z82: =IF(M82=1,1,0) -> 0 | AA82: =if(L82<7,1,0) -> 1 | AC82: =P82*100+R82/4 -> 1212.75 | AD82: =if(L82=1,1,0) -> 1 | AF82: =sumifs('WL Matrix 2'!T:T,'WL Matrix 2'!B:B,A82,'WL Matrix 2'!C:C,C82,'WL Matrix 2'!M:M,"Regular Season") -> 72 | AG82: =11*O82-AF82 -> 71 | AI82: No PPR | AJ82: =rank(R82,$R$74:$R$85) -> 3 | AK82: =R82/ averageif($A:$A,A82,R:R) -> 1.0397562 | AL82: =S82/averageif($A:$A,A82,S:S) -> 0.95996011 | AM82: =sumifs('WL Matrix 2'!T:T,'WL Matrix 2'!B:B,A82,'WL Matrix 2'!C:C,C82,'WL Matrix 2'!M:M,"Regular Season") -> 72
A83: 2015 | B83: 42005 | C83: KnardDawg | D83: All AmeriKins | E83: =D83&" - "&A83 -> All AmeriKins - 2015 | F83: Jay Cutler | G83: TJ Yeldon | H83: Odell Beckham Jr. | I83: Tyler Eifert | J83: Current Owner | L83: 7 | M83: 7 | N83: =M83 -> 7 | O83: 13 | P83: 7 | Q83: 6 | R83: 1160 | S83: 1103 | T83: Chicago | U83: Illinois | V83: 60657 | W83: 69 | Y83: =X83-W83 -> -69 | Z83: =IF(M83=1,1,0) -> 0 | AA83: =if(L83<7,1,0) -> 0 | AC83: =P83*100+R83/4 -> 990 | AD83: =if(L83=1,1,0) -> 0 | AF83: =sumifs('WL Matrix 2'!T:T,'WL Matrix 2'!B:B,A83,'WL Matrix 2'!C:C,C83,'WL Matrix 2'!M:M,"Regular Season") -> 68 | AG83: =11*O83-AF83 -> 75 | AI83: No PPR | AJ83: =rank(R83,$R$74:$R$85) -> 10 | AK83: =R83/ averageif($A:$A,A83,R:R) -> 0.96412245 | AL83: =S83/averageif($A:$A,A83,S:S) -> 0.91674112 | AM83: =sumifs('WL Matrix 2'!T:T,'WL Matrix 2'!B:B,A83,'WL Matrix 2'!C:C,C83,'WL Matrix 2'!M:M,"Regular Season") -> 68
A84: 2015 | B84: 42005 | C84: Shep | D84: Suburban Kings | E84: =D84&" - "&A84 -> Suburban Kings - 2015 | F84: Cam Newton | G84: Frank Gore | H84: AJ Green | I84: Greg Olsen | J84: Current Owner | L84: 6 | M84: 1 | N84: =M84 -> 1 | O84: 13 | P84: 7 | Q84: 6 | R84: 1180 | S84: 1162 | T84: Fishers | U84: Indiana | V84: 46037 | W84: 69 | X84: =310 -> 310 | Y84: =X84-W84 -> 241 | Z84: =IF(M84=1,1,0) -> 1 | AA84: =if(L84<7,1,0) -> 1 | AC84: =P84*100+R84/4 -> 995 | AD84: =if(L84=1,1,0) -> 0 | AF84: =sumifs('WL Matrix 2'!T:T,'WL Matrix 2'!B:B,A84,'WL Matrix 2'!C:C,C84,'WL Matrix 2'!M:M,"Regular Season") -> 75 | AG84: =11*O84-AF84 -> 68 | AI84: No PPR | AJ84: =rank(R84,$R$74:$R$85) -> 9 | AK84: =R84/ averageif($A:$A,A84,R:R) -> 0.98074526 | AL84: =S84/averageif($A:$A,A84,S:S) -> 0.96577805 | AM84: =sumifs('WL Matrix 2'!T:T,'WL Matrix 2'!B:B,A84,'WL Matrix 2'!C:C,C84,'WL Matrix 2'!M:M,"Regular Season") -> 75
A85: 2015 | B85: 42005 | C85: Pierson | D85: Gary Biebnidge | E85: =D85&" - "&A85 -> Gary Biebnidge - 2015 | F85: Matt Ryan | G85: Doug Martin | H85: Allen Robinson | I85: Gary Barnidge | J85: Current Owner | L85: 9 | M85: 9 | N85: =M85 -> 9 | O85: 13 | P85: 6 | Q85: 7 | R85: 1187 | S85: 1282 | T85: Chicago | U85: Illinois | V85: 60657 | W85: 69 | Y85: =X85-W85 -> -69 | Z85: =IF(M85=1,1,0) -> 0 | AA85: =if(L85<7,1,0) -> 0 | AC85: =P85*100+R85/4 -> 896.75 | AD85: =if(L85=1,1,0) -> 0 | AF85: =sumifs('WL Matrix 2'!T:T,'WL Matrix 2'!B:B,A85,'WL Matrix 2'!C:C,C85,'WL Matrix 2'!M:M,"Regular Season") -> 73 | AG85: =11*O85-AF85 -> 70 | AI85: No PPR | AJ85: =rank(R85,$R$74:$R$85) -> 8 | AK85: =R85/ averageif($A:$A,A85,R:R) -> 0.98656324 | AL85: =S85/averageif($A:$A,A85,S:S) -> 1.0655142 | AM85: =sumifs('WL Matrix 2'!T:T,'WL Matrix 2'!B:B,A85,'WL Matrix 2'!C:C,C85,'WL Matrix 2'!M:M,"Regular Season") -> 73
A86: 2016 | B86: 42370 | C86: Buser | D86: Julio Get the Catch | E86: =D86&" - "&A86 -> Julio Get the Catch - 2016 | F86: Aaron Rodgers | G86: DeMarco Murray | H86: Julio Jones | I86: Rob Gronkowski | J86: Current Owner | L86: 5 | M86: 5 | N86: =M86 -> 5 | O86: 13 | P86: 7 | Q86: 6 | R86: 1338.5 | S86: 1243.2 | T86: New York | U86: New York | V86: 10023 | W86: 69 | Y86: =X86-W86 -> -69 | Z86: 0 | AA86: =if(L86<7,1,0) -> 1 | AC86: =P86*100+R86/4 -> 1034.625 | AD86: =if(L86=1,1,0) -> 0 | AF86: =sumifs('WL Matrix 2'!T:T,'WL Matrix 2'!B:B,A86,'WL Matrix 2'!C:C,C86,'WL Matrix 2'!M:M,"Regular Season") -> 91 | AG86: =11*O86-AF86 -> 52 | AI86: No PPR | AJ86: =rank(R86,$R$86:$R$97) -> 3 | AK86: =R86/ averageif($A:$A,A86,R:R) -> 1.0931364 | AL86: =S86/averageif($A:$A,A86,S:S) -> 1.0153061 | AM86: =sumifs('WL Matrix 2'!T:T,'WL Matrix 2'!B:B,A86,'WL Matrix 2'!C:C,C86,'WL Matrix 2'!M:M,"Regular Season") -> 91
A87: 2016 | B87: 42370 | C87: Tayski | D87: Keenan Allen Memorial Team | E87: =D87&" - "&A87 -> Keenan Allen Memorial Team - 2016 | F87: Phillip Rivers | G87: Matt Jones | H87: Larry Fitzgerald | I87: Delanie Walker | J87: Current Owner | L87: 12 | M87: 12 | N87: =M87 -> 12 | O87: 13 | P87: 3 | Q87: 10 | R87: 1007.9 | S87: 1181 | T87: Nashville | U87: Tennessee | V87: 37115 | W87: 69 | Y87: =X87-W87 -> -69 | Z87: 0 | AA87: =if(L87<7,1,0) -> 0 | AC87: =P87*100+R87/4 -> 551.975 | AD87: =if(L87=1,1,0) -> 0 | AF87: =sumifs('WL Matrix 2'!T:T,'WL Matrix 2'!B:B,A87,'WL Matrix 2'!C:C,C87,'WL Matrix 2'!M:M,"Regular Season") -> 32 | AG87: =11*O87-AF87 -> 111 | AI87: No PPR | AJ87: =rank(R87,$R$86:$R$97) -> 12 | AK87: =R87/ averageif($A:$A,A87,R:R) -> 0.82313948 | AL87: =S87/averageif($A:$A,A87,S:S) -> 0.96450812 | AM87: =sumifs('WL Matrix 2'!T:T,'WL Matrix 2'!B:B,A87,'WL Matrix 2'!C:C,C87,'WL Matrix 2'!M:M,"Regular Season") -> 32
A88: 2016 | B88: 42370 | C88: Rooney/Jackson | D88: Rob "Ryan Chip" Kelley | E88: =D88&" - "&A88 -> Rob "Ryan Chip" Kelley - 2016 | F88: Russell Wilson | G88: Melvin Gordon | H88: Allen Robinson | I88: Kyle Rudolph | J88: Current Owner | L88: 11 | M88: 11 | N88: =M88 -> 11 | O88: 13 | P88: 5 | Q88: 8 | R88: 1138.1 | S88: 1251.1 | T88: Chicago | U88: Illinois | V88: 60647 | W88: 69 | Y88: =X88-W88 -> -69 | Z88: 0 | AA88: =if(L88<7,1,0) -> 0 | AC88: =P88*100+R88/4 -> 784.525 | AD88: =if(L88=1,1,0) -> 0 | AF88: =sumifs('WL Matrix 2'!T:T,'WL Matrix 2'!B:B,A88,'WL Matrix 2'!C:C,C88,'WL Matrix 2'!M:M,"Regular Season") -> 62 | AG88: =11*O88-AF88 -> 81 | AI88: No PPR | AJ88: =rank(R88,$R$86:$R$97) -> 9 | AK88: =R88/ averageif($A:$A,A88,R:R) -> 0.92947222 | AL88: =S88/averageif($A:$A,A88,S:S) -> 1.0217579 | AM88: =sumifs('WL Matrix 2'!T:T,'WL Matrix 2'!B:B,A88,'WL Matrix 2'!C:C,C88,'WL Matrix 2'!M:M,"Regular Season") -> 62
A89: 2016 | B89: 42370 | C89: Hudspeath | D89: Cutler's Year | E89: =D89&" - "&A89 -> Cutler's Year - 2016 | F89: Carson Palmer | G89: Frank Gore | H89: Jordy Nelson | I89: Julius Thomas | J89: Current Owner | L89: 7 | M89: 7 | N89: =M89 -> 7 | O89: 13 | P89: 7 | Q89: 6 | R89: 1137.7 | S89: 1219.5 | T89: San Francisco | U89: California | V89: 94101 | W89: 69 | Y89: =X89-W89 -> -69 | Z89: 0 | AA89: =if(L89<7,1,0) -> 0 | AC89: =P89*100+R89/4 -> 984.425 | AD89: =if(L89=1,1,0) -> 0 | AF89: =sumifs('WL Matrix 2'!T:T,'WL Matrix 2'!B:B,A89,'WL Matrix 2'!C:C,C89,'WL Matrix 2'!M:M,"Regular Season") -> 68 | AG89: =11*O89-AF89 -> 75 | AI89: No PPR | AJ89: =rank(R89,$R$86:$R$97) -> 10 | AK89: =R89/ averageif($A:$A,A89,R:R) -> 0.92914554 | AL89: =S89/averageif($A:$A,A89,S:S) -> 0.99595059 | AM89: =sumifs('WL Matrix 2'!T:T,'WL Matrix 2'!B:B,A89,'WL Matrix 2'!C:C,C89,'WL Matrix 2'!M:M,"Regular Season") -> 68
A90: 2016 | B90: 42370 | C90: Riley | D90: Wain Newton | E90: =D90&" - "&A90 -> Wain Newton - 2016 | F90: Cam Newton | G90: David Johnson | H90: Jordan Matthews | I90: Martellus Bennett | J90: Current Owner | L90: 9 | M90: 9 | N90: =M90 -> 9 | O90: 13 | P90: 6 | Q90: 7 | R90: 1388.1 | S90: 1204.3 | T90: Chicago | U90: Illinois | V90: 60610 | W90: 69 | Y90: =X90-W90 -> -69 | Z90: 0 | AA90: =if(L90<7,1,0) -> 0 | AC90: =P90*100+R90/4 -> 947.025 | AD90: =if(L90=1,1,0) -> 0 | AF90: =sumifs('WL Matrix 2'!T:T,'WL Matrix 2'!B:B,A90,'WL Matrix 2'!C:C,C90,'WL Matrix 2'!M:M,"Regular Season") -> 91 | AG90: =11*O90-AF90 -> 52 | AI90: No PPR | AJ90: =rank(R90,$R$86:$R$97) -> 2 | AK90: =R90/ averageif($A:$A,A90,R:R) -> 1.1336441 | AL90: =S90/averageif($A:$A,A90,S:S) -> 0.98353694 | AM90: =sumifs('WL Matrix 2'!T:T,'WL Matrix 2'!B:B,A90,'WL Matrix 2'!C:C,C90,'WL Matrix 2'!M:M,"Regular Season") -> 91
A91: 2016 | B91: 42370 | C91: Cock | D91: J. Cash and The CochSlappers | E91: =D91&" - "&A91 -> J. Cash and The CochSlappers - 2016 | F91: Matt Ryan | G91: Jamaal Charles | H91: Brandin Cooks | I91: Jimmy Graham | J91: Current Owner | L91: 8 | M91: 8 | N91: =M91 -> 8 | O91: 13 | P91: 7 | Q91: 7 | R91: 1102.7 | S91: 1264.8 | T91: Chicago | U91: Illinois | V91: 60614 | W91: 69 | Y91: =X91-W91 -> -69 | Z91: 0 | AA91: =if(L91<7,1,0) -> 0 | AC91: =P91*100+R91/4 -> 975.675 | AD91: =if(L91=1,1,0) -> 0 | AF91: =sumifs('WL Matrix 2'!T:T,'WL Matrix 2'!B:B,A91,'WL Matrix 2'!C:C,C91,'WL Matrix 2'!M:M,"Regular Season") -> 52 | AG91: =11*O91-AF91 -> 91 | AI91: No PPR | AJ91: =rank(R91,$R$86:$R$97) -> 11 | AK91: =R91/ averageif($A:$A,A91,R:R) -> 0.90056147 | AL91: =S91/averageif($A:$A,A91,S:S) -> 1.0329465 | AM91: =sumifs('WL Matrix 2'!T:T,'WL Matrix 2'!B:B,A91,'WL Matrix 2'!C:C,C91,'WL Matrix 2'!M:M,"Regular Season") -> 52
A92: 2016 | B92: 42370 | C92: Salty | D92: Last Manning Standing | E92: =D92&" - "&A92 -> Last Manning Standing - 2016 | F92: Eli Manning | G92: Carlos Hyde | H92: Antonio Brown | I92: Coby Fleener | J92: Current Owner | L92: 6 | M92: 4 | N92: 3 | O92: 13 | P92: 7 | Q92: 6 | R92: 1170.3 | S92: 1139.2 | T92: Los Angeles | U92: California | V92: 90026 | W92: 69 | X92: 69 | Y92: =X92-W92 -> 0 | Z92: 0 | AA92: =if(L92<7,1,0) -> 1 | AC92: =P92*100+R92/4 -> 992.575 | AD92: =if(L92=1,1,0) -> 0 | AF92: =sumifs('WL Matrix 2'!T:T,'WL Matrix 2'!B:B,A92,'WL Matrix 2'!C:C,C92,'WL Matrix 2'!M:M,"Regular Season") -> 63 | AG92: =11*O92-AF92 -> 80 | AI92: No PPR | AJ92: =rank(R92,$R$86:$R$97) -> 8 | AK92: =R92/ averageif($A:$A,A92,R:R) -> 0.95576956 | AL92: =S92/averageif($A:$A,A92,S:S) -> 0.93037057 | AM92: =sumifs('WL Matrix 2'!T:T,'WL Matrix 2'!B:B,A92,'WL Matrix 2'!C:C,C92,'WL Matrix 2'!M:M,"Regular Season") -> 63
A93: 2016 | B93: 42370 | C93: Fellows | D93: Dak to Dak Jacks | E93: =D93&" - "&A93 -> Dak to Dak Jacks - 2016 | F93: Derek Carr | G93: Mark Ingram | H93: Dez Bryant | I93: Jordan Reed | J93: Retired Owner | L93: 3 | M93: 6 | N93: =M93 -> 6 | O93: 13 | P93: 8 | Q93: 5 | R93: 1244.6 | S93: 1232.6 | T93: Austin | U93: Texas | V93: 73301 | W93: 69 | Y93: =X93-W93 -> -69 | Z93: 0 | AA93: =if(L93<7,1,0) -> 1 | AC93: =P93*100+R93/4 -> 1111.15 | AD93: =if(L93=1,1,0) -> 0 | AF93: =sumifs('WL Matrix 2'!T:T,'WL Matrix 2'!B:B,A93,'WL Matrix 2'!C:C,C93,'WL Matrix 2'!M:M,"Regular Season") -> 82 | AG93: =11*O93-AF93 -> 61 | AI93: No PPR | AJ93: =rank(R93,$R$86:$R$97) -> 6 | AK93: =R93/ averageif($A:$A,A93,R:R) -> 1.0164495 | AL93: =S93/averageif($A:$A,A93,S:S) -> 1.0066492 | AM93: =sumifs('WL Matrix 2'!T:T,'WL Matrix 2'!B:B,A93,'WL Matrix 2'!C:C,C93,'WL Matrix 2'!M:M,"Regular Season") -> 82
A94: 2016 | B94: 42370 | C94: T-How | D94: DeAndre 3000 | E94: =D94&" - "&A94 -> DeAndre 3000 - 2016 | F94: Andrew Luck | G94: Ryan Matthews | H94: DeAndre Hopkins | I94: Greg Olsen | J94: Current Owner | L94: 2 | M94: 2 | N94: =M94 -> 2 | O94: 13 | P94: 8 | Q94: 5 | R94: 1252.6 | S94: 1242.5 | T94: Chicago | U94: Illinois | V94: 60610 | W94: 69 | X94: 170 | Y94: =X94-W94 -> 101 | Z94: 0 | AA94: =if(L94<7,1,0) -> 1 | AC94: =P94*100+R94/4 -> 1113.15 | AD94: =if(L94=1,1,0) -> 0 | AF94: =sumifs('WL Matrix 2'!T:T,'WL Matrix 2'!B:B,A94,'WL Matrix 2'!C:C,C94,'WL Matrix 2'!M:M,"Regular Season") -> 71 | AG94: =11*O94-AF94 -> 72 | AI94: No PPR | AJ94: =rank(R94,$R$86:$R$97) -> 5 | AK94: =R94/ averageif($A:$A,A94,R:R) -> 1.022983 | AL94: =S94/averageif($A:$A,A94,S:S) -> 1.0147344 | AM94: =sumifs('WL Matrix 2'!T:T,'WL Matrix 2'!B:B,A94,'WL Matrix 2'!C:C,C94,'WL Matrix 2'!M:M,"Regular Season") -> 71
A95: 2016 | B95: 42370 | C95: KnardDawg | D95: Bring Tha Juice | E95: =D95&" - "&A95 -> Bring Tha Juice - 2016 | F95: Tom Brady | G95: Matt Forte | H95: Mike Evans | I95: CJ Fiedorowicz | J95: Current Owner | L95: 10 | M95: 10 | N95: =M95 -> 10 | O95: 13 | P95: 5 | Q95: 8 | R95: 1225.9 | S95: =sumifs('WL Matrix 2'!K:K,'WL Matrix 2'!B:B,A95,'WL Matrix 2'!C:C,C95,'WL Matrix 2'!M:M,"Regular Season") -> 1301.9 | T95: Chicago | U95: Illinois | V95: 60657 | W95: 69 | Y95: =X95-W95 -> -69 | Z95: 0 | AA95: =if(L95<7,1,0) -> 0 | AC95: =P95*100+R95/4 -> 806.475 | AD95: =if(L95=1,1,0) -> 0 | AF95: =sumifs('WL Matrix 2'!T:T,'WL Matrix 2'!B:B,A95,'WL Matrix 2'!C:C,C95,'WL Matrix 2'!M:M,"Regular Season") -> 73 | AG95: =11*O95-AF95 -> 70 | AI95: No PPR | AJ95: =rank(R95,$R$86:$R$97) -> 7 | AK95: =R95/ averageif($A:$A,A95,R:R) -> 1.0011774 | AL95: =S95/averageif($A:$A,A95,S:S) -> 1.0632457 | AM95: =sumifs('WL Matrix 2'!T:T,'WL Matrix 2'!B:B,A95,'WL Matrix 2'!C:C,C95,'WL Matrix 2'!M:M,"Regular Season") -> 73
A96: 2016 | B96: 42370 | C96: Shep | D96: Suburban Kings II | E96: =D96&" - "&A96 -> Suburban Kings II - 2016 | F96: Matthew Stafford | G96: Ezekiel Elliott | H96: TY Hilton | I96: Gary Barnidge | J96: Current Owner | L96: 1 | M96: 3 | N96: 4 | O96: 13 | P96: 8 | Q96: 5 | R96: 1289.5 | S96: =sumifs('WL Matrix 2'!K:K,'WL Matrix 2'!B:B,A96,'WL Matrix 2'!C:C,C96,'WL Matrix 2'!M:M,"Regular Season") -> 1099.2 | T96: Fishers | U96: Indiana | V96: 46037 | W96: 69 | X96: =137 -> 137 | Y96: =X96-W96 -> 68 | Z96: 0 | AA96: =if(L96<7,1,0) -> 1 | AC96: =P96*100+R96/4 -> 1122.375 | AD96: =if(L96=1,1,0) -> 1 | AF96: =sumifs('WL Matrix 2'!T:T,'WL Matrix 2'!B:B,A96,'WL Matrix 2'!C:C,C96,'WL Matrix 2'!M:M,"Regular Season") -> 79 | AG96: =11*O96-AF96 -> 64 | AI96: No PPR | AJ96: =rank(R96,$R$86:$R$97) -> 4 | AK96: =R96/ averageif($A:$A,A96,R:R) -> 1.0531187 | AL96: =S96/averageif($A:$A,A96,S:S) -> 0.89770307 | AM96: =sumifs('WL Matrix 2'!T:T,'WL Matrix 2'!B:B,A96,'WL Matrix 2'!C:C,C96,'WL Matrix 2'!M:M,"Regular Season") -> 79
A97: 2016 | B97: 42370 | C97: Pierson | D97: Yung Breezy n Lil' LeSean | E97: =D97&" - "&A97 -> Yung Breezy n Lil' LeSean - 2016 | F97: Drew Brees | G97: LeSean McCoy | H97: Brandon Marshall | I97: Travis Kelce | J97: Current Owner | L97: 4 | M97: 1 | N97: =M97 -> 1 | O97: 13 | P97: 7 | Q97: 6 | R97: 1397.6 | S97: =sumifs('WL Matrix 2'!K:K,'WL Matrix 2'!B:B,A97,'WL Matrix 2'!C:C,C97,'WL Matrix 2'!M:M,"Regular Season") -> 1314.2 | T97: Chicago | U97: Illinois | V97: 60657 | W97: 69 | X97: =137+310 -> 447 | Y97: =X97-W97 -> 378 | Z97: 1 | AA97: =if(L97<7,1,0) -> 1 | AC97: =P97*100+R97/4 -> 1049.4 | AD97: =if(L97=1,1,0) -> 0 | AE97: 1 | AF97: =sumifs('WL Matrix 2'!T:T,'WL Matrix 2'!B:B,A97,'WL Matrix 2'!C:C,C97,'WL Matrix 2'!M:M,"Regular Season") -> 94 | AG97: =11*O97-AF97 -> 49 | AI97: No PPR | AJ97: =rank(R97,$R$86:$R$97) -> 1 | AK97: =R97/ averageif($A:$A,A97,R:R) -> 1.1414027 | AL97: =S97/averageif($A:$A,A97,S:S) -> 1.0732909 | AM97: =sumifs('WL Matrix 2'!T:T,'WL Matrix 2'!B:B,A97,'WL Matrix 2'!C:C,C97,'WL Matrix 2'!M:M,"Regular Season") -> 94
A98: 2017 | B98: 42736 | C98: Buser | D98: Hunting Szn | E98: Hunting Szn - 2017 | F98: Eli Manning | G98: DeMarco Murray | H98: Antonio Brown | I98: Eric Ebron | J98: Current Owner | L98: 4 | M98: 4 | N98: 4 | O98: 13 | P98: =sumifs('WL Matrix 2'!L:L,'WL Matrix 2'!B:B,A98,'WL Matrix 2'!C:C,C98) -> 8 | Q98: =O98-P98 -> 5 | R98: =sumifs('WL Matrix 2'!J:J,'WL Matrix 2'!B:B,A98,'WL Matrix 2'!C:C,C98,'WL Matrix 2'!M:M,"Regular Season") -> 1184.62 | S98: =sumifs('WL Matrix 2'!K:K,'WL Matrix 2'!B:B,A98,'WL Matrix 2'!C:C,C98,'WL Matrix 2'!M:M,"Regular Season") -> 1078.22 | T98: New York | U98: New York | V98: 10023 | W98: 100 | X98: $ - | Y98: -100 | Z98: =if(M98=1,1,0) -> 0 | AA98: =if(L98<7,1,0) -> 1 | AC98: =P98*100+R98/4 -> 1096.155 | AD98: =if(L98=1,1,0) -> 0 | AF98: =sumifs('WL Matrix 2'!T:T,'WL Matrix 2'!B:B,A98,'WL Matrix 2'!C:C,C98,'WL Matrix 2'!M:M,"Regular Season") -> 70 | AG98: =11*O98-AF98 -> 73 | AI98: No PPR | AJ98: =rank(R98,$R$98:$R$109) -> 7 | AK98: =R98/ averageif($A:$A,A98,R:R) -> 1.0105552 | AL98: =S98/averageif($A:$A,A98,S:S) -> 0.91978935 | AM98: =sumifs('WL Matrix 2'!T:T,'WL Matrix 2'!B:B,A98,'WL Matrix 2'!C:C,C98,'WL Matrix 2'!M:M,"Regular Season") -> 70
A99: 2017 | B99: 42736 | C99: Tayski | D99: Mariota and Some Randos | E99: Mariota and Some Randos - 2017 | F99: Marcus Mariota | G99: Jay Ajayi | H99: Alshon Jeffery | I99: Martellus Bennett | J99: Current Owner | L99: 10 | M99: 10 | N99: 10 | O99: 13 | P99: =sumifs('WL Matrix 2'!L:L,'WL Matrix 2'!B:B,A99,'WL Matrix 2'!C:C,C99) -> 4 | Q99: =O99-P99 -> 9 | R99: =sumifs('WL Matrix 2'!J:J,'WL Matrix 2'!B:B,A99,'WL Matrix 2'!C:C,C99,'WL Matrix 2'!M:M,"Regular Season") -> 932.7 | S99: =sumifs('WL Matrix 2'!K:K,'WL Matrix 2'!B:B,A99,'WL Matrix 2'!C:C,C99,'WL Matrix 2'!M:M,"Regular Season") -> 1100.8 | T99: Nashville | U99: Tennessee | V99: 37115 | W99: 100 | X99: $ - | Y99: -100 | Z99: =if(M99=1,1,0) -> 0 | AA99: =if(L99<7,1,0) -> 0 | AC99: =P99*100+R99/4 -> 633.175 | AD99: =if(L99=1,1,0) -> 0 | AF99: =sumifs('WL Matrix 2'!T:T,'WL Matrix 2'!B:B,A99,'WL Matrix 2'!C:C,C99,'WL Matrix 2'!M:M,"Regular Season") -> 33 | AG99: =11*O99-AF99 -> 110 | AI99: No PPR | AJ99: =rank(R99,$R$98:$R$109) -> 12 | AK99: =R99/ averageif($A:$A,A99,R:R) -> 0.79565165 | AL99: =S99/averageif($A:$A,A99,S:S) -> 0.93905151 | AM99: =sumifs('WL Matrix 2'!T:T,'WL Matrix 2'!B:B,A99,'WL Matrix 2'!C:C,C99,'WL Matrix 2'!M:M,"Regular Season") -> 33
A100: 2017 | B100: 42736 | C100: Rooney/Jackson | D100: GOD DAMNIT DALVIN | E100: GOD DAMNIT DALVIN - 2017 | F100: Derek Carr | G100: LeSean McCoy | H100: Dalvin Cook | I100: Jordy Nelson | J100: Current Owner | L100: 11 | M100: 11 | N100: 11 | O100: 13 | P100: =sumifs('WL Matrix 2'!L:L,'WL Matrix 2'!B:B,A100,'WL Matrix 2'!C:C,C100) -> 5 | Q100: =O100-P100 -> 8 | R100: =sumifs('WL Matrix 2'!J:J,'WL Matrix 2'!B:B,A100,'WL Matrix 2'!C:C,C100,'WL Matrix 2'!M:M,"Regular Season") -> 1074.84 | S100: =sumifs('WL Matrix 2'!K:K,'WL Matrix 2'!B:B,A100,'WL Matrix 2'!C:C,C100,'WL Matrix 2'!M:M,"Regular Season") -> 1287.6 | T100: Chicago | U100: Illinois | V100: 60647 | W100: 100 | X100: $ - | Y100: -100 | Z100: =if(M100=1,1,0) -> 0 | AA100: =if(L100<7,1,0) -> 0 | AC100: =P100*100+R100/4 -> 768.71 | AD100: =if(L100=1,1,0) -> 0 | AF100: =sumifs('WL Matrix 2'!T:T,'WL Matrix 2'!B:B,A100,'WL Matrix 2'!C:C,C100,'WL Matrix 2'!M:M,"Regular Season") -> 60 | AG100: =11*O100-AF100 -> 83 | AI100: No PPR | AJ100: =rank(R100,$R$98:$R$109) -> 9 | AK100: =R100/ averageif($A:$A,A100,R:R) -> 0.916906 | AL100: =S100/averageif($A:$A,A100,S:S) -> 1.0984036 | AM100: =sumifs('WL Matrix 2'!T:T,'WL Matrix 2'!B:B,A100,'WL Matrix 2'!C:C,C100,'WL Matrix 2'!M:M,"Regular Season") -> 60
...

Sheet WL Matrix 2
A1: YearOwnerWeek | B1: Year | C1: Owner | D1: Week | E1: Record | F1: Score | G1: Placeholder 2 | H1: Opponent | I1: Opponent Name | J1: Owner's Score | K1: Opponent's Score | L1: Result | M1: Game Type | N1: Mapped Opponent | O1: Week Number | P1: OpponentsSimplified Name | Q1: Week | R1: YearWeek | S1: Weekly Score Rank | T1: Power Rank Score (Wins) | U1: Power Rank Losses | V1: Annual avg score | W1: Score Index
A2: =B2&C2&O2 -> 2011Hudspeath15 | B2: 2011 | C2: Hudspeath | D2: Round 1 | E2: 42192 | F2: L 94.3-101.6 | G2: at | H2: Salt Bake City (9-5) | I2: R Saltiel | J2: 94.3 | K2: 101.6 | L2: =IF(LEFT(F2,1)="W",1,0) -> 0 | M2: =IF(ISNUMBER(SEARCH("Round",D2)),"Playoffs","Regular Season") -> Playoffs | N2: =IFERROR(VLOOKUP(I2,Mapped_Owner,2,0),"") -> Salty | O2: =VLOOKUP(D2,'Mapped Opponent'!$G$4:$H$22,2,0) -> 15 | Q2: ="Week "&O2 -> Week 15 | R2: =B2&D2 -> 2011Round 1 | S2: =IFERROR(__xludf.DUMMYFUNCTION("rank(J2,FILTER(J:J,R:R=R2))"),6.0) -> 6 | T2: =IFERROR(12-S2,0) -> 6 | U2: =12-T2 -> 6 | V2: =averageif(AllData!A:A,B2,AllData!R:R)/vlookup(B2,AllData!A:O,15,0) -> 88.551282
A3: =B3&C3&O3 -> 2011Salty15 | B3: 2011 | C3: Salty | D3: Round 1 | E3: 42252 | F3: W 101.6-94.3 | H3: Cutler's Year (7-7) | I3: matt hudspeath | J3: 101.6 | K3: 94.3 | L3: =IF(LEFT(F3,1)="W",1,0) -> 1 | M3: =IF(ISNUMBER(SEARCH("Round",D3)),"Playoffs","Regular Season") -> Playoffs | N3: =IFERROR(VLOOKUP(I3,Mapped_Owner,2,0),"") -> Hudspeath | O3: =VLOOKUP(D3,'Mapped Opponent'!$G$4:$H$22,2,0) -> 15 | Q3: ="Week "&O3 -> Week 15 | R3: =B3&D3 -> 2011Round 1 | S3: =IFERROR(__xludf.DUMMYFUNCTION("rank(J3,FILTER(J:J,R:R=R3))"),3.0) -> 3 | T3: =IFERROR(12-S3,0) -> 9 | U3: =12-T3 -> 3 | V3: =averageif(AllData!A:A,B3,AllData!R:R)/vlookup(B3,AllData!A:O,15,0) -> 88.551282
A4: =B4&C4&O4 -> 2011Fellows15 | B4: 2011 | C4: Fellows | D4: Round 1 | E4: 42104 | F4: L 88.3-114.4 | H4: Team Weis (4-10) | I4: Taylor Weis | J4: 88.3 | K4: 114.4 | L4: =IF(LEFT(F4,1)="W",1,0) -> 0 | M4: =IF(ISNUMBER(SEARCH("Round",D4)),"Playoffs","Regular Season") -> Playoffs | N4: =IFERROR(VLOOKUP(I4,Mapped_Owner,2,0),"") -> Tayski | O4: =VLOOKUP(D4,'Mapped Opponent'!$G$4:$H$22,2,0) -> 15 | Q4: ="Week "&O4 -> Week 15 | R4: =B4&D4 -> 2011Round 1 | S4: =IFERROR(__xludf.DUMMYFUNCTION("rank(J4,FILTER(J:J,R:R=R4))"),9.0) -> 9 | T4: =IFERROR(12-S4,0) -> 3 | U4: =12-T4 -> 9 | V4: =averageif(AllData!A:A,B4,AllData!R:R)/vlookup(B4,AllData!A:O,15,0) -> 88.551282
A5: =B5&C5&O5 -> 2011Shep15 | B5: 2011 | C5: Shep | D5: Round 1 | E5: 42192 | F5: L 98.6-114.9 | G5: at | H5: Kibbles 'n Fitz (9-5) | I5: Tyler Howard | J5: 98.6 | K5: 114.9 | L5: =IF(LEFT(F5,1)="W",1,0) -> 0 | M5: =IF(ISNUMBER(SEARCH("Round",D5)),"Playoffs","Regular Season") -> Playoffs | N5: =IFERROR(VLOOKUP(I5,Mapped_Owner,2,0),"") -> T-How | O5: =VLOOKUP(D5,'Mapped Opponent'!$G$4:$H$22,2,0) -> 15 | Q5: ="Week "&O5 -> Week 15 | R5: =B5&D5 -> 2011Round 1 | S5: =IFERROR(__xludf.DUMMYFUNCTION("rank(J5,FILTER(J:J,R:R=R5))"),4.0) -> 4 | T5: =IFERROR(12-S5,0) -> 8 | U5: =12-T5 -> 4 | V5: =averageif(AllData!A:A,B5,AllData!R:R)/vlookup(B5,AllData!A:O,15,0) -> 88.551282
A6: =B6&C6&O6 -> 2011Guckien15 | B6: 2011 | C6: Guckien | D6: Round 1 | E6: 42222 | F6: W 96.7-77.4 | H6: Tat Five (6-8) | I6: Alex Kinniard | J6: 96.7 | K6: 77.4 | L6: =IF(LEFT(F6,1)="W",1,0) -> 1 | M6: =IF(ISNUMBER(SEARCH("Round",D6)),"Playoffs","Regular Season") -> Playoffs | N6: =IFERROR(VLOOKUP(I6,Mapped_Owner,2,0),"") -> KnardDawg | O6: =VLOOKUP(D6,'Mapped Opponent'!$G$4:$H$22,2,0) -> 15 | Q6: ="Week "&O6 -> Week 15 | R6: =B6&D6 -> 2011Round 1 | S6: =IFERROR(__xludf.DUMMYFUNCTION("rank(J6,FILTER(J:J,R:R=R6))"),5.0) -> 5 | T6: =IFERROR(12-S6,0) -> 7 | U6: =12-T6 -> 5 | V6: =averageif(AllData!A:A,B6,AllData!R:R)/vlookup(B6,AllData!A:O,15,0) -> 88.551282
A7: =B7&C7&O7 -> 2011Rooney/Jackson15 | B7: 2011 | C7: Rooney/Jackson | D7: Round 1 | E7: 42163 | F7: W 92.1-88.5 | H7: It's My Vick In a Box! (5-9) | I7: Chris Cochrane | J7: 92.1 | K7: 88.5 | L7: =IF(LEFT(F7,1)="W",1,0) -> 1 | M7: =IF(ISNUMBER(SEARCH("Round",D7)),"Playoffs","Regular Season") -> Playoffs | N7: =IFERROR(VLOOKUP(I7,Mapped_Owner,2,0),"") -> Cock | O7: =VLOOKUP(D7,'Mapped Opponent'!$G$4:$H$22,2,0) -> 15 | Q7: ="Week "&O7 -> Week 15 | R7: =B7&D7 -> 2011Round 1 | S7: =IFERROR(__xludf.DUMMYFUNCTION("rank(J7,FILTER(J:J,R:R=R7))"),7.0) -> 7 | T7: =IFERROR(12-S7,0) -> 5 | U7: =12-T7 -> 7 | V7: =averageif(AllData!A:A,B7,AllData!R:R)/vlookup(B7,AllData!A:O,15,0) -> 88.551282
A8: =B8&C8&O8 -> 2011Buser15 | B8: 2011 | C8: Buser | D8: Round 1 | E8: 42251 | F8: 0 pts | H8: BYE | J8: 0 | K8: 0 | L8: =IF(LEFT(F8,1)="W",1,0) -> 0 | M8: =IF(ISNUMBER(SEARCH("Round",D8)),"Playoffs","Regular Season") -> Playoffs | N8: =IFERROR(VLOOKUP(I8,Mapped_Owner,2,0),"") -> BYE | O8: =VLOOKUP(D8,'Mapped Opponent'!$G$4:$H$22,2,0) -> 15 | Q8: ="Week "&O8 -> Week 15 | R8: =B8&D8 -> 2011Round 1 | S8: =IFERROR(__xludf.DUMMYFUNCTION("rank(J8,FILTER(J:J,R:R=R8))"),11.0) -> 11 | T8: =IFERROR(12-S8,0) -> 1 | U8: =12-T8 -> 11 | V8: =averageif(AllData!A:A,B8,AllData!R:R)/vlookup(B8,AllData!A:O,15,0) -> 88.551282
A9: =B9&C9&O9 -> 2011Pierson15 | B9: 2011 | C9: Pierson | D9: Round 1 | E9: 42251 | F9: 0 pts | H9: BYE | J9: 0 | K9: 0 | L9: =IF(LEFT(F9,1)="W",1,0) -> 0 | M9: =IF(ISNUMBER(SEARCH("Round",D9)),"Playoffs","Regular Season") -> Playoffs | N9: =IFERROR(VLOOKUP(I9,Mapped_Owner,2,0),"") -> BYE | O9: =VLOOKUP(D9,'Mapped Opponent'!$G$4:$H$22,2,0) -> 15 | Q9: ="Week "&O9 -> Week 15 | R9: =B9&D9 -> 2011Round 1 | S9: =IFERROR(__xludf.DUMMYFUNCTION("rank(J9,FILTER(J:J,R:R=R9))"),11.0) -> 11 | T9: =IFERROR(12-S9,0) -> 1 | U9: =12-T9 -> 11 | V9: =averageif(AllData!A:A,B9,AllData!R:R)/vlookup(B9,AllData!A:O,15,0) -> 88.551282
A10: =B10&C10&O10 -> 2011Cock15 | B10: 2011 | C10: Cock | D10: Round 1 | E10: 42133 | F10: L 88.5-92.1 | G10: at | H10: Clay Rodge (6-8) | I10: Stephen Rooney | J10: 88.5 | K10: 92.1 | L10: =IF(LEFT(F10,1)="W",1,0) -> 0 | M10: =IF(ISNUMBER(SEARCH("Round",D10)),"Playoffs","Regular Season") -> Playoffs | N10: =IFERROR(VLOOKUP(I10,Mapped_Owner,2,0),"") -> Rooney/Jackson | O10: =VLOOKUP(D10,'Mapped Opponent'!$G$4:$H$22,2,0) -> 15 | Q10: ="Week "&O10 -> Week 15 | R10: =B10&D10 -> 2011Round 1 | S10: =IFERROR(__xludf.DUMMYFUNCTION("rank(J10,FILTER(J:J,R:R=R10))"),8.0) -> 8 | T10: =IFERROR(12-S10,0) -> 4 | U10: =12-T10 -> 8 | V10: =averageif(AllData!A:A,B10,AllData!R:R)/vlookup(B10,AllData!A:O,15,0) -> 88.551282
A11: =B11&C11&O11 -> 2011Tayski15 | B11: 2011 | C11: Tayski | D11: Round 1 | E11: 42104 | F11: W 114.4-88.3 | G11: at | H11: Yo Adrian! (4-10) | I11: Michael Fellows | J11: 114.4 | K11: 88.3 | L11: =IF(LEFT(F11,1)="W",1,0) -> 1 | M11: =IF(ISNUMBER(SEARCH("Round",D11)),"Playoffs","Regular Season") -> Playoffs | N11: =IFERROR(VLOOKUP(I11,Mapped_Owner,2,0),"") -> Fellows | O11: =VLOOKUP(D11,'Mapped Opponent'!$G$4:$H$22,2,0) -> 15 | Q11: ="Week "&O11 -> Week 15 | R11: =B11&D11 -> 2011Round 1 | S11: =IFERROR(__xludf.DUMMYFUNCTION("rank(J11,FILTER(J:J,R:R=R11))"),2.0) -> 2 | T11: =IFERROR(12-S11,0) -> 10 | U11: =12-T11 -> 2 | V11: =averageif(AllData!A:A,B11,AllData!R:R)/vlookup(B11,AllData!A:O,15,0) -> 88.551282
A12: =B12&C12&O12 -> 2011KnardDawg15 | B12: 2011 | C12: KnardDawg | D12: Round 1 | E12: 42163 | F12: L 77.4-96.7 | G12: at | H12: The McRB is back! (8-6) | I12: Tyler Guckien | J12: 77.4 | K12: 96.7 | L12: =IF(LEFT(F12,1)="W",1,0) -> 0 | M12: =IF(ISNUMBER(SEARCH("Round",D12)),"Playoffs","Regular Season") -> Playoffs | N12: =IFERROR(VLOOKUP(I12,Mapped_Owner,2,0),"") -> Guckien | O12: =VLOOKUP(D12,'Mapped Opponent'!$G$4:$H$22,2,0) -> 15 | Q12: ="Week "&O12 -> Week 15 | R12: =B12&D12 -> 2011Round 1 | S12: =IFERROR(__xludf.DUMMYFUNCTION("rank(J12,FILTER(J:J,R:R=R12))"),10.0) -> 10 | T12: =IFERROR(12-S12,0) -> 2 | U12: =12-T12 -> 10 | V12: =averageif(AllData!A:A,B12,AllData!R:R)/vlookup(B12,AllData!A:O,15,0) -> 88.551282
A13: =B13&C13&O13 -> 2011T-How15 | B13: 2011 | C13: T-How | D13: Round 1 | E13: 42252 | F13: W 114.9-98.6 | H13: Show me your TDs (7-7) | I13: Jordan Shepherd | J13: 114.9 | K13: 98.6 | L13: =IF(LEFT(F13,1)="W",1,0) -> 1 | M13: =IF(ISNUMBER(SEARCH("Round",D13)),"Playoffs","Regular Season") -> Playoffs | N13: =IFERROR(VLOOKUP(I13,Mapped_Owner,2,0),"") -> Shep | O13: =VLOOKUP(D13,'Mapped Opponent'!$G$4:$H$22,2,0) -> 15 | Q13: ="Week "&O13 -> Week 15 | R13: =B13&D13 -> 2011Round 1 | S13: =IFERROR(__xludf.DUMMYFUNCTION("rank(J13,FILTER(J:J,R:R=R13))"),1.0) -> 1 | T13: =IFERROR(12-S13,0) -> 11 | U13: =12-T13 -> 1 | V13: =averageif(AllData!A:A,B13,AllData!R:R)/vlookup(B13,AllData!A:O,15,0) -> 88.551282
A14: =B14&C14&O14 -> 2011Hudspeath16 | B14: 2011 | C14: Hudspeath | D14: Round 2 | E14: 42223 | F14: W 139.1-72.4 | G14: at | H14: Show me your TDs (7-8) | I14: Jordan Shepherd | J14: 139.1 | K14: 72.4 | L14: =IF(LEFT(F14,1)="W",1,0) -> 1 | M14: =IF(ISNUMBER(SEARCH("Round",D14)),"Playoffs","Regular Season") -> Playoffs | N14: =IFERROR(VLOOKUP(I14,Mapped_Owner,2,0),"") -> Shep | O14: =VLOOKUP(D14,'Mapped Opponent'!$G$4:$H$22,2,0) -> 16 | Q14: ="Week "&O14 -> Week 16 | R14: =B14&D14 -> 2011Round 2 | S14: =IFERROR(__xludf.DUMMYFUNCTION("rank(J14,FILTER(J:J,R:R=R14))"),1.0) -> 1 | T14: =IFERROR(12-S14,0) -> 11 | U14: =12-T14 -> 1 | V14: =averageif(AllData!A:A,B14,AllData!R:R)/vlookup(B14,AllData!A:O,15,0) -> 88.551282
A15: =B15&C15&O15 -> 2011Salty16 | B15: 2011 | C15: Salty | D15: Round 2 | E15: 42253 | F15: L 51.8-99.7 | G15: at | H15: Yes We Cam (10-4) | I15: Ed Buser | J15: 51.8 | K15: 99.7 | L15: =IF(LEFT(F15,1)="W",1,0) -> 0 | M15: =IF(ISNUMBER(SEARCH("Round",D15)),"Playoffs","Regular Season") -> Playoffs | N15: =IFERROR(VLOOKUP(I15,Mapped_Owner,2,0),"") -> Buser | O15: =VLOOKUP(D15,'Mapped Opponent'!$G$4:$H$22,2,0) -> 16 | Q15: ="Week "&O15 -> Week 16 | R15: =B15&D15 -> 2011Round 2 | S15: =IFERROR(__xludf.DUMMYFUNCTION("rank(J15,FILTER(J:J,R:R=R15))"),12.0) -> 12 | T15: =IFERROR(12-S15,0) -> 0 | U15: =12-T15 -> 12 | V15: =averageif(AllData!A:A,B15,AllData!R:R)/vlookup(B15,AllData!A:O,15,0) -> 88.551282
A16: =B16&C16&O16 -> 2011Fellows16 | B16: 2011 | C16: Fellows | D16: Round 2 | E16: 42134 | F16: W 91.9-76.1 | G16: at | H16: It's My Vick In a Box! (5-10) | I16: Chris Cochrane | J16: 91.9 | K16: 76.1 | L16: =IF(LEFT(F16,1)="W",1,0) -> 1 | M16: =IF(ISNUMBER(SEARCH("Round",D16)),"Playoffs","Regular Season") -> Playoffs | N16: =IFERROR(VLOOKUP(I16,Mapped_Owner,2,0),"") -> Cock | O16: =VLOOKUP(D16,'Mapped Opponent'!$G$4:$H$22,2,0) -> 16 | Q16: ="Week "&O16 -> Week 16 | R16: =B16&D16 -> 2011Round 2 | S16: =IFERROR(__xludf.DUMMYFUNCTION("rank(J16,FILTER(J:J,R:R=R16))"),7.0) -> 7 | T16: =IFERROR(12-S16,0) -> 5 | U16: =12-T16 -> 7 | V16: =averageif(AllData!A:A,B16,AllData!R:R)/vlookup(B16,AllData!A:O,15,0) -> 88.551282
A17: =B17&C17&O17 -> 2011Shep16 | B17: 2011 | C17: Shep | D17: Round 2 | E17: 42193 | F17: L 72.4-139.1 | H17: Cutler's Year (8-7) | I17: matt hudspeath | J17: 72.4 | K17: 139.1 | L17: =IF(LEFT(F17,1)="W",1,0) -> 0 | M17: =IF(ISNUMBER(SEARCH("Round",D17)),"Playoffs","Regular Season") -> Playoffs | N17: =IFERROR(VLOOKUP(I17,Mapped_Owner,2,0),"") -> Hudspeath | O17: =VLOOKUP(D17,'Mapped Opponent'!$G$4:$H$22,2,0) -> 16 | Q17: ="Week "&O17 -> Week 16 | R17: =B17&D17 -> 2011Round 2 | S17: =IFERROR(__xludf.DUMMYFUNCTION("rank(J17,FILTER(J:J,R:R=R17))"),9.0) -> 9 | T17: =IFERROR(12-S17,0) -> 3 | U17: =12-T17 -> 9 | V17: =averageif(AllData!A:A,B17,AllData!R:R)/vlookup(B17,AllData!A:O,15,0) -> 88.551282
A18: =B18&C18&O18 -> 2011Guckien16 | B18: 2011 | C18: Guckien | D18: Round 2 | E18: 42253 | F18: W 118.2-92.3 | H18: Clay Rodge (6-9) | I18: Stephen Rooney | J18: 118.2 | K18: 92.3 | L18: =IF(LEFT(F18,1)="W",1,0) -> 1 | M18: =IF(ISNUMBER(SEARCH("Round",D18)),"Playoffs","Regular Season") -> Playoffs | N18: =IFERROR(VLOOKUP(I18,Mapped_Owner,2,0),"") -> Rooney/Jackson | O18: =VLOOKUP(D18,'Mapped Opponent'!$G$4:$H$22,2,0) -> 16 | Q18: ="Week "&O18 -> Week 16 | R18: =B18&D18 -> 2011Round 2 | S18: =IFERROR(__xludf.DUMMYFUNCTION("rank(J18,FILTER(J:J,R:R=R18))"),2.0) -> 2 | T18: =IFERROR(12-S18,0) -> 10 | U18: =12-T18 -> 2 | V18: =averageif(AllData!A:A,B18,AllData!R:R)/vlookup(B18,AllData!A:O,15,0) -> 88.551282
A19: =B19&C19&O19 -> 2011Rooney/Jackson16 | B19: 2011 | C19: Rooney/Jackson | D19: Round 2 | E19: 42164 | F19: L 92.3-118.2 | G19: at | H19: The McRB is back! (9-6) | I19: Tyler Guckien | J19: 92.3 | K19: 118.2 | L19: =IF(LEFT(F19,1)="W",1,0) -> 0 | M19: =IF(ISNUMBER(SEARCH("Round",D19)),"Playoffs","Regular Season") -> Playoffs | N19: =IFERROR(VLOOKUP(I19,Mapped_Owner,2,0),"") -> Guckien | O19: =VLOOKUP(D19,'Mapped Opponent'!$G$4:$H$22,2,0) -> 16 | Q19: ="Week "&O19 -> Week 16 | R19: =B19&D19 -> 2011Round 2 | S19: =IFERROR(__xludf.DUMMYFUNCTION("rank(J19,FILTER(J:J,R:R=R19))"),6.0) -> 6 | T19: =IFERROR(12-S19,0) -> 6 | U19: =12-T19 -> 6 | V19: =averageif(AllData!A:A,B19,AllData!R:R)/vlookup(B19,AllData!A:O,15,0) -> 88.551282
A20: =B20&C20&O20 -> 2011Buser16 | B20: 2011 | C20: Buser | D20: Round 2 | E20: 42281 | F20: W 99.7-51.8 | H20: Salt Bake City (9-6) | I20: R Saltiel | J20: 99.7 | K20: 51.8 | L20: =IF(LEFT(F20,1)="W",1,0) -> 1 | M20: =IF(ISNUMBER(SEARCH("Round",D20)),"Playoffs","Regular Season") -> Playoffs | N20: =IFERROR(VLOOKUP(I20,Mapped_Owner,2,0),"") -> Salty | O20: =VLOOKUP(D20,'Mapped Opponent'!$G$4:$H$22,2,0) -> 16 | Q20: ="Week "&O20 -> Week 16 | R20: =B20&D20 -> 2011Round 2 | S20: =IFERROR(__xludf.DUMMYFUNCTION("rank(J20,FILTER(J:J,R:R=R20))"),5.0) -> 5 | T20: =IFERROR(12-S20,0) -> 7 | U20: =12-T20 -> 5 | V20: =averageif(AllData!A:A,B20,AllData!R:R)/vlookup(B20,AllData!A:O,15,0) -> 88.551282
A21: =B21&C21&O21 -> 2011Pierson16 | B21: 2011 | C21: Pierson | D21: Round 2 | E21: 42252 | F21: L 67.9-109.9 | H21: Kibbles 'n Fitz (10-5) | I21: Tyler Howard | J21: 67.9 | K21: 109.9 | L21: =IF(LEFT(F21,1)="W",1,0) -> 0 | M21: =IF(ISNUMBER(SEARCH("Round",D21)),"Playoffs","Regular Season") -> Playoffs | N21: =IFERROR(VLOOKUP(I21,Mapped_Owner,2,0),"") -> T-How | O21: =VLOOKUP(D21,'Mapped Opponent'!$G$4:$H$22,2,0) -> 16 | Q21: ="Week "&O21 -> Week 16 | R21: =B21&D21 -> 2011Round 2 | S21: =IFERROR(__xludf.DUMMYFUNCTION("rank(J21,FILTER(J:J,R:R=R21))"),11.0) -> 11 | T21: =IFERROR(12-S21,0) -> 1 | U21: =12-T21 -> 11 | V21: =averageif(AllData!A:A,B21,AllData!R:R)/vlookup(B21,AllData!A:O,15,0) -> 88.551282
A22: =B22&C22&O22 -> 2011Cock16 | B22: 2011 | C22: Cock | D22: Round 2 | E22: 42134 | F22: L 76.1-91.9 | H22: Yo Adrian! (5-10) | I22: Michael Fellows | J22: 76.1 | K22: 91.9 | L22: =IF(LEFT(F22,1)="W",1,0) -> 0 | M22: =IF(ISNUMBER(SEARCH("Round",D22)),"Playoffs","Regular Season") -> Playoffs | N22: =IFERROR(VLOOKUP(I22,Mapped_Owner,2,0),"") -> Fellows | O22: =VLOOKUP(D22,'Mapped Opponent'!$G$4:$H$22,2,0) -> 16 | Q22: ="Week "&O22 -> Week 16 | R22: =B22&D22 -> 2011Round 2 | S22: =IFERROR(__xludf.DUMMYFUNCTION("rank(J22,FILTER(J:J,R:R=R22))"),8.0) -> 8 | T22: =IFERROR(12-S22,0) -> 4 | U22: =12-T22 -> 8 | V22: =averageif(AllData!A:A,B22,AllData!R:R)/vlookup(B22,AllData!A:O,15,0) -> 88.551282
A23: =B23&C23&O23 -> 2011Tayski16 | B23: 2011 | C23: Tayski | D23: Round 2 | E23: 42105 | F23: L 69.7-110.3 | G23: at | H23: Tat Five (7-8) | I23: Alex Kinniard | J23: 69.7 | K23: 110.3 | L23: =IF(LEFT(F23,1)="W",1,0) -> 0 | M23: =IF(ISNUMBER(SEARCH("Round",D23)),"Playoffs","Regular Season") -> Playoffs | N23: =IFERROR(VLOOKUP(I23,Mapped_Owner,2,0),"") -> KnardDawg | O23: =VLOOKUP(D23,'Mapped Opponent'!$G$4:$H$22,2,0) -> 16 | Q23: ="Week "&O23 -> Week 16 | R23: =B23&D23 -> 2011Round 2 | S23: =IFERROR(__xludf.DUMMYFUNCTION("rank(J23,FILTER(J:J,R:R=R23))"),10.0) -> 10 | T23: =IFERROR(12-S23,0) -> 2 | U23: =12-T23 -> 10 | V23: =averageif(AllData!A:A,B23,AllData!R:R)/vlookup(B23,AllData!A:O,15,0) -> 88.551282
A24: =B24&C24&O24 -> 2011KnardDawg16 | B24: 2011 | C24: KnardDawg | D24: Round 2 | E24: 42193 | F24: W 110.3-69.7 | H24: Team Weis (4-11) | I24: Taylor Weis | J24: 110.3 | K24: 69.7 | L24: =IF(LEFT(F24,1)="W",1,0) -> 1 | M24: =IF(ISNUMBER(SEARCH("Round",D24)),"Playoffs","Regular Season") -> Playoffs | N24: =IFERROR(VLOOKUP(I24,Mapped_Owner,2,0),"") -> Tayski | O24: =VLOOKUP(D24,'Mapped Opponent'!$G$4:$H$22,2,0) -> 16 | Q24: ="Week "&O24 -> Week 16 | R24: =B24&D24 -> 2011Round 2 | S24: =IFERROR(__xludf.DUMMYFUNCTION("rank(J24,FILTER(J:J,R:R=R24))"),3.0) -> 3 | T24: =IFERROR(12-S24,0) -> 9 | U24: =12-T24 -> 3 | V24: =averageif(AllData!A:A,B24,AllData!R:R)/vlookup(B24,AllData!A:O,15,0) -> 88.551282
A25: =B25&C25&O25 -> 2011T-How16 | B25: 2011 | C25: T-How | D25: Round 2 | E25: 42282 | F25: W 109.9-67.9 | G25: at | H25: Gambling Man (9-5) | I25: Pierson Curtis | J25: 109.9 | K25: 67.9 | L25: =IF(LEFT(F25,1)="W",1,0) -> 1 | M25: =IF(ISNUMBER(SEARCH("Round",D25)),"Playoffs","Regular Season") -> Playoffs | N25: =IFERROR(VLOOKUP(I25,Mapped_Owner,2,0),"") -> Pierson | O25: =VLOOKUP(D25,'Mapped Opponent'!$G$4:$H$22,2,0) -> 16 | Q25: ="Week "&O25 -> Week 16 | R25: =B25&D25 -> 2011Round 2 | S25: =IFERROR(__xludf.DUMMYFUNCTION("rank(J25,FILTER(J:J,R:R=R25))"),4.0) -> 4 | T25: =IFERROR(12-S25,0) -> 8 | U25: =12-T25 -> 4 | V25: =averageif(AllData!A:A,B25,AllData!R:R)/vlookup(B25,AllData!A:O,15,0) -> 88.551282
A26: =B26&C26&O26 -> 2011Hudspeath17 | B26: 2011 | C26: Hudspeath | D26: Round 3 | E26: 42254 | F26: W 123.3-93 | G26: at | H26: Show me your TDs (7-9) | I26: Jordan Shepherd | J26: 123.3 | K26: 93 | L26: =IF(LEFT(F26,1)="W",1,0) -> 1 | M26: =IF(ISNUMBER(SEARCH("Round",D26)),"Playoffs","Regular Season") -> Playoffs | N26: =IFERROR(VLOOKUP(I26,Mapped_Owner,2,0),"") -> Shep | O26: =VLOOKUP(D26,'Mapped Opponent'!$G$4:$H$22,2,0) -> 17 | Q26: ="Week "&O26 -> Week 17 | R26: =B26&D26 -> 2011Round 3 | S26: =IFERROR(__xludf.DUMMYFUNCTION("rank(J26,FILTER(J:J,R:R=R26))"),1.0) -> 1 | T26: =IFERROR(12-S26,0) -> 11 | U26: =12-T26 -> 1 | V26: =averageif(AllData!A:A,B26,AllData!R:R)/vlookup(B26,AllData!A:O,15,0) -> 88.551282
A27: =B27&C27&O27 -> 2011Salty17 | B27: 2011 | C27: Salty | D27: Round 3 | E27: 42254 | F27: L 76.6-103 | G27: at | H27: Gambling Man (10-5) | I27: Pierson Curtis | J27: 76.6 | K27: 103 | L27: =IF(LEFT(F27,1)="W",1,0) -> 0 | M27: =IF(ISNUMBER(SEARCH("Round",D27)),"Playoffs","Regular Season") -> Playoffs | N27: =IFERROR(VLOOKUP(I27,Mapped_Owner,2,0),"") -> Pierson | O27: =VLOOKUP(D27,'Mapped Opponent'!$G$4:$H$22,2,0) -> 17 | Q27: ="Week "&O27 -> Week 17 | R27: =B27&D27 -> 2011Round 3 | S27: =IFERROR(__xludf.DUMMYFUNCTION("rank(J27,FILTER(J:J,R:R=R27))"),8.0) -> 8 | T27: =IFERROR(12-S27,0) -> 4 | U27: =12-T27 -> 8 | V27: =averageif(AllData!A:A,B27,AllData!R:R)/vlookup(B27,AllData!A:O,15,0) -> 88.551282
A28: =B28&C28&O28 -> 2011Fellows17 | B28: 2011 | C28: Fellows | D28: Round 3 | E28: 42135 | F28: L 53.4-104.4 | G28: at | H28: Clay Rodge (7-9) | I28: Stephen Rooney | J28: 53.4 | K28: 104.4 | L28: =IF(LEFT(F28,1)="W",1,0) -> 0 | M28: =IF(ISNUMBER(SEARCH("Round",D28)),"Playoffs","Regular Season") -> Playoffs | N28: =IFERROR(VLOOKUP(I28,Mapped_Owner,2,0),"") -> Rooney/Jackson | O28: =VLOOKUP(D28,'Mapped Opponent'!$G$4:$H$22,2,0) -> 17 | Q28: ="Week "&O28 -> Week 17 | R28: =B28&D28 -> 2011Round 3 | S28: =IFERROR(__xludf.DUMMYFUNCTION("rank(J28,FILTER(J:J,R:R=R28))"),11.0) -> 11 | T28: =IFERROR(12-S28,0) -> 1 | U28: =12-T28 -> 11 | V28: =averageif(AllData!A:A,B28,AllData!R:R)/vlookup(B28,AllData!A:O,15,0) -> 88.551282
A29: =B29&C29&O29 -> 2011Shep17 | B29: 2011 | C29: Shep | D29: Round 3 | E29: 42194 | F29: L 93-123.3 | H29: Cutler's Year (9-7) | I29: matt hudspeath | J29: 93 | K29: 123.3 | L29: =IF(LEFT(F29,1)="W",1,0) -> 0 | M29: =IF(ISNUMBER(SEARCH("Round",D29)),"Playoffs","Regular Season") -> Playoffs | N29: =IFERROR(VLOOKUP(I29,Mapped_Owner,2,0),"") -> Hudspeath | O29: =VLOOKUP(D29,'Mapped Opponent'!$G$4:$H$22,2,0) -> 17 | Q29: ="Week "&O29 -> Week 17 | R29: =B29&D29 -> 2011Round 3 | S29: =IFERROR(__xludf.DUMMYFUNCTION("rank(J29,FILTER(J:J,R:R=R29))"),6.0) -> 6 | T29: =IFERROR(12-S29,0) -> 6 | U29: =12-T29 -> 6 | V29: =averageif(AllData!A:A,B29,AllData!R:R)/vlookup(B29,AllData!A:O,15,0) -> 88.551282
A30: =B30&C30&O30 -> 2011Guckien17 | B30: 2011 | C30: Guckien | D30: Round 3 | E30: 42254 | F30: L 74.7-106 | H30: Tat Five (8-8) | I30: Alex Kinniard | J30: 74.7 | K30: 106 | L30: =IF(LEFT(F30,1)="W",1,0) -> 0 | M30: =IF(ISNUMBER(SEARCH("Round",D30)),"Playoffs","Regular Season") -> Playoffs | N30: =IFERROR(VLOOKUP(I30,Mapped_Owner,2,0),"") -> KnardDawg | O30: =VLOOKUP(D30,'Mapped Opponent'!$G$4:$H$22,2,0) -> 17 | Q30: ="Week "&O30 -> Week 17 | R30: =B30&D30 -> 2011Round 3 | S30: =IFERROR(__xludf.DUMMYFUNCTION("rank(J30,FILTER(J:J,R:R=R30))"),9.0) -> 9 | T30: =IFERROR(12-S30,0) -> 3 | U30: =12-T30 -> 9 | V30: =averageif(AllData!A:A,B30,AllData!R:R)/vlookup(B30,AllData!A:O,15,0) -> 88.551282
A31: =B31&C31&O31 -> 2011Rooney/Jackson17 | B31: 2011 | C31: Rooney/Jackson | D31: Round 3 | E31: 42194 | F31: W 104.4-53.4 | H31: Yo Adrian! (5-11) | I31: Michael Fellows | J31: 104.4 | K31: 53.4 | L31: =IF(LEFT(F31,1)="W",1,0) -> 1 | M31: =IF(ISNUMBER(SEARCH("Round",D31)),"Playoffs","Regular Season") -> Playoffs | N31: =IFERROR(VLOOKUP(I31,Mapped_Owner,2,0),"") -> Fellows | O31: =VLOOKUP(D31,'Mapped Opponent'!$G$4:$H$22,2,0) -> 17 | Q31: ="Week "&O31 -> Week 17 | R31: =B31&D31 -> 2011Round 3 | S31: =IFERROR(__xludf.DUMMYFUNCTION("rank(J31,FILTER(J:J,R:R=R31))"),4.0) -> 4 | T31: =IFERROR(12-S31,0) -> 8 | U31: =12-T31 -> 4 | V31: =averageif(AllData!A:A,B31,AllData!R:R)/vlookup(B31,AllData!A:O,15,0) -> 88.551282
A32: =B32&C32&O32 -> 2011Buser17 | B32: 2011 | C32: Buser | D32: Round 3 | E32: 42312 | F32: W 105.3-71.9 | H32: Kibbles 'n Fitz (10-6) | I32: Tyler Howard | J32: 105.3 | K32: 71.9 | L32: =IF(LEFT(F32,1)="W",1,0) -> 1 | M32: =IF(ISNUMBER(SEARCH("Round",D32)),"Playoffs","Regular Season") -> Playoffs | N32: =IFERROR(VLOOKUP(I32,Mapped_Owner,2,0),"") -> T-How | O32: =VLOOKUP(D32,'Mapped Opponent'!$G$4:$H$22,2,0) -> 17 | Q32: ="Week "&O32 -> Week 17 | R32: =B32&D32 -> 2011Round 3 | S32: =IFERROR(__xludf.DUMMYFUNCTION("rank(J32,FILTER(J:J,R:R=R32))"),3.0) -> 3 | T32: =IFERROR(12-S32,0) -> 9 | U32: =12-T32 -> 3 | V32: =averageif(AllData!A:A,B32,AllData!R:R)/vlookup(B32,AllData!A:O,15,0) -> 88.551282
A33: =B33&C33&O33 -> 2011Pierson17 | B33: 2011 | C33: Pierson | D33: Round 3 | E33: 42282 | F33: W 103-76.6 | H33: Salt Bake City (9-7) | I33: R Saltiel | J33: 103 | K33: 76.6 | L33: =IF(LEFT(F33,1)="W",1,0) -> 1 | M33: =IF(ISNUMBER(SEARCH("Round",D33)),"Playoffs","Regular Season") -> Playoffs | N33: =IFERROR(VLOOKUP(I33,Mapped_Owner,2,0),"") -> Salty | O33: =VLOOKUP(D33,'Mapped Opponent'!$G$4:$H$22,2,0) -> 17 | Q33: ="Week "&O33 -> Week 17 | R33: =B33&D33 -> 2011Round 3 | S33: =IFERROR(__xludf.DUMMYFUNCTION("rank(J33,FILTER(J:J,R:R=R33))"),5.0) -> 5 | T33: =IFERROR(12-S33,0) -> 7 | U33: =12-T33 -> 5 | V33: =averageif(AllData!A:A,B33,AllData!R:R)/vlookup(B33,AllData!A:O,15,0) -> 88.551282
A34: =B34&C34&O34 -> 2011Cock17 | B34: 2011 | C34: Cock | D34: Round 3 | E34: 42135 | F34: L 44.6-80.1 | H34: Team Weis (5-11) | I34: Taylor Weis | J34: 44.6 | K34: 80.1 | L34: =IF(LEFT(F34,1)="W",1,0) -> 0 | M34: =IF(ISNUMBER(SEARCH("Round",D34)),"Playoffs","Regular Season") -> Playoffs | N34: =IFERROR(VLOOKUP(I34,Mapped_Owner,2,0),"") -> Tayski | O34: =VLOOKUP(D34,'Mapped Opponent'!$G$4:$H$22,2,0) -> 17 | Q34: ="Week "&O34 -> Week 17 | R34: =B34&D34 -> 2011Round 3 | S34: =IFERROR(__xludf.DUMMYFUNCTION("rank(J34,FILTER(J:J,R:R=R34))"),12.0) -> 12 | T34: =IFERROR(12-S34,0) -> 0 | U34: =12-T34 -> 12 | V34: =averageif(AllData!A:A,B34,AllData!R:R)/vlookup(B34,AllData!A:O,15,0) -> 88.551282
A35: =B35&C35&O35 -> 2011Tayski17 | B35: 2011 | C35: Tayski | D35: Round 3 | E35: 42135 | F35: W 80.1-44.6 | G35: at | H35: It's My Vick In a Box! (5-11) | I35: Chris Cochrane | J35: 80.1 | K35: 44.6 | L35: =IF(LEFT(F35,1)="W",1,0) -> 1 | M35: =IF(ISNUMBER(SEARCH("Round",D35)),"Playoffs","Regular Season") -> Playoffs | N35: =IFERROR(VLOOKUP(I35,Mapped_Owner,2,0),"") -> Cock | O35: =VLOOKUP(D35,'Mapped Opponent'!$G$4:$H$22,2,0) -> 17 | Q35: ="Week "&O35 -> Week 17 | R35: =B35&D35 -> 2011Round 3 | S35: =IFERROR(__xludf.DUMMYFUNCTION("rank(J35,FILTER(J:J,R:R=R35))"),7.0) -> 7 | T35: =IFERROR(12-S35,0) -> 5 | U35: =12-T35 -> 7 | V35: =averageif(AllData!A:A,B35,AllData!R:R)/vlookup(B35,AllData!A:O,15,0) -> 88.551282
A36: =B36&C36&O36 -> 2011KnardDawg17 | B36: 2011 | C36: KnardDawg | D36: Round 3 | E36: 42224 | F36: W 106-74.7 | G36: at | H36: The McRB is back! (9-7) | I36: Tyler Guckien | J36: 106 | K36: 74.7 | L36: =IF(LEFT(F36,1)="W",1,0) -> 1 | M36: =IF(ISNUMBER(SEARCH("Round",D36)),"Playoffs","Regular Season") -> Playoffs | N36: =IFERROR(VLOOKUP(I36,Mapped_Owner,2,0),"") -> Guckien | O36: =VLOOKUP(D36,'Mapped Opponent'!$G$4:$H$22,2,0) -> 17 | Q36: ="Week "&O36 -> Week 17 | R36: =B36&D36 -> 2011Round 3 | S36: =IFERROR(__xludf.DUMMYFUNCTION("rank(J36,FILTER(J:J,R:R=R36))"),2.0) -> 2 | T36: =IFERROR(12-S36,0) -> 10 | U36: =12-T36 -> 2 | V36: =averageif(AllData!A:A,B36,AllData!R:R)/vlookup(B36,AllData!A:O,15,0) -> 88.551282
A37: =B37&C37&O37 -> 2011T-How17 | B37: 2011 | C37: T-How | D37: Round 3 | E37: 42283 | F37: L 71.9-105.3 | G37: at | H37: Yes We Cam (11-4) | I37: Ed Buser | J37: 71.9 | K37: 105.3 | L37: =IF(LEFT(F37,1)="W",1,0) -> 0 | M37: =IF(ISNUMBER(SEARCH("Round",D37)),"Playoffs","Regular Season") -> Playoffs | N37: =IFERROR(VLOOKUP(I37,Mapped_Owner,2,0),"") -> Buser | O37: =VLOOKUP(D37,'Mapped Opponent'!$G$4:$H$22,2,0) -> 17 | Q37: ="Week "&O37 -> Week 17 | R37: =B37&D37 -> 2011Round 3 | S37: =IFERROR(__xludf.DUMMYFUNCTION("rank(J37,FILTER(J:J,R:R=R37))"),10.0) -> 10 | T37: =IFERROR(12-S37,0) -> 2 | U37: =12-T37 -> 10 | V37: =averageif(AllData!A:A,B37,AllData!R:R)/vlookup(B37,AllData!A:O,15,0) -> 88.551282
A38: =B38&C38&O38 -> 2011Hudspeath1 | B38: 2011 | C38: Hudspeath | D38: Week 1 | E38: 36526 | F38: W 97.4-74.8 | G38: at | H38: Clay Rodge (0-1) | I38: Stephen Rooney | J38: 97.4 | K38: 74.8 | L38: =IF(LEFT(F38,1)="W",1,0) -> 1 | M38: =IF(ISNUMBER(SEARCH("Round",D38)),"Playoffs","Regular Season") -> Regular Season | N38: =IFERROR(VLOOKUP(I38,Mapped_Owner,2,0),"") -> Rooney/Jackson | O38: =VLOOKUP(D38,'Mapped Opponent'!$G$4:$H$22,2,0) -> 1 | Q38: ="Week "&O38 -> Week 1 | R38: =B38&D38 -> 2011Week 1 | S38: =IFERROR(__xludf.DUMMYFUNCTION("rank(J38,FILTER(J:J,R:R=R38))"),5.0) -> 5 | T38: =IFERROR(12-S38,0) -> 7 | U38: =12-T38 -> 5 | V38: =averageif(AllData!A:A,B38,AllData!R:R)/vlookup(B38,AllData!A:O,15,0) -> 88.551282
A39: =B39&C39&O39 -> 2011Salty1 | B39: 2011 | C39: Salty | D39: Week 1 | E39: 36526 | F39: W 111.9-82.8 | G39: at | H39: Yo Adrian! (0-1) | I39: Michael Fellows | J39: 111.9 | K39: 82.8 | L39: =IF(LEFT(F39,1)="W",1,0) -> 1 | M39: =IF(ISNUMBER(SEARCH("Round",D39)),"Playoffs","Regular Season") -> Regular Season | N39: =IFERROR(VLOOKUP(I39,Mapped_Owner,2,0),"") -> Fellows | O39: =VLOOKUP(D39,'Mapped Opponent'!$G$4:$H$22,2,0) -> 1 | Q39: ="Week "&O39 -> Week 1 | R39: =B39&D39 -> 2011Week 1 | S39: =IFERROR(__xludf.DUMMYFUNCTION("rank(J39,FILTER(J:J,R:R=R39))"),2.0) -> 2 | T39: =IFERROR(12-S39,0) -> 10 | U39: =12-T39 -> 2 | V39: =averageif(AllData!A:A,B39,AllData!R:R)/vlookup(B39,AllData!A:O,15,0) -> 88.551282
A40: =B40&C40&O40 -> 2011Fellows1 | B40: 2011 | C40: Fellows | D40: Week 1 | E40: 0-1 | F40: L 82.8-111.9 | H40: Salt Bake City (1-0) | I40: R Saltiel | J40: 82.8 | K40: 111.9 | L40: =IF(LEFT(F40,1)="W",1,0) -> 0 | M40: =IF(ISNUMBER(SEARCH("Round",D40)),"Playoffs","Regular Season") -> Regular Season | N40: =IFERROR(VLOOKUP(I40,Mapped_Owner,2,0),"") -> Salty | O40: =VLOOKUP(D40,'Mapped Opponent'!$G$4:$H$22,2,0) -> 1 | Q40: ="Week "&O40 -> Week 1 | R40: =B40&D40 -> 2011Week 1 | S40: =IFERROR(__xludf.DUMMYFUNCTION("rank(J40,FILTER(J:J,R:R=R40))"),8.0) -> 8 | T40: =IFERROR(12-S40,0) -> 4 | U40: =12-T40 -> 8 | V40: =averageif(AllData!A:A,B40,AllData!R:R)/vlookup(B40,AllData!A:O,15,0) -> 88.551282
A41: =B41&C41&O41 -> 2011Shep1 | B41: 2011 | C41: Shep | D41: Week 1 | E41: 0-1 | F41: L 102.1-105.5 | G41: at | H41: The McRB is back! (1-0) | I41: Tyler Guckien | J41: 102.1 | K41: 105.5 | L41: =IF(LEFT(F41,1)="W",1,0) -> 0 | M41: =IF(ISNUMBER(SEARCH("Round",D41)),"Playoffs","Regular Season") -> Regular Season | N41: =IFERROR(VLOOKUP(I41,Mapped_Owner,2,0),"") -> Guckien | O41: =VLOOKUP(D41,'Mapped Opponent'!$G$4:$H$22,2,0) -> 1 | Q41: ="Week "&O41 -> Week 1 | R41: =B41&D41 -> 2011Week 1 | S41: =IFERROR(__xludf.DUMMYFUNCTION("rank(J41,FILTER(J:J,R:R=R41))"),4.0) -> 4 | T41: =IFERROR(12-S41,0) -> 8 | U41: =12-T41 -> 4 | V41: =averageif(AllData!A:A,B41,AllData!R:R)/vlookup(B41,AllData!A:O,15,0) -> 88.551282
A42: =B42&C42&O42 -> 2011Guckien1 | B42: 2011 | C42: Guckien | D42: Week 1 | E42: 36526 | F42: W 105.5-102.1 | H42: Show me your TDs (0-1) | I42: Jordan Shepherd | J42: 105.5 | K42: 102.1 | L42: =IF(LEFT(F42,1)="W",1,0) -> 1 | M42: =IF(ISNUMBER(SEARCH("Round",D42)),"Playoffs","Regular Season") -> Regular Season | N42: =IFERROR(VLOOKUP(I42,Mapped_Owner,2,0),"") -> Shep | O42: =VLOOKUP(D42,'Mapped Opponent'!$G$4:$H$22,2,0) -> 1 | Q42: ="Week "&O42 -> Week 1 | R42: =B42&D42 -> 2011Week 1 | S42: =IFERROR(__xludf.DUMMYFUNCTION("rank(J42,FILTER(J:J,R:R=R42))"),3.0) -> 3 | T42: =IFERROR(12-S42,0) -> 9 | U42: =12-T42 -> 3 | V42: =averageif(AllData!A:A,B42,AllData!R:R)/vlookup(B42,AllData!A:O,15,0) -> 88.551282
A43: =B43&C43&O43 -> 2011Rooney/Jackson1 | B43: 2011 | C43: Rooney/Jackson | D43: Week 1 | E43: 0-1 | F43: L 74.8-97.4 | H43: Cutler's Year (1-0) | I43: matt hudspeath | J43: 74.8 | K43: 97.4 | L43: =IF(LEFT(F43,1)="W",1,0) -> 0 | M43: =IF(ISNUMBER(SEARCH("Round",D43)),"Playoffs","Regular Season") -> Regular Season | N43: =IFERROR(VLOOKUP(I43,Mapped_Owner,2,0),"") -> Hudspeath | O43: =VLOOKUP(D43,'Mapped Opponent'!$G$4:$H$22,2,0) -> 1 | Q43: ="Week "&O43 -> Week 1 | R43: =B43&D43 -> 2011Week 1 | S43: =IFERROR(__xludf.DUMMYFUNCTION("rank(J43,FILTER(J:J,R:R=R43))"),10.0) -> 10 | T43: =IFERROR(12-S43,0) -> 2 | U43: =12-T43 -> 10 | V43: =averageif(AllData!A:A,B43,AllData!R:R)/vlookup(B43,AllData!A:O,15,0) -> 88.551282
A44: =B44&C44&O44 -> 2011Buser1 | B44: 2011 | C44: Buser | D44: Week 1 | E44: 0-1 | F44: L 56.8-86.8 | G44: at | H44: Gambling Man (1-0) | I44: Pierson Curtis | J44: 56.8 | K44: 86.8 | L44: =IF(LEFT(F44,1)="W",1,0) -> 0 | M44: =IF(ISNUMBER(SEARCH("Round",D44)),"Playoffs","Regular Season") -> Regular Season | N44: =IFERROR(VLOOKUP(I44,Mapped_Owner,2,0),"") -> Pierson | O44: =VLOOKUP(D44,'Mapped Opponent'!$G$4:$H$22,2,0) -> 1 | Q44: ="Week "&O44 -> Week 1 | R44: =B44&D44 -> 2011Week 1 | S44: =IFERROR(__xludf.DUMMYFUNCTION("rank(J44,FILTER(J:J,R:R=R44))"),11.0) -> 11 | T44: =IFERROR(12-S44,0) -> 1 | U44: =12-T44 -> 11 | V44: =averageif(AllData!A:A,B44,AllData!R:R)/vlookup(B44,AllData!A:O,15,0) -> 88.551282
A45: =B45&C45&O45 -> 2011Pierson1 | B45: 2011 | C45: Pierson | D45: Week 1 | E45: 36526 | F45: W 86.8-56.8 | H45: Yes We Cam (0-1) | I45: Ed Buser | J45: 86.8 | K45: 56.8 | L45: =IF(LEFT(F45,1)="W",1,0) -> 1 | M45: =IF(ISNUMBER(SEARCH("Round",D45)),"Playoffs","Regular Season") -> Regular Season | N45: =IFERROR(VLOOKUP(I45,Mapped_Owner,2,0),"") -> Buser | O45: =VLOOKUP(D45,'Mapped Opponent'!$G$4:$H$22,2,0) -> 1 | Q45: ="Week "&O45 -> Week 1 | R45: =B45&D45 -> 2011Week 1 | S45: =IFERROR(__xludf.DUMMYFUNCTION("rank(J45,FILTER(J:J,R:R=R45))"),7.0) -> 7 | T45: =IFERROR(12-S45,0) -> 5 | U45: =12-T45 -> 7 | V45: =averageif(AllData!A:A,B45,AllData!R:R)/vlookup(B45,AllData!A:O,15,0) -> 88.551282
A46: =B46&C46&O46 -> 2011Cock1 | B46: 2011 | C46: Cock | D46: Week 1 | E46: 0-1 | F46: L 79.8-91.8 | G46: at | H46: Kibbles 'n Fitz (1-0) | I46: Tyler Howard | J46: 79.8 | K46: 91.8 | L46: =IF(LEFT(F46,1)="W",1,0) -> 0 | M46: =IF(ISNUMBER(SEARCH("Round",D46)),"Playoffs","Regular Season") -> Regular Season | N46: =IFERROR(VLOOKUP(I46,Mapped_Owner,2,0),"") -> T-How | O46: =VLOOKUP(D46,'Mapped Opponent'!$G$4:$H$22,2,0) -> 1 | Q46: ="Week "&O46 -> Week 1 | R46: =B46&D46 -> 2011Week 1 | S46: =IFERROR(__xludf.DUMMYFUNCTION("rank(J46,FILTER(J:J,R:R=R46))"),9.0) -> 9 | T46: =IFERROR(12-S46,0) -> 3 | U46: =12-T46 -> 9 | V46: =averageif(AllData!A:A,B46,AllData!R:R)/vlookup(B46,AllData!A:O,15,0) -> 88.551282
A47: =B47&C47&O47 -> 2011Tayski1 | B47: 2011 | C47: Tayski | D47: Week 1 | E47: 0-1 | F47: L 56.4-131.3 | G47: at | H47: Tat Five (1-0) | I47: Alex Kinniard | J47: 56.4 | K47: 131.3 | L47: =IF(LEFT(F47,1)="W",1,0) -> 0 | M47: =IF(ISNUMBER(SEARCH("Round",D47)),"Playoffs","Regular Season") -> Regular Season | N47: =IFERROR(VLOOKUP(I47,Mapped_Owner,2,0),"") -> KnardDawg | O47: =VLOOKUP(D47,'Mapped Opponent'!$G$4:$H$22,2,0) -> 1 | Q47: ="Week "&O47 -> Week 1 | R47: =B47&D47 -> 2011Week 1 | S47: =IFERROR(__xludf.DUMMYFUNCTION("rank(J47,FILTER(J:J,R:R=R47))"),12.0) -> 12 | T47: =IFERROR(12-S47,0) -> 0 | U47: =12-T47 -> 12 | V47: =averageif(AllData!A:A,B47,AllData!R:R)/vlookup(B47,AllData!A:O,15,0) -> 88.551282
A48: =B48&C48&O48 -> 2011KnardDawg1 | B48: 2011 | C48: KnardDawg | D48: Week 1 | E48: 36526 | F48: W 131.3-56.4 | H48: Team Weis (0-1) | I48: Taylor Weis | J48: 131.3 | K48: 56.4 | L48: =IF(LEFT(F48,1)="W",1,0) -> 1 | M48: =IF(ISNUMBER(SEARCH("Round",D48)),"Playoffs","Regular Season") -> Regular Season | N48: =IFERROR(VLOOKUP(I48,Mapped_Owner,2,0),"") -> Tayski | O48: =VLOOKUP(D48,'Mapped Opponent'!$G$4:$H$22,2,0) -> 1 | Q48: ="Week "&O48 -> Week 1 | R48: =B48&D48 -> 2011Week 1 | S48: =IFERROR(__xludf.DUMMYFUNCTION("rank(J48,FILTER(J:J,R:R=R48))"),1.0) -> 1 | T48: =IFERROR(12-S48,0) -> 11 | U48: =12-T48 -> 1 | V48: =averageif(AllData!A:A,B48,AllData!R:R)/vlookup(B48,AllData!A:O,15,0) -> 88.551282
A49: =B49&C49&O49 -> 2011T-How1 | B49: 2011 | C49: T-How | D49: Week 1 | E49: 36526 | F49: W 91.8-79.8 | H49: It's My Vick In a Box! (0-1) | I49: Chris Cochrane | J49: 91.8 | K49: 79.8 | L49: =IF(LEFT(F49,1)="W",1,0) -> 1 | M49: =IF(ISNUMBER(SEARCH("Round",D49)),"Playoffs","Regular Season") -> Regular Season | N49: =IFERROR(VLOOKUP(I49,Mapped_Owner,2,0),"") -> Cock | O49: =VLOOKUP(D49,'Mapped Opponent'!$G$4:$H$22,2,0) -> 1 | Q49: ="Week "&O49 -> Week 1 | R49: =B49&D49 -> 2011Week 1 | S49: =IFERROR(__xludf.DUMMYFUNCTION("rank(J49,FILTER(J:J,R:R=R49))"),6.0) -> 6 | T49: =IFERROR(12-S49,0) -> 6 | U49: =12-T49 -> 6 | V49: =averageif(AllData!A:A,B49,AllData!R:R)/vlookup(B49,AllData!A:O,15,0) -> 88.551282
A50: =B50&C50&O50 -> 2011Hudspeath10 | B50: 2011 | C50: Hudspeath | D50: Week 10 | E50: 42129 | F50: W 119.6-63.4 | H50: Tat Five (4-6) | I50: Alex Kinniard | J50: 119.6 | K50: 63.4 | L50: =IF(LEFT(F50,1)="W",1,0) -> 1 | M50: =IF(ISNUMBER(SEARCH("Round",D50)),"Playoffs","Regular Season") -> Regular Season | N50: =IFERROR(VLOOKUP(I50,Mapped_Owner,2,0),"") -> KnardDawg | O50: =VLOOKUP(D50,'Mapped Opponent'!$G$4:$H$22,2,0) -> 10 | Q50: ="Week "&O50 -> Week 10 | R50: =B50&D50 -> 2011Week 10 | S50: =IFERROR(__xludf.DUMMYFUNCTION("rank(J50,FILTER(J:J,R:R=R50))"),2.0) -> 2 | T50: =IFERROR(12-S50,0) -> 10 | U50: =12-T50 -> 2 | V50: =averageif(AllData!A:A,B50,AllData!R:R)/vlookup(B50,AllData!A:O,15,0) -> 88.551282
A51: =B51&C51&O51 -> 2011Salty10 | B51: 2011 | C51: Salty | D51: Week 10 | E51: 42159 | F51: W 94.9-54.8 | H51: It's My Vick In a Box! (4-6) | I51: Chris Cochrane | J51: 94.9 | K51: 54.8 | L51: =IF(LEFT(F51,1)="W",1,0) -> 1 | M51: =IF(ISNUMBER(SEARCH("Round",D51)),"Playoffs","Regular Season") -> Regular Season | N51: =IFERROR(VLOOKUP(I51,Mapped_Owner,2,0),"") -> Cock | O51: =VLOOKUP(D51,'Mapped Opponent'!$G$4:$H$22,2,0) -> 10 | Q51: ="Week "&O51 -> Week 10 | R51: =B51&D51 -> 2011Week 10 | S51: =IFERROR(__xludf.DUMMYFUNCTION("rank(J51,FILTER(J:J,R:R=R51))"),4.0) -> 4 | T51: =IFERROR(12-S51,0) -> 8 | U51: =12-T51 -> 4 | V51: =averageif(AllData!A:A,B51,AllData!R:R)/vlookup(B51,AllData!A:O,15,0) -> 88.551282
A52: =B52&C52&O52 -> 2011Fellows10 | B52: 2011 | C52: Fellows | D52: Week 10 | E52: 42100 | F52: W 83.1-78.3 | H52: Team Weis (2-8) | I52: Taylor Weis | J52: 83.1 | K52: 78.3 | L52: =IF(LEFT(F52,1)="W",1,0) -> 1 | M52: =IF(ISNUMBER(SEARCH("Round",D52)),"Playoffs","Regular Season") -> Regular Season | N52: =IFERROR(VLOOKUP(I52,Mapped_Owner,2,0),"") -> Tayski | O52: =VLOOKUP(D52,'Mapped Opponent'!$G$4:$H$22,2,0) -> 10 | Q52: ="Week "&O52 -> Week 10 | R52: =B52&D52 -> 2011Week 10 | S52: =IFERROR(__xludf.DUMMYFUNCTION("rank(J52,FILTER(J:J,R:R=R52))"),6.0) -> 6 | T52: =IFERROR(12-S52,0) -> 6 | U52: =12-T52 -> 6 | V52: =averageif(AllData!A:A,B52,AllData!R:R)/vlookup(B52,AllData!A:O,15,0) -> 88.551282
A53: =B53&C53&O53 -> 2011Shep10 | B53: 2011 | C53: Shep | D53: Week 10 | E53: 42159 | F53: L 90.6-96.6 | H53: Kibbles 'n Fitz (7-3) | I53: Tyler Howard | J53: 90.6 | K53: 96.6 | L53: =IF(LEFT(F53,1)="W",1,0) -> 0 | M53: =IF(ISNUMBER(SEARCH("Round",D53)),"Playoffs","Regular Season") -> Regular Season | N53: =IFERROR(VLOOKUP(I53,Mapped_Owner,2,0),"") -> T-How | O53: =VLOOKUP(D53,'Mapped Opponent'!$G$4:$H$22,2,0) -> 10 | Q53: ="Week "&O53 -> Week 10 | R53: =B53&D53 -> 2011Week 10 | S53: =IFERROR(__xludf.DUMMYFUNCTION("rank(J53,FILTER(J:J,R:R=R53))"),5.0) -> 5 | T53: =IFERROR(12-S53,0) -> 7 | U53: =12-T53 -> 5 | V53: =averageif(AllData!A:A,B53,AllData!R:R)/vlookup(B53,AllData!A:O,15,0) -> 88.551282
A54: =B54&C54&O54 -> 2011Guckien10 | B54: 2011 | C54: Guckien | D54: Week 10 | E54: 42159 | F54: W 81.6-79.1 | H54: Yes We Cam (6-4) | I54: Ed Buser | J54: 81.6 | K54: 79.1 | L54: =IF(LEFT(F54,1)="W",1,0) -> 1 | M54: =IF(ISNUMBER(SEARCH("Round",D54)),"Playoffs","Regular Season") -> Regular Season | N54: =IFERROR(VLOOKUP(I54,Mapped_Owner,2,0),"") -> Buser | O54: =VLOOKUP(D54,'Mapped Opponent'!$G$4:$H$22,2,0) -> 10 | Q54: ="Week "&O54 -> Week 10 | R54: =B54&D54 -> 2011Week 10 | S54: =IFERROR(__xludf.DUMMYFUNCTION("rank(J54,FILTER(J:J,R:R=R54))"),7.0) -> 7 | T54: =IFERROR(12-S54,0) -> 5 | U54: =12-T54 -> 7 | V54: =averageif(AllData!A:A,B54,AllData!R:R)/vlookup(B54,AllData!A:O,15,0) -> 88.551282
A55: =B55&C55&O55 -> 2011Rooney/Jackson10 | B55: 2011 | C55: Rooney/Jackson | D55: Week 10 | E55: 42070 | F55: L 76.7-120.8 | H55: Gambling Man (7-3) | I55: Pierson Curtis | J55: 76.7 | K55: 120.8 | L55: =IF(LEFT(F55,1)="W",1,0) -> 0 | M55: =IF(ISNUMBER(SEARCH("Round",D55)),"Playoffs","Regular Season") -> Regular Season | N55: =IFERROR(VLOOKUP(I55,Mapped_Owner,2,0),"") -> Pierson | O55: =VLOOKUP(D55,'Mapped Opponent'!$G$4:$H$22,2,0) -> 10 | Q55: ="Week "&O55 -> Week 10 | R55: =B55&D55 -> 2011Week 10 | S55: =IFERROR(__xludf.DUMMYFUNCTION("rank(J55,FILTER(J:J,R:R=R55))"),10.0) -> 10 | T55: =IFERROR(12-S55,0) -> 2 | U55: =12-T55 -> 10 | V55: =averageif(AllData!A:A,B55,AllData!R:R)/vlookup(B55,AllData!A:O,15,0) -> 88.551282
A56: =B56&C56&O56 -> 2011Buser10 | B56: 2011 | C56: Buser | D56: Week 10 | E56: 42159 | F56: L 79.1-81.6 | G56: at | H56: The McRB is back! (6-4) | I56: Tyler Guckien | J56: 79.1 | K56: 81.6 | L56: =IF(LEFT(F56,1)="W",1,0) -> 0 | M56: =IF(ISNUMBER(SEARCH("Round",D56)),"Playoffs","Regular Season") -> Regular Season | N56: =IFERROR(VLOOKUP(I56,Mapped_Owner,2,0),"") -> Guckien | O56: =VLOOKUP(D56,'Mapped Opponent'!$G$4:$H$22,2,0) -> 10 | Q56: ="Week "&O56 -> Week 10 | R56: =B56&D56 -> 2011Week 10 | S56: =IFERROR(__xludf.DUMMYFUNCTION("rank(J56,FILTER(J:J,R:R=R56))"),8.0) -> 8 | T56: =IFERROR(12-S56,0) -> 4 | U56: =12-T56 -> 8 | V56: =averageif(AllData!A:A,B56,AllData!R:R)/vlookup(B56,AllData!A:O,15,0) -> 88.551282
A57: =B57&C57&O57 -> 2011Pierson10 | B57: 2011 | C57: Pierson | D57: Week 10 | E57: 42188 | F57: W 120.8-76.7 | G57: at | H57: Clay Rodge (3-7) | I57: Stephen Rooney | J57: 120.8 | K57: 76.7 | L57: =IF(LEFT(F57,1)="W",1,0) -> 1 | M57: =IF(ISNUMBER(SEARCH("Round",D57)),"Playoffs","Regular Season") -> Regular Season | N57: =IFERROR(VLOOKUP(I57,Mapped_Owner,2,0),"") -> Rooney/Jackson | O57: =VLOOKUP(D57,'Mapped Opponent'!$G$4:$H$22,2,0) -> 10 | Q57: ="Week "&O57 -> Week 10 | R57: =B57&D57 -> 2011Week 10 | S57: =IFERROR(__xludf.DUMMYFUNCTION("rank(J57,FILTER(J:J,R:R=R57))"),1.0) -> 1 | T57: =IFERROR(12-S57,0) -> 11 | U57: =12-T57 -> 1 | V57: =averageif(AllData!A:A,B57,AllData!R:R)/vlookup(B57,AllData!A:O,15,0) -> 88.551282
A58: =B58&C58&O58 -> 2011Cock10 | B58: 2011 | C58: Cock | D58: Week 10 | E58: 42100 | F58: L 54.8-94.9 | G58: at | H58: Salt Bake City (6-4) | I58: R Saltiel | J58: 54.8 | K58: 94.9 | L58: =IF(LEFT(F58,1)="W",1,0) -> 0 | M58: =IF(ISNUMBER(SEARCH("Round",D58)),"Playoffs","Regular Season") -> Regular Season | N58: =IFERROR(VLOOKUP(I58,Mapped_Owner,2,0),"") -> Salty | O58: =VLOOKUP(D58,'Mapped Opponent'!$G$4:$H$22,2,0) -> 10 | Q58: ="Week "&O58 -> Week 10 | R58: =B58&D58 -> 2011Week 10 | S58: =IFERROR(__xludf.DUMMYFUNCTION("rank(J58,FILTER(J:J,R:R=R58))"),12.0) -> 12 | T58: =IFERROR(12-S58,0) -> 0 | U58: =12-T58 -> 12 | V58: =averageif(AllData!A:A,B58,AllData!R:R)/vlookup(B58,AllData!A:O,15,0) -> 88.551282
A59: =B59&C59&O59 -> 2011Tayski10 | B59: 2011 | C59: Tayski | D59: Week 10 | E59: 42043 | F59: L 78.3-83.1 | G59: at | H59: Yo Adrian! (4-6) | I59: Michael Fellows | J59: 78.3 | K59: 83.1 | L59: =IF(LEFT(F59,1)="W",1,0) -> 0 | M59: =IF(ISNUMBER(SEARCH("Round",D59)),"Playoffs","Regular Season") -> Regular Season | N59: =IFERROR(VLOOKUP(I59,Mapped_Owner,2,0),"") -> Fellows | O59: =VLOOKUP(D59,'Mapped Opponent'!$G$4:$H$22,2,0) -> 10 | Q59: ="Week "&O59 -> Week 10 | R59: =B59&D59 -> 2011Week 10 | S59: =IFERROR(__xludf.DUMMYFUNCTION("rank(J59,FILTER(J:J,R:R=R59))"),9.0) -> 9 | T59: =IFERROR(12-S59,0) -> 3 | U59: =12-T59 -> 9 | V59: =averageif(AllData!A:A,B59,AllData!R:R)/vlookup(B59,AllData!A:O,15,0) -> 88.551282
A60: =B60&C60&O60 -> 2011KnardDawg10 | B60: 2011 | C60: KnardDawg | D60: Week 10 | E60: 42100 | F60: L 63.4-119.6 | G60: at | H60: Cutler's Year (5-5) | I60: matt hudspeath | J60: 63.4 | K60: 119.6 | L60: =IF(LEFT(F60,1)="W",1,0) -> 0 | M60: =IF(ISNUMBER(SEARCH("Round",D60)),"Playoffs","Regular Season") -> Regular Season | N60: =IFERROR(VLOOKUP(I60,Mapped_Owner,2,0),"") -> Hudspeath | O60: =VLOOKUP(D60,'Mapped Opponent'!$G$4:$H$22,2,0) -> 10 | Q60: ="Week "&O60 -> Week 10 | R60: =B60&D60 -> 2011Week 10 | S60: =IFERROR(__xludf.DUMMYFUNCTION("rank(J60,FILTER(J:J,R:R=R60))"),11.0) -> 11 | T60: =IFERROR(12-S60,0) -> 1 | U60: =12-T60 -> 11 | V60: =averageif(AllData!A:A,B60,AllData!R:R)/vlookup(B60,AllData!A:O,15,0) -> 88.551282
A61: =B61&C61&O61 -> 2011T-How10 | B61: 2011 | C61: T-How | D61: Week 10 | E61: 42188 | F61: W 96.6-90.6 | G61: at | H61: Show me your TDs (6-4) | I61: Jordan Shepherd | J61: 96.6 | K61: 90.6 | L61: =IF(LEFT(F61,1)="W",1,0) -> 1 | M61: =IF(ISNUMBER(SEARCH("Round",D61)),"Playoffs","Regular Season") -> Regular Season | N61: =IFERROR(VLOOKUP(I61,Mapped_Owner,2,0),"") -> Shep | O61: =VLOOKUP(D61,'Mapped Opponent'!$G$4:$H$22,2,0) -> 10 | Q61: ="Week "&O61 -> Week 10 | R61: =B61&D61 -> 2011Week 10 | S61: =IFERROR(__xludf.DUMMYFUNCTION("rank(J61,FILTER(J:J,R:R=R61))"),3.0) -> 3 | T61: =IFERROR(12-S61,0) -> 9 | U61: =12-T61 -> 3 | V61: =averageif(AllData!A:A,B61,AllData!R:R)/vlookup(B61,AllData!A:O,15,0) -> 88.551282
A62: =B62&C62&O62 -> 2011Hudspeath11 | B62: 2011 | C62: Hudspeath | D62: Week 11 | E62: 42160 | F62: W 76.6-74 | G62: at | H62: Team Weis (2-9) | I62: Taylor Weis | J62: 76.6 | K62: 74 | L62: =IF(LEFT(F62,1)="W",1,0) -> 1 | M62: =IF(ISNUMBER(SEARCH("Round",D62)),"Playoffs","Regular Season") -> Regular Season | N62: =IFERROR(VLOOKUP(I62,Mapped_Owner,2,0),"") -> Tayski | O62: =VLOOKUP(D62,'Mapped Opponent'!$G$4:$H$22,2,0) -> 11 | Q62: ="Week "&O62 -> Week 11 | R62: =B62&D62 -> 2011Week 11 | S62: =IFERROR(__xludf.DUMMYFUNCTION("rank(J62,FILTER(J:J,R:R=R62))"),8.0) -> 8 | T62: =IFERROR(12-S62,0) -> 4 | U62: =12-T62 -> 8 | V62: =averageif(AllData!A:A,B62,AllData!R:R)/vlookup(B62,AllData!A:O,15,0) -> 88.551282
A63: =B63&C63&O63 -> 2011Salty11 | B63: 2011 | C63: Salty | D63: Week 11 | E63: 42189 | F63: W 116.5-58.4 | G63: at | H63: Gambling Man (7-4) | I63: Pierson Curtis | J63: 116.5 | K63: 58.4 | L63: =IF(LEFT(F63,1)="W",1,0) -> 1 | M63: =IF(ISNUMBER(SEARCH("Round",D63)),"Playoffs","Regular Season") -> Regular Season | N63: =IFERROR(VLOOKUP(I63,Mapped_Owner,2,0),"") -> Pierson | O63: =VLOOKUP(D63,'Mapped Opponent'!$G$4:$H$22,2,0) -> 11 | Q63: ="Week "&O63 -> Week 11 | R63: =B63&D63 -> 2011Week 11 | S63: =IFERROR(__xludf.DUMMYFUNCTION("rank(J63,FILTER(J:J,R:R=R63))"),1.0) -> 1 | T63: =IFERROR(12-S63,0) -> 11 | U63: =12-T63 -> 1 | V63: =averageif(AllData!A:A,B63,AllData!R:R)/vlookup(B63,AllData!A:O,15,0) -> 88.551282
A64: =B64&C64&O64 -> 2011Fellows11 | B64: 2011 | C64: Fellows | D64: Week 11 | E64: 42101 | F64: L 84.7-90.6 | G64: at | H64: It's My Vick In a Box! (5-6) | I64: Chris Cochrane | J64: 84.7 | K64: 90.6 | L64: =IF(LEFT(F64,1)="W",1,0) -> 0 | M64: =IF(ISNUMBER(SEARCH("Round",D64)),"Playoffs","Regular Season") -> Regular Season | N64: =IFERROR(VLOOKUP(I64,Mapped_Owner,2,0),"") -> Cock | O64: =VLOOKUP(D64,'Mapped Opponent'!$G$4:$H$22,2,0) -> 11 | Q64: ="Week "&O64 -> Week 11 | R64: =B64&D64 -> 2011Week 11 | S64: =IFERROR(__xludf.DUMMYFUNCTION("rank(J64,FILTER(J:J,R:R=R64))"),7.0) -> 7 | T64: =IFERROR(12-S64,0) -> 5 | U64: =12-T64 -> 7 | V64: =averageif(AllData!A:A,B64,AllData!R:R)/vlookup(B64,AllData!A:O,15,0) -> 88.551282
A65: =B65&C65&O65 -> 2011Shep11 | B65: 2011 | C65: Shep | D65: Week 11 | E65: 42160 | F65: L 94.4-107.6 | G65: at | H65: Tat Five (5-6) | I65: Alex Kinniard | J65: 94.4 | K65: 107.6 | L65: =IF(LEFT(F65,1)="W",1,0) -> 0 | M65: =IF(ISNUMBER(SEARCH("Round",D65)),"Playoffs","Regular Season") -> Regular Season | N65: =IFERROR(VLOOKUP(I65,Mapped_Owner,2,0),"") -> KnardDawg | O65: =VLOOKUP(D65,'Mapped Opponent'!$G$4:$H$22,2,0) -> 11 | Q65: ="Week "&O65 -> Week 11 | R65: =B65&D65 -> 2011Week 11 | S65: =IFERROR(__xludf.DUMMYFUNCTION("rank(J65,FILTER(J:J,R:R=R65))"),4.0) -> 4 | T65: =IFERROR(12-S65,0) -> 8 | U65: =12-T65 -> 4 | V65: =averageif(AllData!A:A,B65,AllData!R:R)/vlookup(B65,AllData!A:O,15,0) -> 88.551282
A66: =B66&C66&O66 -> 2011Guckien11 | B66: 2011 | C66: Guckien | D66: Week 11 | E66: 42160 | F66: L 71.5-95.1 | G66: at | H66: Kibbles 'n Fitz (8-3) | I66: Tyler Howard | J66: 71.5 | K66: 95.1 | L66: =IF(LEFT(F66,1)="W",1,0) -> 0 | M66: =IF(ISNUMBER(SEARCH("Round",D66)),"Playoffs","Regular Season") -> Regular Season | N66: =IFERROR(VLOOKUP(I66,Mapped_Owner,2,0),"") -> T-How | O66: =VLOOKUP(D66,'Mapped Opponent'!$G$4:$H$22,2,0) -> 11 | Q66: ="Week "&O66 -> Week 11 | R66: =B66&D66 -> 2011Week 11 | S66: =IFERROR(__xludf.DUMMYFUNCTION("rank(J66,FILTER(J:J,R:R=R66))"),10.0) -> 10 | T66: =IFERROR(12-S66,0) -> 2 | U66: =12-T66 -> 10 | V66: =averageif(AllData!A:A,B66,AllData!R:R)/vlookup(B66,AllData!A:O,15,0) -> 88.551282
A67: =B67&C67&O67 -> 2011Rooney/Jackson11 | B67: 2011 | C67: Rooney/Jackson | D67: Week 11 | E67: 42071 | F67: L 68.9-88.5 | G67: at | H67: Yes We Cam (7-4) | I67: Ed Buser | J67: 68.9 | K67: 88.5 | L67: =IF(LEFT(F67,1)="W",1,0) -> 0 | M67: =IF(ISNUMBER(SEARCH("Round",D67)),"Playoffs","Regular Season") -> Regular Season | N67: =IFERROR(VLOOKUP(I67,Mapped_Owner,2,0),"") -> Buser | O67: =VLOOKUP(D67,'Mapped Opponent'!$G$4:$H$22,2,0) -> 11 | Q67: ="Week "&O67 -> Week 11 | R67: =B67&D67 -> 2011Week 11 | S67: =IFERROR(__xludf.DUMMYFUNCTION("rank(J67,FILTER(J:J,R:R=R67))"),11.0) -> 11 | T67: =IFERROR(12-S67,0) -> 1 | U67: =12-T67 -> 11 | V67: =averageif(AllData!A:A,B67,AllData!R:R)/vlookup(B67,AllData!A:O,15,0) -> 88.551282
A68: =B68&C68&O68 -> 2011Buser11 | B68: 2011 | C68: Buser | D68: Week 11 | E68: 42189 | F68: W 88.5-68.9 | H68: Clay Rodge (3-8) | I68: Stephen Rooney | J68: 88.5 | K68: 68.9 | L68: =IF(LEFT(F68,1)="W",1,0) -> 1 | M68: =IF(ISNUMBER(SEARCH("Round",D68)),"Playoffs","Regular Season") -> Regular Season | N68: =IFERROR(VLOOKUP(I68,Mapped_Owner,2,0),"") -> Rooney/Jackson | O68: =VLOOKUP(D68,'Mapped Opponent'!$G$4:$H$22,2,0) -> 11 | Q68: ="Week "&O68 -> Week 11 | R68: =B68&D68 -> 2011Week 11 | S68: =IFERROR(__xludf.DUMMYFUNCTION("rank(J68,FILTER(J:J,R:R=R68))"),6.0) -> 6 | T68: =IFERROR(12-S68,0) -> 6 | U68: =12-T68 -> 6 | V68: =averageif(AllData!A:A,B68,AllData!R:R)/vlookup(B68,AllData!A:O,15,0) -> 88.551282
A69: =B69&C69&O69 -> 2011Pierson11 | B69: 2011 | C69: Pierson | D69: Week 11 | E69: 42189 | F69: L 58.4-116.5 | H69: Salt Bake City (7-4) | I69: R Saltiel | J69: 58.4 | K69: 116.5 | L69: =IF(LEFT(F69,1)="W",1,0) -> 0 | M69: =IF(ISNUMBER(SEARCH("Round",D69)),"Playoffs","Regular Season") -> Regular Season | N69: =IFERROR(VLOOKUP(I69,Mapped_Owner,2,0),"") -> Salty | O69: =VLOOKUP(D69,'Mapped Opponent'!$G$4:$H$22,2,0) -> 11 | Q69: ="Week "&O69 -> Week 11 | R69: =B69&D69 -> 2011Week 11 | S69: =IFERROR(__xludf.DUMMYFUNCTION("rank(J69,FILTER(J:J,R:R=R69))"),12.0) -> 12 | T69: =IFERROR(12-S69,0) -> 0 | U69: =12-T69 -> 12 | V69: =averageif(AllData!A:A,B69,AllData!R:R)/vlookup(B69,AllData!A:O,15,0) -> 88.551282
A70: =B70&C70&O70 -> 2011Cock11 | B70: 2011 | C70: Cock | D70: Week 11 | E70: 42130 | F70: W 90.6-84.7 | H70: Yo Adrian! (4-7) | I70: Michael Fellows | J70: 90.6 | K70: 84.7 | L70: =IF(LEFT(F70,1)="W",1,0) -> 1 | M70: =IF(ISNUMBER(SEARCH("Round",D70)),"Playoffs","Regular Season") -> Regular Season | N70: =IFERROR(VLOOKUP(I70,Mapped_Owner,2,0),"") -> Fellows | O70: =VLOOKUP(D70,'Mapped Opponent'!$G$4:$H$22,2,0) -> 11 | Q70: ="Week "&O70 -> Week 11 | R70: =B70&D70 -> 2011Week 11 | S70: =IFERROR(__xludf.DUMMYFUNCTION("rank(J70,FILTER(J:J,R:R=R70))"),5.0) -> 5 | T70: =IFERROR(12-S70,0) -> 7 | U70: =12-T70 -> 5 | V70: =averageif(AllData!A:A,B70,AllData!R:R)/vlookup(B70,AllData!A:O,15,0) -> 88.551282
A71: =B71&C71&O71 -> 2011Tayski11 | B71: 2011 | C71: Tayski | D71: Week 11 | E71: 42044 | F71: L 74-76.6 | H71: Cutler's Year (6-5) | I71: matt hudspeath | J71: 74 | K71: 76.6 | L71: =IF(LEFT(F71,1)="W",1,0) -> 0 | M71: =IF(ISNUMBER(SEARCH("Round",D71)),"Playoffs","Regular Season") -> Regular Season | N71: =IFERROR(VLOOKUP(I71,Mapped_Owner,2,0),"") -> Hudspeath | O71: =VLOOKUP(D71,'Mapped Opponent'!$G$4:$H$22,2,0) -> 11 | Q71: ="Week "&O71 -> Week 11 | R71: =B71&D71 -> 2011Week 11 | S71: =IFERROR(__xludf.DUMMYFUNCTION("rank(J71,FILTER(J:J,R:R=R71))"),9.0) -> 9 | T71: =IFERROR(12-S71,0) -> 3 | U71: =12-T71 -> 9 | V71: =averageif(AllData!A:A,B71,AllData!R:R)/vlookup(B71,AllData!A:O,15,0) -> 88.551282
A72: =B72&C72&O72 -> 2011KnardDawg11 | B72: 2011 | C72: KnardDawg | D72: Week 11 | E72: 42130 | F72: W 107.6-94.4 | H72: Show me your TDs (6-5) | I72: Jordan Shepherd | J72: 107.6 | K72: 94.4 | L72: =IF(LEFT(F72,1)="W",1,0) -> 1 | M72: =IF(ISNUMBER(SEARCH("Round",D72)),"Playoffs","Regular Season") -> Regular Season | N72: =IFERROR(VLOOKUP(I72,Mapped_Owner,2,0),"") -> Shep | O72: =VLOOKUP(D72,'Mapped Opponent'!$G$4:$H$22,2,0) -> 11 | Q72: ="Week "&O72 -> Week 11 | R72: =B72&D72 -> 2011Week 11 | S72: =IFERROR(__xludf.DUMMYFUNCTION("rank(J72,FILTER(J:J,R:R=R72))"),2.0) -> 2 | T72: =IFERROR(12-S72,0) -> 10 | U72: =12-T72 -> 2 | V72: =averageif(AllData!A:A,B72,AllData!R:R)/vlookup(B72,AllData!A:O,15,0) -> 88.551282
A73: =B73&C73&O73 -> 2011T-How11 | B73: 2011 | C73: T-How | D73: Week 11 | E73: 42219 | F73: W 95.1-71.5 | H73: The McRB is back! (6-5) | I73: Tyler Guckien | J73: 95.1 | K73: 71.5 | L73: =IF(LEFT(F73,1)="W",1,0) -> 1 | M73: =IF(ISNUMBER(SEARCH("Round",D73)),"Playoffs","Regular Season") -> Regular Season | N73: =IFERROR(VLOOKUP(I73,Mapped_Owner,2,0),"") -> Guckien | O73: =VLOOKUP(D73,'Mapped Opponent'!$G$4:$H$22,2,0) -> 11 | Q73: ="Week "&O73 -> Week 11 | R73: =B73&D73 -> 2011Week 11 | S73: =IFERROR(__xludf.DUMMYFUNCTION("rank(J73,FILTER(J:J,R:R=R73))"),3.0) -> 3 | T73: =IFERROR(12-S73,0) -> 9 | U73: =12-T73 -> 3 | V73: =averageif(AllData!A:A,B73,AllData!R:R)/vlookup(B73,AllData!A:O,15,0) -> 88.551282
A74: =B74&C74&O74 -> 2011Hudspeath12 | B74: 2011 | C74: Hudspeath | D74: Week 12 | E74: 42190 | F74: W 114.2-70.6 | G74: at | H74: It's My Vick In a Box! (5-7) | I74: Chris Cochrane | J74: 114.2 | K74: 70.6 | L74: =IF(LEFT(F74,1)="W",1,0) -> 1 | M74: =IF(ISNUMBER(SEARCH("Round",D74)),"Playoffs","Regular Season") -> Regular Season | N74: =IFERROR(VLOOKUP(I74,Mapped_Owner,2,0),"") -> Cock | O74: =VLOOKUP(D74,'Mapped Opponent'!$G$4:$H$22,2,0) -> 12 | Q74: ="Week "&O74 -> Week 12 | R74: =B74&D74 -> 2011Week 12 | S74: =IFERROR(__xludf.DUMMYFUNCTION("rank(J74,FILTER(J:J,R:R=R74))"),3.0) -> 3 | T74: =IFERROR(12-S74,0) -> 9 | U74: =12-T74 -> 3 | V74: =averageif(AllData!A:A,B74,AllData!R:R)/vlookup(B74,AllData!A:O,15,0) -> 88.551282
A75: =B75&C75&O75 -> 2011Salty12 | B75: 2011 | C75: Salty | D75: Week 12 | E75: 42190 | F75: L 74.9-116.1 | G75: at | H75: Yes We Cam (8-4) | I75: Ed Buser | J75: 74.9 | K75: 116.1 | L75: =IF(LEFT(F75,1)="W",1,0) -> 0 | M75: =IF(ISNUMBER(SEARCH("Round",D75)),"Playoffs","Regular Season") -> Regular Season | N75: =IFERROR(VLOOKUP(I75,Mapped_Owner,2,0),"") -> Buser | O75: =VLOOKUP(D75,'Mapped Opponent'!$G$4:$H$22,2,0) -> 12 | Q75: ="Week "&O75 -> Week 12 | R75: =B75&D75 -> 2011Week 12 | S75: =IFERROR(__xludf.DUMMYFUNCTION("rank(J75,FILTER(J:J,R:R=R75))"),9.0) -> 9 | T75: =IFERROR(12-S75,0) -> 3 | U75: =12-T75 -> 9 | V75: =averageif(AllData!A:A,B75,AllData!R:R)/vlookup(B75,AllData!A:O,15,0) -> 88.551282
A76: =B76&C76&O76 -> 2011Fellows12 | B76: 2011 | C76: Fellows | D76: Week 12 | E76: 42102 | F76: L 62.3-98.1 | G76: at | H76: Gambling Man (8-4) | I76: Pierson Curtis | J76: 62.3 | K76: 98.1 | L76: =IF(LEFT(F76,1)="W",1,0) -> 0 | M76: =IF(ISNUMBER(SEARCH("Round",D76)),"Playoffs","Regular Season") -> Regular Season | N76: =IFERROR(VLOOKUP(I76,Mapped_Owner,2,0),"") -> Pierson | O76: =VLOOKUP(D76,'Mapped Opponent'!$G$4:$H$22,2,0) -> 12 | Q76: ="Week "&O76 -> Week 12 | R76: =B76&D76 -> 2011Week 12 | S76: =IFERROR(__xludf.DUMMYFUNCTION("rank(J76,FILTER(J:J,R:R=R76))"),12.0) -> 12 | T76: =IFERROR(12-S76,0) -> 0 | U76: =12-T76 -> 12 | V76: =averageif(AllData!A:A,B76,AllData!R:R)/vlookup(B76,AllData!A:O,15,0) -> 88.551282
A77: =B77&C77&O77 -> 2011Shep12 | B77: 2011 | C77: Shep | D77: Week 12 | E77: 42161 | F77: L 81.2-83.3 | G77: at | H77: Team Weis (3-9) | I77: Taylor Weis | J77: 81.2 | K77: 83.3 | L77: =IF(LEFT(F77,1)="W",1,0) -> 0 | M77: =IF(ISNUMBER(SEARCH("Round",D77)),"Playoffs","Regular Season") -> Regular Season | N77: =IFERROR(VLOOKUP(I77,Mapped_Owner,2,0),"") -> Tayski | O77: =VLOOKUP(D77,'Mapped Opponent'!$G$4:$H$22,2,0) -> 12 | Q77: ="Week "&O77 -> Week 12 | R77: =B77&D77 -> 2011Week 12 | S77: =IFERROR(__xludf.DUMMYFUNCTION("rank(J77,FILTER(J:J,R:R=R77))"),8.0) -> 8 | T77: =IFERROR(12-S77,0) -> 4 | U77: =12-T77 -> 8 | V77: =averageif(AllData!A:A,B77,AllData!R:R)/vlookup(B77,AllData!A:O,15,0) -> 88.551282
A78: =B78&C78&O78 -> 2011Guckien12 | B78: 2011 | C78: Guckien | D78: Week 12 | E78: 42161 | F78: L 89.6-116.4 | G78: at | H78: Tat Five (6-6) | I78: Alex Kinniard | J78: 89.6 | K78: 116.4 | L78: =IF(LEFT(F78,1)="W",1,0) -> 0 | M78: =IF(ISNUMBER(SEARCH("Round",D78)),"Playoffs","Regular Season") -> Regular Season | N78: =IFERROR(VLOOKUP(I78,Mapped_Owner,2,0),"") -> KnardDawg | O78: =VLOOKUP(D78,'Mapped Opponent'!$G$4:$H$22,2,0) -> 12 | Q78: ="Week "&O78 -> Week 12 | R78: =B78&D78 -> 2011Week 12 | S78: =IFERROR(__xludf.DUMMYFUNCTION("rank(J78,FILTER(J:J,R:R=R78))"),6.0) -> 6 | T78: =IFERROR(12-S78,0) -> 6 | U78: =12-T78 -> 6 | V78: =averageif(AllData!A:A,B78,AllData!R:R)/vlookup(B78,AllData!A:O,15,0) -> 88.551282
A79: =B79&C79&O79 -> 2011Rooney/Jackson12 | B79: 2011 | C79: Rooney/Jackson | D79: Week 12 | E79: 42102 | F79: W 98.2-70.8 | G79: at | H79: Kibbles 'n Fitz (8-4) | I79: Tyler Howard | J79: 98.2 | K79: 70.8 | L79: =IF(LEFT(F79,1)="W",1,0) -> 1 | M79: =IF(ISNUMBER(SEARCH("Round",D79)),"Playoffs","Regular Season") -> Regular Season | N79: =IFERROR(VLOOKUP(I79,Mapped_Owner,2,0),"") -> T-How | O79: =VLOOKUP(D79,'Mapped Opponent'!$G$4:$H$22,2,0) -> 12 | Q79: ="Week "&O79 -> Week 12 | R79: =B79&D79 -> 2011Week 12 | S79: =IFERROR(__xludf.DUMMYFUNCTION("rank(J79,FILTER(J:J,R:R=R79))"),4.0) -> 4 | T79: =IFERROR(12-S79,0) -> 8 | U79: =12-T79 -> 4 | V79: =averageif(AllData!A:A,B79,AllData!R:R)/vlookup(B79,AllData!A:O,15,0) -> 88.551282
A80: =B80&C80&O80 -> 2011Buser12 | B80: 2011 | C80: Buser | D80: Week 12 | E80: 42220 | F80: W 116.1-74.9 | H80: Salt Bake City (7-5) | I80: R Saltiel | J80: 116.1 | K80: 74.9 | L80: =IF(LEFT(F80,1)="W",1,0) -> 1 | M80: =IF(ISNUMBER(SEARCH("Round",D80)),"Playoffs","Regular Season") -> Regular Season | N80: =IFERROR(VLOOKUP(I80,Mapped_Owner,2,0),"") -> Salty | O80: =VLOOKUP(D80,'Mapped Opponent'!$G$4:$H$22,2,0) -> 12 | Q80: ="Week "&O80 -> Week 12 | R80: =B80&D80 -> 2011Week 12 | S80: =IFERROR(__xludf.DUMMYFUNCTION("rank(J80,FILTER(J:J,R:R=R80))"),2.0) -> 2 | T80: =IFERROR(12-S80,0) -> 10 | U80: =12-T80 -> 2 | V80: =averageif(AllData!A:A,B80,AllData!R:R)/vlookup(B80,AllData!A:O,15,0) -> 88.551282
A81: =B81&C81&O81 -> 2011Pierson12 | B81: 2011 | C81: Pierson | D81: Week 12 | E81: 42220 | F81: W 98.1-62.3 | H81: Yo Adrian! (4-8) | I81: Michael Fellows | J81: 98.1 | K81: 62.3 | L81: =IF(LEFT(F81,1)="W",1,0) -> 1 | M81: =IF(ISNUMBER(SEARCH("Round",D81)),"Playoffs","Regular Season") -> Regular Season | N81: =IFERROR(VLOOKUP(I81,Mapped_Owner,2,0),"") -> Fellows | O81: =VLOOKUP(D81,'Mapped Opponent'!$G$4:$H$22,2,0) -> 12 | Q81: ="Week "&O81 -> Week 12 | R81: =B81&D81 -> 2011Week 12 | S81: =IFERROR(__xludf.DUMMYFUNCTION("rank(J81,FILTER(J:J,R:R=R81))"),5.0) -> 5 | T81: =IFERROR(12-S81,0) -> 7 | U81: =12-T81 -> 5 | V81: =averageif(AllData!A:A,B81,AllData!R:R)/vlookup(B81,AllData!A:O,15,0) -> 88.551282
A82: =B82&C82&O82 -> 2011Cock12 | B82: 2011 | C82: Cock | D82: Week 12 | E82: 42131 | F82: L 70.6-114.2 | H82: Cutler's Year (7-5) | I82: matt hudspeath | J82: 70.6 | K82: 114.2 | L82: =IF(LEFT(F82,1)="W",1,0) -> 0 | M82: =IF(ISNUMBER(SEARCH("Round",D82)),"Playoffs","Regular Season") -> Regular Season | N82: =IFERROR(VLOOKUP(I82,Mapped_Owner,2,0),"") -> Hudspeath | O82: =VLOOKUP(D82,'Mapped Opponent'!$G$4:$H$22,2,0) -> 12 | Q82: ="Week "&O82 -> Week 12 | R82: =B82&D82 -> 2011Week 12 | S82: =IFERROR(__xludf.DUMMYFUNCTION("rank(J82,FILTER(J:J,R:R=R82))"),11.0) -> 11 | T82: =IFERROR(12-S82,0) -> 1 | U82: =12-T82 -> 11 | V82: =averageif(AllData!A:A,B82,AllData!R:R)/vlookup(B82,AllData!A:O,15,0) -> 88.551282
A83: =B83&C83&O83 -> 2011Tayski12 | B83: 2011 | C83: Tayski | D83: Week 12 | E83: 42072 | F83: W 83.3-81.2 | H83: Show me your TDs (6-6) | I83: Jordan Shepherd | J83: 83.3 | K83: 81.2 | L83: =IF(LEFT(F83,1)="W",1,0) -> 1 | M83: =IF(ISNUMBER(SEARCH("Round",D83)),"Playoffs","Regular Season") -> Regular Season | N83: =IFERROR(VLOOKUP(I83,Mapped_Owner,2,0),"") -> Shep | O83: =VLOOKUP(D83,'Mapped Opponent'!$G$4:$H$22,2,0) -> 12 | Q83: ="Week "&O83 -> Week 12 | R83: =B83&D83 -> 2011Week 12 | S83: =IFERROR(__xludf.DUMMYFUNCTION("rank(J83,FILTER(J:J,R:R=R83))"),7.0) -> 7 | T83: =IFERROR(12-S83,0) -> 5 | U83: =12-T83 -> 7 | V83: =averageif(AllData!A:A,B83,AllData!R:R)/vlookup(B83,AllData!A:O,15,0) -> 88.551282
A84: =B84&C84&O84 -> 2011KnardDawg12 | B84: 2011 | C84: KnardDawg | D84: Week 12 | E84: 42161 | F84: W 116.4-89.6 | H84: The McRB is back! (6-6) | I84: Tyler Guckien | J84: 116.4 | K84: 89.6 | L84: =IF(LEFT(F84,1)="W",1,0) -> 1 | M84: =IF(ISNUMBER(SEARCH("Round",D84)),"Playoffs","Regular Season") -> Regular Season | N84: =IFERROR(VLOOKUP(I84,Mapped_Owner,2,0),"") -> Guckien | O84: =VLOOKUP(D84,'Mapped Opponent'!$G$4:$H$22,2,0) -> 12 | Q84: ="Week "&O84 -> Week 12 | R84: =B84&D84 -> 2011Week 12 | S84: =IFERROR(__xludf.DUMMYFUNCTION("rank(J84,FILTER(J:J,R:R=R84))"),1.0) -> 1 | T84: =IFERROR(12-S84,0) -> 11 | U84: =12-T84 -> 1 | V84: =averageif(AllData!A:A,B84,AllData!R:R)/vlookup(B84,AllData!A:O,15,0) -> 88.551282
A85: =B85&C85&O85 -> 2011T-How12 | B85: 2011 | C85: T-How | D85: Week 12 | E85: 42220 | F85: L 70.8-98.2 | H85: Clay Rodge (4-8) | I85: Stephen Rooney | J85: 70.8 | K85: 98.2 | L85: =IF(LEFT(F85,1)="W",1,0) -> 0 | M85: =IF(ISNUMBER(SEARCH("Round",D85)),"Playoffs","Regular Season") -> Regular Season | N85: =IFERROR(VLOOKUP(I85,Mapped_Owner,2,0),"") -> Rooney/Jackson | O85: =VLOOKUP(D85,'Mapped Opponent'!$G$4:$H$22,2,0) -> 12 | Q85: ="Week "&O85 -> Week 12 | R85: =B85&D85 -> 2011Week 12 | S85: =IFERROR(__xludf.DUMMYFUNCTION("rank(J85,FILTER(J:J,R:R=R85))"),10.0) -> 10 | T85: =IFERROR(12-S85,0) -> 2 | U85: =12-T85 -> 10 | V85: =averageif(AllData!A:A,B85,AllData!R:R)/vlookup(B85,AllData!A:O,15,0) -> 88.551282
A86: =B86&C86&O86 -> 2011Hudspeath13 | B86: 2011 | C86: Hudspeath | D86: Week 13 | E86: 42191 | F86: L 128.4-130.1 | H86: Gambling Man (9-4) | I86: Pierson Curtis | J86: 128.4 | K86: 130.1 | L86: =IF(LEFT(F86,1)="W",1,0) -> 0 | M86: =IF(ISNUMBER(SEARCH("Round",D86)),"Playoffs","Regular Season") -> Regular Season | N86: =IFERROR(VLOOKUP(I86,Mapped_Owner,2,0),"") -> Pierson | O86: =VLOOKUP(D86,'Mapped Opponent'!$G$4:$H$22,2,0) -> 13 | Q86: ="Week "&O86 -> Week 13 | R86: =B86&D86 -> 2011Week 13 | S86: =IFERROR(__xludf.DUMMYFUNCTION("rank(J86,FILTER(J:J,R:R=R86))"),2.0) -> 2 | T86: =IFERROR(12-S86,0) -> 10 | U86: =12-T86 -> 2 | V86: =averageif(AllData!A:A,B86,AllData!R:R)/vlookup(B86,AllData!A:O,15,0) -> 88.551282
A87: =B87&C87&O87 -> 2011Salty13 | B87: 2011 | C87: Salty | D87: Week 13 | E87: 42221 | F87: W 87-72.8 | H87: Kibbles 'n Fitz (8-5) | I87: Tyler Howard | J87: 87 | K87: 72.8 | L87: =IF(LEFT(F87,1)="W",1,0) -> 1 | M87: =IF(ISNUMBER(SEARCH("Round",D87)),"Playoffs","Regular Season") -> Regular Season | N87: =IFERROR(VLOOKUP(I87,Mapped_Owner,2,0),"") -> T-How | O87: =VLOOKUP(D87,'Mapped Opponent'!$G$4:$H$22,2,0) -> 13 | Q87: ="Week "&O87 -> Week 13 | R87: =B87&D87 -> 2011Week 13 | S87: =IFERROR(__xludf.DUMMYFUNCTION("rank(J87,FILTER(J:J,R:R=R87))"),6.0) -> 6 | T87: =IFERROR(12-S87,0) -> 6 | U87: =12-T87 -> 6 | V87: =averageif(AllData!A:A,B87,AllData!R:R)/vlookup(B87,AllData!A:O,15,0) -> 88.551282
A88: =B88&C88&O88 -> 2011Fellows13 | B88: 2011 | C88: Fellows | D88: Week 13 | E88: 42103 | F88: L 76.1-128.2 | H88: Yes We Cam (9-4) | I88: Ed Buser | J88: 76.1 | K88: 128.2 | L88: =IF(LEFT(F88,1)="W",1,0) -> 0 | M88: =IF(ISNUMBER(SEARCH("Round",D88)),"Playoffs","Regular Season") -> Regular Season | N88: =IFERROR(VLOOKUP(I88,Mapped_Owner,2,0),"") -> Buser | O88: =VLOOKUP(D88,'Mapped Opponent'!$G$4:$H$22,2,0) -> 13 | Q88: ="Week "&O88 -> Week 13 | R88: =B88&D88 -> 2011Week 13 | S88: =IFERROR(__xludf.DUMMYFUNCTION("rank(J88,FILTER(J:J,R:R=R88))"),8.0) -> 8 | T88: =IFERROR(12-S88,0) -> 4 | U88: =12-T88 -> 8 | V88: =averageif(AllData!A:A,B88,AllData!R:R)/vlookup(B88,AllData!A:O,15,0) -> 88.551282
A89: =B89&C89&O89 -> 2011Shep13 | B89: 2011 | C89: Shep | D89: Week 13 | E89: 42191 | F89: W 109.8-81.9 | H89: It's My Vick In a Box! (5-8) | I89: Chris Cochrane | J89: 109.8 | K89: 81.9 | L89: =IF(LEFT(F89,1)="W",1,0) -> 1 | M89: =IF(ISNUMBER(SEARCH("Round",D89)),"Playoffs","Regular Season") -> Regular Season | N89: =IFERROR(VLOOKUP(I89,Mapped_Owner,2,0),"") -> Cock | O89: =VLOOKUP(D89,'Mapped Opponent'!$G$4:$H$22,2,0) -> 13 | Q89: ="Week "&O89 -> Week 13 | R89: =B89&D89 -> 2011Week 13 | S89: =IFERROR(__xludf.DUMMYFUNCTION("rank(J89,FILTER(J:J,R:R=R89))"),4.0) -> 4 | T89: =IFERROR(12-S89,0) -> 8 | U89: =12-T89 -> 4 | V89: =averageif(AllData!A:A,B89,AllData!R:R)/vlookup(B89,AllData!A:O,15,0) -> 88.551282
A90: =B90&C90&O90 -> 2011Guckien13 | B90: 2011 | C90: Guckien | D90: Week 13 | E90: 42191 | F90: W 109.4-51.3 | H90: Team Weis (3-10) | I90: Taylor Weis | J90: 109.4 | K90: 51.3 | L90: =IF(LEFT(F90,1)="W",1,0) -> 1 | M90: =IF(ISNUMBER(SEARCH("Round",D90)),"Playoffs","Regular Season") -> Regular Season | N90: =IFERROR(VLOOKUP(I90,Mapped_Owner,2,0),"") -> Tayski | O90: =VLOOKUP(D90,'Mapped Opponent'!$G$4:$H$22,2,0) -> 13 | Q90: ="Week "&O90 -> Week 13 | R90: =B90&D90 -> 2011Week 13 | S90: =IFERROR(__xludf.DUMMYFUNCTION("rank(J90,FILTER(J:J,R:R=R90))"),5.0) -> 5 | T90: =IFERROR(12-S90,0) -> 7 | U90: =12-T90 -> 5 | V90: =averageif(AllData!A:A,B90,AllData!R:R)/vlookup(B90,AllData!A:O,15,0) -> 88.551282
A91: =B91&C91&O91 -> 2011Rooney/Jackson13 | B91: 2011 | C91: Rooney/Jackson | D91: Week 13 | E91: 42132 | F91: W 72-69.5 | H91: Tat Five (6-7) | I91: Alex Kinniard | J91: 72 | K91: 69.5 | L91: =IF(LEFT(F91,1)="W",1,0) -> 1 | M91: =IF(ISNUMBER(SEARCH("Round",D91)),"Playoffs","Regular Season") -> Regular Season | N91: =IFERROR(VLOOKUP(I91,Mapped_Owner,2,0),"") -> KnardDawg | O91: =VLOOKUP(D91,'Mapped Opponent'!$G$4:$H$22,2,0) -> 13 | Q91: ="Week "&O91 -> Week 13 | R91: =B91&D91 -> 2011Week 13 | S91: =IFERROR(__xludf.DUMMYFUNCTION("rank(J91,FILTER(J:J,R:R=R91))"),10.0) -> 10 | T91: =IFERROR(12-S91,0) -> 2 | U91: =12-T91 -> 10 | V91: =averageif(AllData!A:A,B91,AllData!R:R)/vlookup(B91,AllData!A:O,15,0) -> 88.551282
A92: =B92&C92&O92 -> 2011Buser13 | B92: 2011 | C92: Buser | D92: Week 13 | E92: 42251 | F92: W 128.2-76.1 | G92: at | H92: Yo Adrian! (4-9) | I92: Michael Fellows | J92: 128.2 | K92: 76.1 | L92: =IF(LEFT(F92,1)="W",1,0) -> 1 | M92: =IF(ISNUMBER(SEARCH("Round",D92)),"Playoffs","Regular Season") -> Regular Season | N92: =IFERROR(VLOOKUP(I92,Mapped_Owner,2,0),"") -> Fellows | O92: =VLOOKUP(D92,'Mapped Opponent'!$G$4:$H$22,2,0) -> 13 | Q92: ="Week "&O92 -> Week 13 | R92: =B92&D92 -> 2011Week 13 | S92: =IFERROR(__xludf.DUMMYFUNCTION("rank(J92,FILTER(J:J,R:R=R92))"),3.0) -> 3 | T92: =IFERROR(12-S92,0) -> 9 | U92: =12-T92 -> 3 | V92: =averageif(AllData!A:A,B92,AllData!R:R)/vlookup(B92,AllData!A:O,15,0) -> 88.551282
A93: =B93&C93&O93 -> 2011Pierson13 | B93: 2011 | C93: Pierson | D93: Week 13 | E93: 42251 | F93: W 130.1-128.4 | G93: at | H93: Cutler's Year (7-6) | I93: matt hudspeath | J93: 130.1 | K93: 128.4 | L93: =IF(LEFT(F93,1)="W",1,0) -> 1 | M93: =IF(ISNUMBER(SEARCH("Round",D93)),"Playoffs","Regular Season") -> Regular Season | N93: =IFERROR(VLOOKUP(I93,Mapped_Owner,2,0),"") -> Hudspeath | O93: =VLOOKUP(D93,'Mapped Opponent'!$G$4:$H$22,2,0) -> 13 | Q93: ="Week "&O93 -> Week 13 | R93: =B93&D93 -> 2011Week 13 | S93: =IFERROR(__xludf.DUMMYFUNCTION("rank(J93,FILTER(J:J,R:R=R93))"),1.0) -> 1 | T93: =IFERROR(12-S93,0) -> 11 | U93: =12-T93 -> 1 | V93: =averageif(AllData!A:A,B93,AllData!R:R)/vlookup(B93,AllData!A:O,15,0) -> 88.551282
A94: =B94&C94&O94 -> 2011Cock13 | B94: 2011 | C94: Cock | D94: Week 13 | E94: 42132 | F94: L 81.9-109.8 | G94: at | H94: Show me your TDs (7-6) | I94: Jordan Shepherd | J94: 81.9 | K94: 109.8 | L94: =IF(LEFT(F94,1)="W",1,0) -> 0 | M94: =IF(ISNUMBER(SEARCH("Round",D94)),"Playoffs","Regular Season") -> Regular Season | N94: =IFERROR(VLOOKUP(I94,Mapped_Owner,2,0),"") -> Shep | O94: =VLOOKUP(D94,'Mapped Opponent'!$G$4:$H$22,2,0) -> 13 | Q94: ="Week "&O94 -> Week 13 | R94: =B94&D94 -> 2011Week 13 | S94: =IFERROR(__xludf.DUMMYFUNCTION("rank(J94,FILTER(J:J,R:R=R94))"),7.0) -> 7 | T94: =IFERROR(12-S94,0) -> 5 | U94: =12-T94 -> 7 | V94: =averageif(AllData!A:A,B94,AllData!R:R)/vlookup(B94,AllData!A:O,15,0) -> 88.551282
A95: =B95&C95&O95 -> 2011Tayski13 | B95: 2011 | C95: Tayski | D95: Week 13 | E95: 42073 | F95: L 51.3-109.4 | G95: at | H95: The McRB is back! (7-6) | I95: Tyler Guckien | J95: 51.3 | K95: 109.4 | L95: =IF(LEFT(F95,1)="W",1,0) -> 0 | M95: =IF(ISNUMBER(SEARCH("Round",D95)),"Playoffs","Regular Season") -> Regular Season | N95: =IFERROR(VLOOKUP(I95,Mapped_Owner,2,0),"") -> Guckien | O95: =VLOOKUP(D95,'Mapped Opponent'!$G$4:$H$22,2,0) -> 13 | Q95: ="Week "&O95 -> Week 13 | R95: =B95&D95 -> 2011Week 13 | S95: =IFERROR(__xludf.DUMMYFUNCTION("rank(J95,FILTER(J:J,R:R=R95))"),12.0) -> 12 | T95: =IFERROR(12-S95,0) -> 0 | U95: =12-T95 -> 12 | V95: =averageif(AllData!A:A,B95,AllData!R:R)/vlookup(B95,AllData!A:O,15,0) -> 88.551282
A96: =B96&C96&O96 -> 2011KnardDawg13 | B96: 2011 | C96: KnardDawg | D96: Week 13 | E96: 42162 | F96: L 69.5-72 | G96: at | H96: Clay Rodge (5-8) | I96: Stephen Rooney | J96: 69.5 | K96: 72 | L96: =IF(LEFT(F96,1)="W",1,0) -> 0 | M96: =IF(ISNUMBER(SEARCH("Round",D96)),"Playoffs","Regular Season") -> Regular Season | N96: =IFERROR(VLOOKUP(I96,Mapped_Owner,2,0),"") -> Rooney/Jackson | O96: =VLOOKUP(D96,'Mapped Opponent'!$G$4:$H$22,2,0) -> 13 | Q96: ="Week "&O96 -> Week 13 | R96: =B96&D96 -> 2011Week 13 | S96: =IFERROR(__xludf.DUMMYFUNCTION("rank(J96,FILTER(J:J,R:R=R96))"),11.0) -> 11 | T96: =IFERROR(12-S96,0) -> 1 | U96: =12-T96 -> 11 | V96: =averageif(AllData!A:A,B96,AllData!R:R)/vlookup(B96,AllData!A:O,15,0) -> 88.551282
A97: =B97&C97&O97 -> 2011T-How13 | B97: 2011 | C97: T-How | D97: Week 13 | E97: 42221 | F97: L 72.8-87 | G97: at | H97: Salt Bake City (8-5) | I97: R Saltiel | J97: 72.8 | K97: 87 | L97: =IF(LEFT(F97,1)="W",1,0) -> 0 | M97: =IF(ISNUMBER(SEARCH("Round",D97)),"Playoffs","Regular Season") -> Regular Season | N97: =IFERROR(VLOOKUP(I97,Mapped_Owner,2,0),"") -> Salty | O97: =VLOOKUP(D97,'Mapped Opponent'!$G$4:$H$22,2,0) -> 13 | Q97: ="Week "&O97 -> Week 13 | R97: =B97&D97 -> 2011Week 13 | S97: =IFERROR(__xludf.DUMMYFUNCTION("rank(J97,FILTER(J:J,R:R=R97))"),9.0) -> 9 | T97: =IFERROR(12-S97,0) -> 3 | U97: =12-T97 -> 9 | V97: =averageif(AllData!A:A,B97,AllData!R:R)/vlookup(B97,AllData!A:O,15,0) -> 88.551282
A98: =B98&C98&O98 -> 2011Hudspeath2 | B98: 2011 | C98: Hudspeath | D98: Week 2 | E98: 42005 | F98: L 120-153.6 | G98: at | H98: Salt Bake City (2-0) | I98: R Saltiel | J98: 120 | K98: 153.6 | L98: =IF(LEFT(F98,1)="W",1,0) -> 0 | M98: =IF(ISNUMBER(SEARCH("Round",D98)),"Playoffs","Regular Season") -> Regular Season | N98: =IFERROR(VLOOKUP(I98,Mapped_Owner,2,0),"") -> Salty | O98: =VLOOKUP(D98,'Mapped Opponent'!$G$4:$H$22,2,0) -> 2 | Q98: ="Week "&O98 -> Week 2 | R98: =B98&D98 -> 2011Week 2 | S98: =IFERROR(__xludf.DUMMYFUNCTION("rank(J98,FILTER(J:J,R:R=R98))"),3.0) -> 3 | T98: =IFERROR(12-S98,0) -> 9 | U98: =12-T98 -> 3 | V98: =averageif(AllData!A:A,B98,AllData!R:R)/vlookup(B98,AllData!A:O,15,0) -> 88.551282
A99: =B99&C99&O99 -> 2011Salty2 | B99: 2011 | C99: Salty | D99: Week 2 | E99: 36557 | F99: W 153.6-120 | H99: Cutler's Year (1-1) | I99: matt hudspeath | J99: 153.6 | K99: 120 | L99: =IF(LEFT(F99,1)="W",1,0) -> 1 | M99: =IF(ISNUMBER(SEARCH("Round",D99)),"Playoffs","Regular Season") -> Regular Season | N99: =IFERROR(VLOOKUP(I99,Mapped_Owner,2,0),"") -> Hudspeath | O99: =VLOOKUP(D99,'Mapped Opponent'!$G$4:$H$22,2,0) -> 2 | Q99: ="Week "&O99 -> Week 2 | R99: =B99&D99 -> 2011Week 2 | S99: =IFERROR(__xludf.DUMMYFUNCTION("rank(J99,FILTER(J:J,R:R=R99))"),1.0) -> 1 | T99: =IFERROR(12-S99,0) -> 11 | U99: =12-T99 -> 1 | V99: =averageif(AllData!A:A,B99,AllData!R:R)/vlookup(B99,AllData!A:O,15,0) -> 88.551282
A100: =B100&C100&O100 -> 2011Fellows2 | B100: 2011 | C100: Fellows | D100: Week 2 | E100: 42005 | F100: W 128.5-77.4 | G100: at | H100: Show me your TDs (0-2) | I100: Jordan Shepherd | J100: 128.5 | K100: 77.4 | L100: =IF(LEFT(F100,1)="W",1,0) -> 1 | M100: =IF(ISNUMBER(SEARCH("Round",D100)),"Playoffs","Regular Season") -> Regular Season | N100: =IFERROR(VLOOKUP(I100,Mapped_Owner,2,0),"") -> Shep | O100: =VLOOKUP(D100,'Mapped Opponent'!$G$4:$H$22,2,0) -> 2 | Q100: ="Week "&O100 -> Week 2 | R100: =B100&D100 -> 2011Week 2 | S100: =IFERROR(__xludf.DUMMYFUNCTION("rank(J100,FILTER(J:J,R:R=R100))"),2.0) -> 2 | T100: =IFERROR(12-S100,0) -> 10 | U100: =12-T100 -> 2 | V100: =averageif(AllData!A:A,B100,AllData!R:R)/vlookup(B100,AllData!A:O,15,0) -> 88.551282
...

Sheet New Weekly Paste
A1: CONCATAWAY | B1: CONCAT HOME | C1: Week | D1: Year | E1: Week # | F1: Away Manager | G1: Away Manager Clean | H1: Away Score | I1: Home Manager | J1: Home Manager Clean | K1: Home Score | L1: Away Win? | M1: Home Win? | N1: NFL Week 1 | O1: TEAM MANAGER(S) | P1: SCORE | Q1: SCORE | R1: TEAM MANAGER(S) | S1: HOME TEAM | T1: Home Team Name | U1: Away team Name
A2: =D2&G2&C2 -> 2017TayskiWeek 1 | B2: =D2&J2&C2 -> 2017ShepWeek 1 | C2: ="Week "&E2 -> Week 1 | D2: 2017 | E2: =if(left(N1,4)="Play",substitute(right(N1,3),")",""), if(left(N1,3)="NFL",substitute(right(N1,2)," ",""),E1)) -> 1 | F2: =O2 -> Taylor Weis | G2: =VLOOKUP(F2,'Manager Coding'!C:D,2,0) -> Tayski | H2: =P2 -> 47.74 | I2: =R2 -> Jordan Shepherd | J2: =VLOOKUP(I2,'Manager Coding'!C:D,2,0) -> Shep | K2: =Q2 -> 80.22 | L2: =if(H2>K2,1,0) -> 0 | M2: =if(K2>H2,1,0) -> 1 | N2: Mariota and some Randos(4-9-0) | O2: Taylor Weis | P2: 47.74 | Q2: 80.22 | R2: Jordan Shepherd | S2: Suburban Kings(7-6-0) | T2: =IFERROR(abs(H2-K2),0) -> 32.48
A3: =D3&G3&C3 -> 2017PiersonWeek 1 | B3: =D3&J3&C3 -> 2017SaltyWeek 1 | C3: ="Week "&E3 -> Week 1 | D3: 2017 | E3: =if(left(N2,4)="Play",substitute(right(N2,3),")",""), if(left(N2,3)="NFL",substitute(right(N2,2)," ",""),E2)) -> 1 | F3: =O3 -> Pierson Curtis | G3: =VLOOKUP(F3,'Manager Coding'!C:D,2,0) -> Pierson | H3: =P3 -> 77.34 | I3: =R3 -> R Saltiel | J3: =VLOOKUP(I3,'Manager Coding'!C:D,2,0) -> Salty | K3: =Q3 -> 124.34 | L3: =if(H3>K3,1,0) -> 0 | M3: =if(K3>H3,1,0) -> 1 | N3: Aaron It to IR(6-7-0) | O3: Pierson Curtis | P3: 77.34 | Q3: 124.34 | R3: R Saltiel | S3: Mixon It Up(7-6-0) | T3: =IFERROR(abs(H3-K3),0) -> 47
A4: =D4&G4&C4 -> 2017BuserWeek 1 | B4: =D4&J4&C4 -> 2017FellowsWeek 1 | C4: ="Week "&E4 -> Week 1 | D4: 2017 | E4: =if(left(N3,4)="Play",substitute(right(N3,3),")",""), if(left(N3,3)="NFL",substitute(right(N3,2)," ",""),E3)) -> 1 | F4: =O4 -> Ed Buser | G4: =VLOOKUP(F4,'Manager Coding'!C:D,2,0) -> Buser | H4: =P4 -> 89.6 | I4: =R4 -> Michael Fellows | J4: =VLOOKUP(I4,'Manager Coding'!C:D,2,0) -> Fellows | K4: =Q4 -> 81.98 | L4: =if(H4>K4,1,0) -> 1 | M4: =if(K4>H4,1,0) -> 0 | N4: Hunting Szn(8-5-0) | O4: Ed Buser | P4: 89.6 | Q4: 81.98 | R4: Michael Fellows | S4: Deshaun 69ers(2-11-0) | T4: =IFERROR(abs(H4-K4),0) -> 7.62
A5: =D5&G5&C5 -> 2017Rooney/JacksonWeek 1 | B5: =D5&J5&C5 -> 2017CockWeek 1 | C5: ="Week "&E5 -> Week 1 | D5: 2017 | E5: =if(left(N4,4)="Play",substitute(right(N4,3),")",""), if(left(N4,3)="NFL",substitute(right(N4,2)," ",""),E4)) -> 1 | F5: =O5 -> Stephen Rooney, Jackson Sattell | G5: =VLOOKUP(F5,'Manager Coding'!C:D,2,0) -> Rooney/Jackson | H5: =P5 -> 94.98 | I5: =R5 -> Jack Babcock, Chris Cochrane | J5: =VLOOKUP(I5,'Manager Coding'!C:D,2,0) -> Cock | K5: =Q5 -> 94.54 | L5: =if(H5>K5,1,0) -> 1 | M5: =if(K5>H5,1,0) -> 0 | N5: GOD DAMNIT DALVIN(3-10-0) | O5: Stephen Rooney, Jackson Sattell | P5: 94.98 | Q5: 94.54 | R5: Jack Babcock, Chris Cochrane | S5: J. Cash and The Cochslappers(8-5-0) | T5: =IFERROR(abs(H5-K5),0) -> 0.44
A6: =D6&G6&C6 -> 2017HudspeathWeek 1 | B6: =D6&J6&C6 -> 2017KnardDawgWeek 1 | C6: ="Week "&E6 -> Week 1 | D6: 2017 | E6: =if(left(N5,4)="Play",substitute(right(N5,3),")",""), if(left(N5,3)="NFL",substitute(right(N5,2)," ",""),E5)) -> 1 | F6: =O6 -> matt hudspeath | G6: =VLOOKUP(F6,'Manager Coding'!C:D,2,0) -> Hudspeath | H6: =P6 -> 85.62 | I6: =R6 -> Alex Kinniard, Jack Reilly | J6: =VLOOKUP(I6,'Manager Coding'!C:D,2,0) -> KnardDawg | K6: =Q6 -> 108.44 | L6: =if(H6>K6,1,0) -> 0 | M6: =if(K6>H6,1,0) -> 1 | N6: Cutler's Year(7-6-0) | O6: matt hudspeath | P6: 85.62 | Q6: 108.44 | R6: Alex Kinniard, Jack Reilly | S6: Armed and DangeRuss(9-4-0) | T6: =IFERROR(abs(H6-K6),0) -> 22.82
A7: =D7&G7&C7 -> 2017RileyWeek 1 | B7: =D7&J7&C7 -> 2017T-HowWeek 1 | C7: ="Week "&E7 -> Week 1 | D7: 2017 | E7: =if(left(N6,4)="Play",substitute(right(N6,3),")",""), if(left(N6,3)="NFL",substitute(right(N6,2)," ",""),E6)) -> 1 | F7: =O7 -> Riley McElwain | G7: =VLOOKUP(F7,'Manager Coding'!C:D,2,0) -> Riley | H7: =P7 -> 60.68 | I7: =R7 -> Tyler Howard | J7: =VLOOKUP(I7,'Manager Coding'!C:D,2,0) -> T-How | K7: =Q7 -> 80.7 | L7: =if(H7>K7,1,0) -> 0 | M7: =if(K7>H7,1,0) -> 1 | N7: Mark My Words(11-2-0) | O7: Riley McElwain | P7: 60.68 | Q7: 80.7 | R7: Tyler Howard | S7: Big Buddy Brand(6-7-0) | T7: =IFERROR(abs(H7-K7),0) -> 20.02
A8: =D8&G8&C8 -> #N/A | B8: =D8&J8&C8 -> #N/A | C8: ="Week "&E8 -> Week 1 | D8: 2017 | E8: =if(left(N7,4)="Play",substitute(right(N7,3),")",""), if(left(N7,3)="NFL",substitute(right(N7,2)," ",""),E7)) -> 1 | F8: =O8 | G8: =VLOOKUP(F8,'Manager Coding'!C:D,2,0) -> #N/A | H8: =P8 | I8: =R8 | J8: =VLOOKUP(I8,'Manager Coding'!C:D,2,0) -> #N/A | K8: =Q8 | L8: =if(H8>K8,1,0) -> 0 | M8: =if(K8>H8,1,0) -> 0 | N8: NFL Week 2 | T8: =IFERROR(abs(H8-K8),0) -> 0
A9: =D9&G9&C9 -> #N/A | B9: =D9&J9&C9 -> #N/A | C9: ="Week "&E9 -> Week 2 | D9: 2017 | E9: =if(left(N8,4)="Play",substitute(right(N8,3),")",""), if(left(N8,3)="NFL",substitute(right(N8,2)," ",""),E8)) -> 2 | F9: =O9 -> TEAM MANAGER(S) | G9: =VLOOKUP(F9,'Manager Coding'!C:D,2,0) -> #N/A | H9: =P9 -> SCORE | I9: =R9 -> TEAM MANAGER(S) | J9: =VLOOKUP(I9,'Manager Coding'!C:D,2,0) -> #N/A | K9: =Q9 -> SCORE | L9: =if(H9>K9,1,0) -> 0 | M9: =if(K9>H9,1,0) -> 0 | N9: AWAY TEAM | O9: TEAM MANAGER(S) | P9: SCORE | Q9: SCORE | R9: TEAM MANAGER(S) | S9: HOME TEAM | T9: =IFERROR(abs(H9-K9),0) -> 0
A10: =D10&G10&C10 -> 2017PiersonWeek 2 | B10: =D10&J10&C10 -> 2017TayskiWeek 2 | C10: ="Week "&E10 -> Week 2 | D10: 2017 | E10: =if(left(N9,4)="Play",substitute(right(N9,3),")",""), if(left(N9,3)="NFL",substitute(right(N9,2)," ",""),E9)) -> 2 | F10: =O10 -> Pierson Curtis | G10: =VLOOKUP(F10,'Manager Coding'!C:D,2,0) -> Pierson | H10: =P10 -> 70.42 | I10: =R10 -> Taylor Weis | J10: =VLOOKUP(I10,'Manager Coding'!C:D,2,0) -> Tayski | K10: =Q10 -> 108.6 | L10: =if(H10>K10,1,0) -> 0 | M10: =if(K10>H10,1,0) -> 1 | N10: Aaron It to IR(6-7-0) | O10: Pierson Curtis | P10: 70.42 | Q10: 108.6 | R10: Taylor Weis | S10: Mariota and some Randos(4-9-0) | T10: =IFERROR(abs(H10-K10),0) -> 38.18
A11: =D11&G11&C11 -> 2017ShepWeek 2 | B11: =D11&J11&C11 -> 2017BuserWeek 2 | C11: ="Week "&E11 -> Week 2 | D11: 2017 | E11: =if(left(N10,4)="Play",substitute(right(N10,3),")",""), if(left(N10,3)="NFL",substitute(right(N10,2)," ",""),E10)) -> 2 | F11: =O11 -> Jordan Shepherd | G11: =VLOOKUP(F11,'Manager Coding'!C:D,2,0) -> Shep | H11: =P11 -> 84.32 | I11: =R11 -> Ed Buser | J11: =VLOOKUP(I11,'Manager Coding'!C:D,2,0) -> Buser | K11: =Q11 -> 78.76 | L11: =if(H11>K11,1,0) -> 1 | M11: =if(K11>H11,1,0) -> 0 | N11: Suburban Kings(7-6-0) | O11: Jordan Shepherd | P11: 84.32 | Q11: 78.76 | R11: Ed Buser | S11: Hunting Szn(8-5-0) | T11: =IFERROR(abs(H11-K11),0) -> 5.56
A12: =D12&G12&C12 -> 2017SaltyWeek 2 | B12: =D12&J12&C12 -> 2017Rooney/JacksonWeek 2 | C12: ="Week "&E12 -> Week 2 | D12: 2017 | E12: =if(left(N11,4)="Play",substitute(right(N11,3),")",""), if(left(N11,3)="NFL",substitute(right(N11,2)," ",""),E11)) -> 2 | F12: =O12 -> R Saltiel | G12: =VLOOKUP(F12,'Manager Coding'!C:D,2,0) -> Salty | H12: =P12 -> 112.68 | I12: =R12 -> Stephen Rooney, Jackson Sattell | J12: =VLOOKUP(I12,'Manager Coding'!C:D,2,0) -> Rooney/Jackson | K12: =Q12 -> 100.6 | L12: =if(H12>K12,1,0) -> 1 | M12: =if(K12>H12,1,0) -> 0 | N12: Mixon It Up(7-6-0) | O12: R Saltiel | P12: 112.68 | Q12: 100.6 | R12: Stephen Rooney, Jackson Sattell | S12: GOD DAMNIT DALVIN(3-10-0) | T12: =IFERROR(abs(H12-K12),0) -> 12.08
A13: =D13&G13&C13 -> 2017FellowsWeek 2 | B13: =D13&J13&C13 -> 2017HudspeathWeek 2 | C13: ="Week "&E13 -> Week 2 | D13: 2017 | E13: =if(left(N12,4)="Play",substitute(right(N12,3),")",""), if(left(N12,3)="NFL",substitute(right(N12,2)," ",""),E12)) -> 2 | F13: =O13 -> Michael Fellows | G13: =VLOOKUP(F13,'Manager Coding'!C:D,2,0) -> Fellows | H13: =P13 -> 89.9 | I13: =R13 -> matt hudspeath | J13: =VLOOKUP(I13,'Manager Coding'!C:D,2,0) -> Hudspeath | K13: =Q13 -> 90.58 | L13: =if(H13>K13,1,0) -> 0 | M13: =if(K13>H13,1,0) -> 1 | N13: Deshaun 69ers(2-11-0) | O13: Michael Fellows | P13: 89.9 | Q13: 90.58 | R13: matt hudspeath | S13: Cutler's Year(7-6-0) | T13: =IFERROR(abs(H13-K13),0) -> 0.68
A14: =D14&G14&C14 -> 2017CockWeek 2 | B14: =D14&J14&C14 -> 2017RileyWeek 2 | C14: ="Week "&E14 -> Week 2 | D14: 2017 | E14: =if(left(N13,4)="Play",substitute(right(N13,3),")",""), if(left(N13,3)="NFL",substitute(right(N13,2)," ",""),E13)) -> 2 | F14: =O14 -> Jack Babcock, Chris Cochrane | G14: =VLOOKUP(F14,'Manager Coding'!C:D,2,0) -> Cock | H14: =P14 -> 90.04 | I14: =R14 -> Riley McElwain | J14: =VLOOKUP(I14,'Manager Coding'!C:D,2,0) -> Riley | K14: =Q14 -> 119.48 | L14: =if(H14>K14,1,0) -> 0 | M14: =if(K14>H14,1,0) -> 1 | N14: J. Cash and The Cochslappers(8-5-0) | O14: Jack Babcock, Chris Cochrane | P14: 90.04 | Q14: 119.48 | R14: Riley McElwain | S14: Mark My Words(11-2-0) | T14: =IFERROR(abs(H14-K14),0) -> 29.44
A15: =D15&G15&C15 -> 2017KnardDawgWeek 2 | B15: =D15&J15&C15 -> 2017T-HowWeek 2 | C15: ="Week "&E15 -> Week 2 | D15: 2017 | E15: =if(left(N14,4)="Play",substitute(right(N14,3),")",""), if(left(N14,3)="NFL",substitute(right(N14,2)," ",""),E14)) -> 2 | F15: =O15 -> Alex Kinniard, Jack Reilly | G15: =VLOOKUP(F15,'Manager Coding'!C:D,2,0) -> KnardDawg | H15: =P15 -> 60.62 | I15: =R15 -> Tyler Howard | J15: =VLOOKUP(I15,'Manager Coding'!C:D,2,0) -> T-How | K15: =Q15 -> 68.66 | L15: =if(H15>K15,1,0) -> 0 | M15: =if(K15>H15,1,0) -> 1 | N15: Armed and DangeRuss(9-4-0) | O15: Alex Kinniard, Jack Reilly | P15: 60.62 | Q15: 68.66 | R15: Tyler Howard | S15: Big Buddy Brand(6-7-0) | T15: =IFERROR(abs(H15-K15),0) -> 8.04
A16: =D16&G16&C16 -> #N/A | B16: =D16&J16&C16 -> #N/A | C16: ="Week "&E16 -> Week 2 | D16: 2017 | E16: =if(left(N15,4)="Play",substitute(right(N15,3),")",""), if(left(N15,3)="NFL",substitute(right(N15,2)," ",""),E15)) -> 2 | F16: =O16 | G16: =VLOOKUP(F16,'Manager Coding'!C:D,2,0) -> #N/A | H16: =P16 | I16: =R16 | J16: =VLOOKUP(I16,'Manager Coding'!C:D,2,0) -> #N/A | K16: =Q16 | L16: =if(H16>K16,1,0) -> 0 | M16: =if(K16>H16,1,0) -> 0 | N16: NFL Week 3 | T16: =IFERROR(abs(H16-K16),0) -> 0
A17: =D17&G17&C17 -> #N/A | B17: =D17&J17&C17 -> #N/A | C17: ="Week "&E17 -> Week 3 | D17: 2017 | E17: =if(left(N16,4)="Play",substitute(right(N16,3),")",""), if(left(N16,3)="NFL",substitute(right(N16,2)," ",""),E16)) -> 3 | F17: =O17 -> TEAM MANAGER(S) | G17: =VLOOKUP(F17,'Manager Coding'!C:D,2,0) -> #N/A | H17: =P17 -> SCORE | I17: =R17 -> TEAM MANAGER(S) | J17: =VLOOKUP(I17,'Manager Coding'!C:D,2,0) -> #N/A | K17: =Q17 -> SCORE | L17: =if(H17>K17,1,0) -> 0 | M17: =if(K17>H17,1,0) -> 0 | N17: AWAY TEAM | O17: TEAM MANAGER(S) | P17: SCORE | Q17: SCORE | R17: TEAM MANAGER(S) | S17: HOME TEAM | T17: =IFERROR(abs(H17-K17),0) -> 0
A18: =D18&G18&C18 -> 2017TayskiWeek 3 | B18: =D18&J18&C18 -> 2017BuserWeek 3 | C18: ="Week "&E18 -> Week 3 | D18: 2017 | E18: =if(left(N17,4)="Play",substitute(right(N17,3),")",""), if(left(N17,3)="NFL",substitute(right(N17,2)," ",""),E17)) -> 3 | F18: =O18 -> Taylor Weis | G18: =VLOOKUP(F18,'Manager Coding'!C:D,2,0) -> Tayski | H18: =P18 -> 50.7 | I18: =R18 -> Ed Buser | J18: =VLOOKUP(I18,'Manager Coding'!C:D,2,0) -> Buser | K18: =Q18 -> 101.34 | L18: =if(H18>K18,1,0) -> 0 | M18: =if(K18>H18,1,0) -> 1 | N18: Mariota and some Randos(4-9-0) | O18: Taylor Weis | P18: 50.7 | Q18: 101.34 | R18: Ed Buser | S18: Hunting Szn(8-5-0) | T18: =IFERROR(abs(H18-K18),0) -> 50.64
A19: =D19&G19&C19 -> 2017Rooney/JacksonWeek 3 | B19: =D19&J19&C19 -> 2017PiersonWeek 3 | C19: ="Week "&E19 -> Week 3 | D19: 2017 | E19: =if(left(N18,4)="Play",substitute(right(N18,3),")",""), if(left(N18,3)="NFL",substitute(right(N18,2)," ",""),E18)) -> 3 | F19: =O19 -> Stephen Rooney, Jackson Sattell | G19: =VLOOKUP(F19,'Manager Coding'!C:D,2,0) -> Rooney/Jackson | H19: =P19 -> 70.02 | I19: =R19 -> Pierson Curtis | J19: =VLOOKUP(I19,'Manager Coding'!C:D,2,0) -> Pierson | K19: =Q19 -> 99.32 | L19: =if(H19>K19,1,0) -> 0 | M19: =if(K19>H19,1,0) -> 1 | N19: GOD DAMNIT DALVIN(3-10-0) | O19: Stephen Rooney, Jackson Sattell | P19: 70.02 | Q19: 99.32 | R19: Pierson Curtis | S19: Aaron It to IR(6-7-0) | T19: =IFERROR(abs(H19-K19),0) -> 29.3
A20: =D20&G20&C20 -> 2017HudspeathWeek 3 | B20: =D20&J20&C20 -> 2017ShepWeek 3 | C20: ="Week "&E20 -> Week 3 | D20: 2017 | E20: =if(left(N19,4)="Play",substitute(right(N19,3),")",""), if(left(N19,3)="NFL",substitute(right(N19,2)," ",""),E19)) -> 3 | F20: =O20 -> matt hudspeath | G20: =VLOOKUP(F20,'Manager Coding'!C:D,2,0) -> Hudspeath | H20: =P20 -> 90.6 | I20: =R20 -> Jordan Shepherd | J20: =VLOOKUP(I20,'Manager Coding'!C:D,2,0) -> Shep | K20: =Q20 -> 68.56 | L20: =if(H20>K20,1,0) -> 1 | M20: =if(K20>H20,1,0) -> 0 | N20: Cutler's Year(7-6-0) | O20: matt hudspeath | P20: 90.6 | Q20: 68.56 | R20: Jordan Shepherd | S20: Suburban Kings(7-6-0) | T20: =IFERROR(abs(H20-K20),0) -> 22.04
A21: =D21&G21&C21 -> 2017RileyWeek 3 | B21: =D21&J21&C21 -> 2017SaltyWeek 3 | C21: ="Week "&E21 -> Week 3 | D21: 2017 | E21: =if(left(N20,4)="Play",substitute(right(N20,3),")",""), if(left(N20,3)="NFL",substitute(right(N20,2)," ",""),E20)) -> 3 | F21: =O21 -> Riley McElwain | G21: =VLOOKUP(F21,'Manager Coding'!C:D,2,0) -> Riley | H21: =P21 -> 114.22 | I21: =R21 -> R Saltiel | J21: =VLOOKUP(I21,'Manager Coding'!C:D,2,0) -> Salty | K21: =Q21 -> 107.06 | L21: =if(H21>K21,1,0) -> 1 | M21: =if(K21>H21,1,0) -> 0 | N21: Mark My Words(11-2-0) | O21: Riley McElwain | P21: 114.22 | Q21: 107.06 | R21: R Saltiel | S21: Mixon It Up(7-6-0) | T21: =IFERROR(abs(H21-K21),0) -> 7.16
A22: =D22&G22&C22 -> 2017T-HowWeek 3 | B22: =D22&J22&C22 -> 2017FellowsWeek 3 | C22: ="Week "&E22 -> Week 3 | D22: 2017 | E22: =if(left(N21,4)="Play",substitute(right(N21,3),")",""), if(left(N21,3)="NFL",substitute(right(N21,2)," ",""),E21)) -> 3 | F22: =O22 -> Tyler Howard | G22: =VLOOKUP(F22,'Manager Coding'!C:D,2,0) -> T-How | H22: =P22 -> 85 | I22: =R22 -> Michael Fellows | J22: =VLOOKUP(I22,'Manager Coding'!C:D,2,0) -> Fellows | K22: =Q22 -> 73.66 | L22: =if(H22>K22,1,0) -> 1 | M22: =if(K22>H22,1,0) -> 0 | N22: Big Buddy Brand(6-7-0) | O22: Tyler Howard | P22: 85 | Q22: 73.66 | R22: Michael Fellows | S22: Deshaun 69ers(2-11-0) | T22: =IFERROR(abs(H22-K22),0) -> 11.34
A23: =D23&G23&C23 -> 2017KnardDawgWeek 3 | B23: =D23&J23&C23 -> 2017CockWeek 3 | C23: ="Week "&E23 -> Week 3 | D23: 2017 | E23: =if(left(N22,4)="Play",substitute(right(N22,3),")",""), if(left(N22,3)="NFL",substitute(right(N22,2)," ",""),E22)) -> 3 | F23: =O23 -> Alex Kinniard, Jack Reilly | G23: =VLOOKUP(F23,'Manager Coding'!C:D,2,0) -> KnardDawg | H23: =P23 -> 86.38 | I23: =R23 -> Jack Babcock, Chris Cochrane | J23: =VLOOKUP(I23,'Manager Coding'!C:D,2,0) -> Cock | K23: =Q23 -> 110.1 | L23: =if(H23>K23,1,0) -> 0 | M23: =if(K23>H23,1,0) -> 1 | N23: Armed and DangeRuss(9-4-0) | O23: Alex Kinniard, Jack Reilly | P23: 86.38 | Q23: 110.1 | R23: Jack Babcock, Chris Cochrane | S23: J. Cash and The Cochslappers(8-5-0) | T23: =IFERROR(abs(H23-K23),0) -> 23.72
A24: =D24&G24&C24 -> #N/A | B24: =D24&J24&C24 -> #N/A | C24: ="Week "&E24 -> Week 3 | D24: 2017 | E24: =if(left(N23,4)="Play",substitute(right(N23,3),")",""), if(left(N23,3)="NFL",substitute(right(N23,2)," ",""),E23)) -> 3 | F24: =O24 | G24: =VLOOKUP(F24,'Manager Coding'!C:D,2,0) -> #N/A | H24: =P24 | I24: =R24 | J24: =VLOOKUP(I24,'Manager Coding'!C:D,2,0) -> #N/A | K24: =Q24 | L24: =if(H24>K24,1,0) -> 0 | M24: =if(K24>H24,1,0) -> 0 | N24: NFL Week 4 | T24: =IFERROR(abs(H24-K24),0) -> 0
A25: =D25&G25&C25 -> #N/A | B25: =D25&J25&C25 -> #N/A | C25: ="Week "&E25 -> Week 4 | D25: 2017 | E25: =if(left(N24,4)="Play",substitute(right(N24,3),")",""), if(left(N24,3)="NFL",substitute(right(N24,2)," ",""),E24)) -> 4 | F25: =O25 -> TEAM MANAGER(S) | G25: =VLOOKUP(F25,'Manager Coding'!C:D,2,0) -> #N/A | H25: =P25 -> SCORE | I25: =R25 -> TEAM MANAGER(S) | J25: =VLOOKUP(I25,'Manager Coding'!C:D,2,0) -> #N/A | K25: =Q25 -> SCORE | L25: =if(H25>K25,1,0) -> 0 | M25: =if(K25>H25,1,0) -> 0 | N25: AWAY TEAM | O25: TEAM MANAGER(S) | P25: SCORE | Q25: SCORE | R25: TEAM MANAGER(S) | S25: HOME TEAM | T25: =IFERROR(abs(H25-K25),0) -> 0
A26: =D26&G26&C26 -> 2017Rooney/JacksonWeek 4 | B26: =D26&J26&C26 -> 2017TayskiWeek 4 | C26: ="Week "&E26 -> Week 4 | D26: 2017 | E26: =if(left(N25,4)="Play",substitute(right(N25,3),")",""), if(left(N25,3)="NFL",substitute(right(N25,2)," ",""),E25)) -> 4 | F26: =O26 -> Stephen Rooney, Jackson Sattell | G26: =VLOOKUP(F26,'Manager Coding'!C:D,2,0) -> Rooney/Jackson | H26: =P26 -> 74.12 | I26: =R26 -> Taylor Weis | J26: =VLOOKUP(I26,'Manager Coding'!C:D,2,0) -> Tayski | K26: =Q26 -> 65.54 | L26: =if(H26>K26,1,0) -> 1 | M26: =if(K26>H26,1,0) -> 0 | N26: GOD DAMNIT DALVIN(3-10-0) | O26: Stephen Rooney, Jackson Sattell | P26: 74.12 | Q26: 65.54 | R26: Taylor Weis | S26: Mariota and some Randos(4-9-0) | T26: =IFERROR(abs(H26-K26),0) -> 8.58
A27: =D27&G27&C27 -> 2017BuserWeek 4 | B27: =D27&J27&C27 -> 2017HudspeathWeek 4 | C27: ="Week "&E27 -> Week 4 | D27: 2017 | E27: =if(left(N26,4)="Play",substitute(right(N26,3),")",""), if(left(N26,3)="NFL",substitute(right(N26,2)," ",""),E26)) -> 4 | F27: =O27 -> Ed Buser | G27: =VLOOKUP(F27,'Manager Coding'!C:D,2,0) -> Buser | H27: =P27 -> 62.18 | I27: =R27 -> matt hudspeath | J27: =VLOOKUP(I27,'Manager Coding'!C:D,2,0) -> Hudspeath | K27: =Q27 -> 120.58 | L27: =if(H27>K27,1,0) -> 0 | M27: =if(K27>H27,1,0) -> 1 | N27: Hunting Szn(8-5-0) | O27: Ed Buser | P27: 62.18 | Q27: 120.58 | R27: matt hudspeath | S27: Cutler's Year(7-6-0) | T27: =IFERROR(abs(H27-K27),0) -> 58.4
A28: =D28&G28&C28 -> 2017PiersonWeek 4 | B28: =D28&J28&C28 -> 2017RileyWeek 4 | C28: ="Week "&E28 -> Week 4 | D28: 2017 | E28: =if(left(N27,4)="Play",substitute(right(N27,3),")",""), if(left(N27,3)="NFL",substitute(right(N27,2)," ",""),E27)) -> 4 | F28: =O28 -> Pierson Curtis | G28: =VLOOKUP(F28,'Manager Coding'!C:D,2,0) -> Pierson | H28: =P28 -> 136.86 | I28: =R28 -> Riley McElwain | J28: =VLOOKUP(I28,'Manager Coding'!C:D,2,0) -> Riley | K28: =Q28 -> 110.58 | L28: =if(H28>K28,1,0) -> 1 | M28: =if(K28>H28,1,0) -> 0 | N28: Aaron It to IR(6-7-0) | O28: Pierson Curtis | P28: 136.86 | Q28: 110.58 | R28: Riley McElwain | S28: Mark My Words(11-2-0) | T28: =IFERROR(abs(H28-K28),0) -> 26.28
A29: =D29&G29&C29 -> 2017ShepWeek 4 | B29: =D29&J29&C29 -> 2017T-HowWeek 4 | C29: ="Week "&E29 -> Week 4 | D29: 2017 | E29: =if(left(N28,4)="Play",substitute(right(N28,3),")",""), if(left(N28,3)="NFL",substitute(right(N28,2)," ",""),E28)) -> 4 | F29: =O29 -> Jordan Shepherd | G29: =VLOOKUP(F29,'Manager Coding'!C:D,2,0) -> Shep | H29: =P29 -> 103.1 | I29: =R29 -> Tyler Howard | J29: =VLOOKUP(I29,'Manager Coding'!C:D,2,0) -> T-How | K29: =Q29 -> 70.5 | L29: =if(H29>K29,1,0) -> 1 | M29: =if(K29>H29,1,0) -> 0 | N29: Suburban Kings(7-6-0) | O29: Jordan Shepherd | P29: 103.1 | Q29: 70.5 | R29: Tyler Howard | S29: Big Buddy Brand(6-7-0) | T29: =IFERROR(abs(H29-K29),0) -> 32.6
A30: =D30&G30&C30 -> 2017SaltyWeek 4 | B30: =D30&J30&C30 -> 2017KnardDawgWeek 4 | C30: ="Week "&E30 -> Week 4 | D30: 2017 | E30: =if(left(N29,4)="Play",substitute(right(N29,3),")",""), if(left(N29,3)="NFL",substitute(right(N29,2)," ",""),E29)) -> 4 | F30: =O30 -> R Saltiel | G30: =VLOOKUP(F30,'Manager Coding'!C:D,2,0) -> Salty | H30: =P30 -> 51.18 | I30: =R30 -> Alex Kinniard, Jack Reilly | J30: =VLOOKUP(I30,'Manager Coding'!C:D,2,0) -> KnardDawg | K30: =Q30 -> 128.64 | L30: =if(H30>K30,1,0) -> 0 | M30: =if(K30>H30,1,0) -> 1 | N30: Mixon It Up(7-6-0) | O30: R Saltiel | P30: 51.18 | Q30: 128.64 | R30: Alex Kinniard, Jack Reilly | S30: Armed and DangeRuss(9-4-0) | T30: =IFERROR(abs(H30-K30),0) -> 77.46
A31: =D31&G31&C31 -> 2017FellowsWeek 4 | B31: =D31&J31&C31 -> 2017CockWeek 4 | C31: ="Week "&E31 -> Week 4 | D31: 2017 | E31: =if(left(N30,4)="Play",substitute(right(N30,3),")",""), if(left(N30,3)="NFL",substitute(right(N30,2)," ",""),E30)) -> 4 | F31: =O31 -> Michael Fellows | G31: =VLOOKUP(F31,'Manager Coding'!C:D,2,0) -> Fellows | H31: =P31 -> 79.88 | I31: =R31 -> Jack Babcock, Chris Cochrane | J31: =VLOOKUP(I31,'Manager Coding'!C:D,2,0) -> Cock | K31: =Q31 -> 82.62 | L31: =if(H31>K31,1,0) -> 0 | M31: =if(K31>H31,1,0) -> 1 | N31: Deshaun 69ers(2-11-0) | O31: Michael Fellows | P31: 79.88 | Q31: 82.62 | R31: Jack Babcock, Chris Cochrane | S31: J. Cash and The Cochslappers(8-5-0) | T31: =IFERROR(abs(H31-K31),0) -> 2.74
A32: =D32&G32&C32 -> #N/A | B32: =D32&J32&C32 -> #N/A | C32: ="Week "&E32 -> Week 4 | D32: 2017 | E32: =if(left(N31,4)="Play",substitute(right(N31,3),")",""), if(left(N31,3)="NFL",substitute(right(N31,2)," ",""),E31)) -> 4 | F32: =O32 | G32: =VLOOKUP(F32,'Manager Coding'!C:D,2,0) -> #N/A | H32: =P32 | I32: =R32 | J32: =VLOOKUP(I32,'Manager Coding'!C:D,2,0) -> #N/A | K32: =Q32 | L32: =if(H32>K32,1,0) -> 0 | M32: =if(K32>H32,1,0) -> 0 | N32: NFL Week 5 | T32: =IFERROR(abs(H32-K32),0) -> 0
A33: =D33&G33&C33 -> #N/A | B33: =D33&J33&C33 -> #N/A | C33: ="Week "&E33 -> Week 5 | D33: 2017 | E33: =if(left(N32,4)="Play",substitute(right(N32,3),")",""), if(left(N32,3)="NFL",substitute(right(N32,2)," ",""),E32)) -> 5 | F33: =O33 -> TEAM MANAGER(S) | G33: =VLOOKUP(F33,'Manager Coding'!C:D,2,0) -> #N/A | H33: =P33 -> SCORE | I33: =R33 -> TEAM MANAGER(S) | J33: =VLOOKUP(I33,'Manager Coding'!C:D,2,0) -> #N/A | K33: =Q33 -> SCORE | L33: =if(H33>K33,1,0) -> 0 | M33: =if(K33>H33,1,0) -> 0 | N33: AWAY TEAM | O33: TEAM MANAGER(S) | P33: SCORE | Q33: SCORE | R33: TEAM MANAGER(S) | S33: HOME TEAM | T33: =IFERROR(abs(H33-K33),0) -> 0
A34: =D34&G34&C34 -> 2017TayskiWeek 5 | B34: =D34&J34&C34 -> 2017HudspeathWeek 5 | C34: ="Week "&E34 -> Week 5 | D34: 2017 | E34: =if(left(N33,4)="Play",substitute(right(N33,3),")",""), if(left(N33,3)="NFL",substitute(right(N33,2)," ",""),E33)) -> 5 | F34: =O34 -> Taylor Weis | G34: =VLOOKUP(F34,'Manager Coding'!C:D,2,0) -> Tayski | H34: =P34 -> 81.26 | I34: =R34 -> matt hudspeath | J34: =VLOOKUP(I34,'Manager Coding'!C:D,2,0) -> Hudspeath | K34: =Q34 -> 81.08 | L34: =if(H34>K34,1,0) -> 1 | M34: =if(K34>H34,1,0) -> 0 | N34: Mariota and some Randos(4-9-0) | O34: Taylor Weis | P34: 81.26 | Q34: 81.08 | R34: matt hudspeath | S34: Cutler's Year(7-6-0) | T34: =IFERROR(abs(H34-K34),0) -> 0.18
A35: =D35&G35&C35 -> 2017RileyWeek 5 | B35: =D35&J35&C35 -> 2017Rooney/JacksonWeek 5 | C35: ="Week "&E35 -> Week 5 | D35: 2017 | E35: =if(left(N34,4)="Play",substitute(right(N34,3),")",""), if(left(N34,3)="NFL",substitute(right(N34,2)," ",""),E34)) -> 5 | F35: =O35 -> Riley McElwain | G35: =VLOOKUP(F35,'Manager Coding'!C:D,2,0) -> Riley | H35: =P35 -> 96.22 | I35: =R35 -> Stephen Rooney, Jackson Sattell | J35: =VLOOKUP(I35,'Manager Coding'!C:D,2,0) -> Rooney/Jackson | K35: =Q35 -> 91.36 | L35: =if(H35>K35,1,0) -> 1 | M35: =if(K35>H35,1,0) -> 0 | N35: Mark My Words(11-2-0) | O35: Riley McElwain | P35: 96.22 | Q35: 91.36 | R35: Stephen Rooney, Jackson Sattell | S35: GOD DAMNIT DALVIN(3-10-0) | T35: =IFERROR(abs(H35-K35),0) -> 4.86
A36: =D36&G36&C36 -> 2017T-HowWeek 5 | B36: =D36&J36&C36 -> 2017BuserWeek 5 | C36: ="Week "&E36 -> Week 5 | D36: 2017 | E36: =if(left(N35,4)="Play",substitute(right(N35,3),")",""), if(left(N35,3)="NFL",substitute(right(N35,2)," ",""),E35)) -> 5 | F36: =O36 -> Tyler Howard | G36: =VLOOKUP(F36,'Manager Coding'!C:D,2,0) -> T-How | H36: =P36 -> 68.2 | I36: =R36 -> Ed Buser | J36: =VLOOKUP(I36,'Manager Coding'!C:D,2,0) -> Buser | K36: =Q36 -> 91.16 | L36: =if(H36>K36,1,0) -> 0 | M36: =if(K36>H36,1,0) -> 1 | N36: Big Buddy Brand(6-7-0) | O36: Tyler Howard | P36: 68.2 | Q36: 91.16 | R36: Ed Buser | S36: Hunting Szn(8-5-0) | T36: =IFERROR(abs(H36-K36),0) -> 22.96
A37: =D37&G37&C37 -> 2017KnardDawgWeek 5 | B37: =D37&J37&C37 -> 2017PiersonWeek 5 | C37: ="Week "&E37 -> Week 5 | D37: 2017 | E37: =if(left(N36,4)="Play",substitute(right(N36,3),")",""), if(left(N36,3)="NFL",substitute(right(N36,2)," ",""),E36)) -> 5 | F37: =O37 -> Alex Kinniard, Jack Reilly | G37: =VLOOKUP(F37,'Manager Coding'!C:D,2,0) -> KnardDawg | H37: =P37 -> 113 | I37: =R37 -> Pierson Curtis | J37: =VLOOKUP(I37,'Manager Coding'!C:D,2,0) -> Pierson | K37: =Q37 -> 90.64 | L37: =if(H37>K37,1,0) -> 1 | M37: =if(K37>H37,1,0) -> 0 | N37: Armed and DangeRuss(9-4-0) | O37: Alex Kinniard, Jack Reilly | P37: 113 | Q37: 90.64 | R37: Pierson Curtis | S37: Aaron It to IR(6-7-0) | T37: =IFERROR(abs(H37-K37),0) -> 22.36
A38: =D38&G38&C38 -> 2017CockWeek 5 | B38: =D38&J38&C38 -> 2017ShepWeek 5 | C38: ="Week "&E38 -> Week 5 | D38: 2017 | E38: =if(left(N37,4)="Play",substitute(right(N37,3),")",""), if(left(N37,3)="NFL",substitute(right(N37,2)," ",""),E37)) -> 5 | F38: =O38 -> Jack Babcock, Chris Cochrane | G38: =VLOOKUP(F38,'Manager Coding'!C:D,2,0) -> Cock | H38: =P38 -> 81.66 | I38: =R38 -> Jordan Shepherd | J38: =VLOOKUP(I38,'Manager Coding'!C:D,2,0) -> Shep | K38: =Q38 -> 71.12 | L38: =if(H38>K38,1,0) -> 1 | M38: =if(K38>H38,1,0) -> 0 | N38: J. Cash and The Cochslappers(8-5-0) | O38: Jack Babcock, Chris Cochrane | P38: 81.66 | Q38: 71.12 | R38: Jordan Shepherd | S38: Suburban Kings(7-6-0) | T38: =IFERROR(abs(H38-K38),0) -> 10.54
A39: =D39&G39&C39 -> 2017FellowsWeek 5 | B39: =D39&J39&C39 -> 2017SaltyWeek 5 | C39: ="Week "&E39 -> Week 5 | D39: 2017 | E39: =if(left(N38,4)="Play",substitute(right(N38,3),")",""), if(left(N38,3)="NFL",substitute(right(N38,2)," ",""),E38)) -> 5 | F39: =O39 -> Michael Fellows | G39: =VLOOKUP(F39,'Manager Coding'!C:D,2,0) -> Fellows | H39: =P39 -> 107.54 | I39: =R39 -> R Saltiel | J39: =VLOOKUP(I39,'Manager Coding'!C:D,2,0) -> Salty | K39: =Q39 -> 122.94 | L39: =if(H39>K39,1,0) -> 0 | M39: =if(K39>H39,1,0) -> 1 | N39: Deshaun 69ers(2-11-0) | O39: Michael Fellows | P39: 107.54 | Q39: 122.94 | R39: R Saltiel | S39: Mixon It Up(7-6-0) | T39: =IFERROR(abs(H39-K39),0) -> 15.4
A40: =D40&G40&C40 -> #N/A | B40: =D40&J40&C40 -> #N/A | C40: ="Week "&E40 -> Week 5 | D40: 2017 | E40: =if(left(N39,4)="Play",substitute(right(N39,3),")",""), if(left(N39,3)="NFL",substitute(right(N39,2)," ",""),E39)) -> 5 | F40: =O40 | G40: =VLOOKUP(F40,'Manager Coding'!C:D,2,0) -> #N/A | H40: =P40 | I40: =R40 | J40: =VLOOKUP(I40,'Manager Coding'!C:D,2,0) -> #N/A | K40: =Q40 | L40: =if(H40>K40,1,0) -> 0 | M40: =if(K40>H40,1,0) -> 0 | N40: NFL Week 6 | T40: =IFERROR(abs(H40-K40),0) -> 0
A41: =D41&G41&C41 -> #N/A | B41: =D41&J41&C41 -> #N/A | C41: ="Week "&E41 -> Week 6 | D41: 2017 | E41: =if(left(N40,4)="Play",substitute(right(N40,3),")",""), if(left(N40,3)="NFL",substitute(right(N40,2)," ",""),E40)) -> 6 | F41: =O41 -> TEAM MANAGER(S) | G41: =VLOOKUP(F41,'Manager Coding'!C:D,2,0) -> #N/A | H41: =P41 -> SCORE | I41: =R41 -> TEAM MANAGER(S) | J41: =VLOOKUP(I41,'Manager Coding'!C:D,2,0) -> #N/A | K41: =Q41 -> SCORE | L41: =if(H41>K41,1,0) -> 0 | M41: =if(K41>H41,1,0) -> 0 | N41: AWAY TEAM | O41: TEAM MANAGER(S) | P41: SCORE | Q41: SCORE | R41: TEAM MANAGER(S) | S41: HOME TEAM | T41: =IFERROR(abs(H41-K41),0) -> 0
A42: =D42&G42&C42 -> 2017RileyWeek 6 | B42: =D42&J42&C42 -> 2017TayskiWeek 6 | C42: ="Week "&E42 -> Week 6 | D42: 2017 | E42: =if(left(N41,4)="Play",substitute(right(N41,3),")",""), if(left(N41,3)="NFL",substitute(right(N41,2)," ",""),E41)) -> 6 | F42: =O42 -> Riley McElwain | G42: =VLOOKUP(F42,'Manager Coding'!C:D,2,0) -> Riley | H42: =P42 -> 111.18 | I42: =R42 -> Taylor Weis | J42: =VLOOKUP(I42,'Manager Coding'!C:D,2,0) -> Tayski | K42: =Q42 -> 80.14 | L42: =if(H42>K42,1,0) -> 1 | M42: =if(K42>H42,1,0) -> 0 | N42: Mark My Words(11-2-0) | O42: Riley McElwain | P42: 111.18 | Q42: 80.14 | R42: Taylor Weis | S42: Mariota and some Randos(4-9-0) | T42: =IFERROR(abs(H42-K42),0) -> 31.04
A43: =D43&G43&C43 -> 2017HudspeathWeek 6 | B43: =D43&J43&C43 -> 2017T-HowWeek 6 | C43: ="Week "&E43 -> Week 6 | D43: 2017 | E43: =if(left(N42,4)="Play",substitute(right(N42,3),")",""), if(left(N42,3)="NFL",substitute(right(N42,2)," ",""),E42)) -> 6 | F43: =O43 -> matt hudspeath | G43: =VLOOKUP(F43,'Manager Coding'!C:D,2,0) -> Hudspeath | H43: =P43 -> 63.52 | I43: =R43 -> Tyler Howard | J43: =VLOOKUP(I43,'Manager Coding'!C:D,2,0) -> T-How | K43: =Q43 -> 68.9 | L43: =if(H43>K43,1,0) -> 0 | M43: =if(K43>H43,1,0) -> 1 | N43: Cutler's Year(7-6-0) | O43: matt hudspeath | P43: 63.52 | Q43: 68.9 | R43: Tyler Howard | S43: Big Buddy Brand(6-7-0) | T43: =IFERROR(abs(H43-K43),0) -> 5.38
A44: =D44&G44&C44 -> 2017Rooney/JacksonWeek 6 | B44: =D44&J44&C44 -> 2017KnardDawgWeek 6 | C44: ="Week "&E44 -> Week 6 | D44: 2017 | E44: =if(left(N43,4)="Play",substitute(right(N43,3),")",""), if(left(N43,3)="NFL",substitute(right(N43,2)," ",""),E43)) -> 6 | F44: =O44 -> Stephen Rooney, Jackson Sattell | G44: =VLOOKUP(F44,'Manager Coding'!C:D,2,0) -> Rooney/Jackson | H44: =P44 -> 57.64 | I44: =R44 -> Alex Kinniard, Jack Reilly | J44: =VLOOKUP(I44,'Manager Coding'!C:D,2,0) -> KnardDawg | K44: =Q44 -> 107.2 | L44: =if(H44>K44,1,0) -> 0 | M44: =if(K44>H44,1,0) -> 1 | N44: GOD DAMNIT DALVIN(3-10-0) | O44: Stephen Rooney, Jackson Sattell | P44: 57.64 | Q44: 107.2 | R44: Alex Kinniard, Jack Reilly | S44: Armed and DangeRuss(9-4-0) | T44: =IFERROR(abs(H44-K44),0) -> 49.56
A45: =D45&G45&C45 -> 2017BuserWeek 6 | B45: =D45&J45&C45 -> 2017CockWeek 6 | C45: ="Week "&E45 -> Week 6 | D45: 2017 | E45: =if(left(N44,4)="Play",substitute(right(N44,3),")",""), if(left(N44,3)="NFL",substitute(right(N44,2)," ",""),E44)) -> 6 | F45: =O45 -> Ed Buser | G45: =VLOOKUP(F45,'Manager Coding'!C:D,2,0) -> Buser | H45: =P45 -> 123.32 | I45: =R45 -> Jack Babcock, Chris Cochrane | J45: =VLOOKUP(I45,'Manager Coding'!C:D,2,0) -> Cock | K45: =Q45 -> 84.64 | L45: =if(H45>K45,1,0) -> 1 | M45: =if(K45>H45,1,0) -> 0 | N45: Hunting Szn(8-5-0) | O45: Ed Buser | P45: 123.32 | Q45: 84.64 | R45: Jack Babcock, Chris Cochrane | S45: J. Cash and The Cochslappers(8-5-0) | T45: =IFERROR(abs(H45-K45),0) -> 38.68
A46: =D46&G46&C46 -> 2017PiersonWeek 6 | B46: =D46&J46&C46 -> 2017FellowsWeek 6 | C46: ="Week "&E46 -> Week 6 | D46: 2017 | E46: =if(left(N45,4)="Play",substitute(right(N45,3),")",""), if(left(N45,3)="NFL",substitute(right(N45,2)," ",""),E45)) -> 6 | F46: =O46 -> Pierson Curtis | G46: =VLOOKUP(F46,'Manager Coding'!C:D,2,0) -> Pierson | H46: =P46 -> 89.72 | I46: =R46 -> Michael Fellows | J46: =VLOOKUP(I46,'Manager Coding'!C:D,2,0) -> Fellows | K46: =Q46 -> 59 | L46: =if(H46>K46,1,0) -> 1 | M46: =if(K46>H46,1,0) -> 0 | N46: Aaron It to IR(6-7-0) | O46: Pierson Curtis | P46: 89.72 | Q46: 59 | R46: Michael Fellows | S46: Deshaun 69ers(2-11-0) | T46: =IFERROR(abs(H46-K46),0) -> 30.72
A47: =D47&G47&C47 -> 2017ShepWeek 6 | B47: =D47&J47&C47 -> 2017SaltyWeek 6 | C47: ="Week "&E47 -> Week 6 | D47: 2017 | E47: =if(left(N46,4)="Play",substitute(right(N46,3),")",""), if(left(N46,3)="NFL",substitute(right(N46,2)," ",""),E46)) -> 6 | F47: =O47 -> Jordan Shepherd | G47: =VLOOKUP(F47,'Manager Coding'!C:D,2,0) -> Shep | H47: =P47 -> 114.88 | I47: =R47 -> R Saltiel | J47: =VLOOKUP(I47,'Manager Coding'!C:D,2,0) -> Salty | K47: =Q47 -> 92.72 | L47: =if(H47>K47,1,0) -> 1 | M47: =if(K47>H47,1,0) -> 0 | N47: Suburban Kings(7-6-0) | O47: Jordan Shepherd | P47: 114.88 | Q47: 92.72 | R47: R Saltiel | S47: Mixon It Up(7-6-0) | T47: =IFERROR(abs(H47-K47),0) -> 22.16
A48: =D48&G48&C48 -> #N/A | B48: =D48&J48&C48 -> #N/A | C48: ="Week "&E48 -> Week 6 | D48: 2017 | E48: =if(left(N47,4)="Play",substitute(right(N47,3),")",""), if(left(N47,3)="NFL",substitute(right(N47,2)," ",""),E47)) -> 6 | F48: =O48 | G48: =VLOOKUP(F48,'Manager Coding'!C:D,2,0) -> #N/A | H48: =P48 | I48: =R48 | J48: =VLOOKUP(I48,'Manager Coding'!C:D,2,0) -> #N/A | K48: =Q48 | L48: =if(H48>K48,1,0) -> 0 | M48: =if(K48>H48,1,0) -> 0 | N48: NFL Week 7 | T48: =IFERROR(abs(H48-K48),0) -> 0
A49: =D49&G49&C49 -> #N/A | B49: =D49&J49&C49 -> #N/A | C49: ="Week "&E49 -> Week 7 | D49: 2017 | E49: =if(left(N48,4)="Play",substitute(right(N48,3),")",""), if(left(N48,3)="NFL",substitute(right(N48,2)," ",""),E48)) -> 7 | F49: =O49 -> TEAM MANAGER(S) | G49: =VLOOKUP(F49,'Manager Coding'!C:D,2,0) -> #N/A | H49: =P49 -> SCORE | I49: =R49 -> TEAM MANAGER(S) | J49: =VLOOKUP(I49,'Manager Coding'!C:D,2,0) -> #N/A | K49: =Q49 -> SCORE | L49: =if(H49>K49,1,0) -> 0 | M49: =if(K49>H49,1,0) -> 0 | N49: AWAY TEAM | O49: TEAM MANAGER(S) | P49: SCORE | Q49: SCORE | R49: TEAM MANAGER(S) | S49: HOME TEAM | T49: =IFERROR(abs(H49-K49),0) -> 0
A50: =D50&G50&C50 -> 2017TayskiWeek 7 | B50: =D50&J50&C50 -> 2017T-HowWeek 7 | C50: ="Week "&E50 -> Week 7 | D50: 2017 | E50: =if(left(N49,4)="Play",substitute(right(N49,3),")",""), if(left(N49,3)="NFL",substitute(right(N49,2)," ",""),E49)) -> 7 | F50: =O50 -> Taylor Weis | G50: =VLOOKUP(F50,'Manager Coding'!C:D,2,0) -> Tayski | H50: =P50 -> 65.22 | I50: =R50 -> Tyler Howard | J50: =VLOOKUP(I50,'Manager Coding'!C:D,2,0) -> T-How | K50: =Q50 -> 81.12 | L50: =if(H50>K50,1,0) -> 0 | M50: =if(K50>H50,1,0) -> 1 | N50: Mariota and some Randos(4-9-0) | O50: Taylor Weis | P50: 65.22 | Q50: 81.12 | R50: Tyler Howard | S50: Big Buddy Brand(6-7-0) | T50: =IFERROR(abs(H50-K50),0) -> 15.9
A51: =D51&G51&C51 -> 2017KnardDawgWeek 7 | B51: =D51&J51&C51 -> 2017RileyWeek 7 | C51: ="Week "&E51 -> Week 7 | D51: 2017 | E51: =if(left(N50,4)="Play",substitute(right(N50,3),")",""), if(left(N50,3)="NFL",substitute(right(N50,2)," ",""),E50)) -> 7 | F51: =O51 -> Alex Kinniard, Jack Reilly | G51: =VLOOKUP(F51,'Manager Coding'!C:D,2,0) -> KnardDawg | H51: =P51 -> 97.04 | I51: =R51 -> Riley McElwain | J51: =VLOOKUP(I51,'Manager Coding'!C:D,2,0) -> Riley | K51: =Q51 -> 106.16 | L51: =if(H51>K51,1,0) -> 0 | M51: =if(K51>H51,1,0) -> 1 | N51: Armed and DangeRuss(9-4-0) | O51: Alex Kinniard, Jack Reilly | P51: 97.04 | Q51: 106.16 | R51: Riley McElwain | S51: Mark My Words(11-2-0) | T51: =IFERROR(abs(H51-K51),0) -> 9.12
A52: =D52&G52&C52 -> 2017CockWeek 7 | B52: =D52&J52&C52 -> 2017HudspeathWeek 7 | C52: ="Week "&E52 -> Week 7 | D52: 2017 | E52: =if(left(N51,4)="Play",substitute(right(N51,3),")",""), if(left(N51,3)="NFL",substitute(right(N51,2)," ",""),E51)) -> 7 | F52: =O52 -> Jack Babcock, Chris Cochrane | G52: =VLOOKUP(F52,'Manager Coding'!C:D,2,0) -> Cock | H52: =P52 -> 103.84 | I52: =R52 -> matt hudspeath | J52: =VLOOKUP(I52,'Manager Coding'!C:D,2,0) -> Hudspeath | K52: =Q52 -> 100.12 | L52: =if(H52>K52,1,0) -> 1 | M52: =if(K52>H52,1,0) -> 0 | N52: J. Cash and The Cochslappers(8-5-0) | O52: Jack Babcock, Chris Cochrane | P52: 103.84 | Q52: 100.12 | R52: matt hudspeath | S52: Cutler's Year(7-6-0) | T52: =IFERROR(abs(H52-K52),0) -> 3.72
A53: =D53&G53&C53 -> 2017FellowsWeek 7 | B53: =D53&J53&C53 -> 2017Rooney/JacksonWeek 7 | C53: ="Week "&E53 -> Week 7 | D53: 2017 | E53: =if(left(N52,4)="Play",substitute(right(N52,3),")",""), if(left(N52,3)="NFL",substitute(right(N52,2)," ",""),E52)) -> 7 | F53: =O53 -> Michael Fellows | G53: =VLOOKUP(F53,'Manager Coding'!C:D,2,0) -> Fellows | H53: =P53 -> 99.98 | I53: =R53 -> Stephen Rooney, Jackson Sattell | J53: =VLOOKUP(I53,'Manager Coding'!C:D,2,0) -> Rooney/Jackson | K53: =Q53 -> 96.68 | L53: =if(H53>K53,1,0) -> 1 | M53: =if(K53>H53,1,0) -> 0 | N53: Deshaun 69ers(2-11-0) | O53: Michael Fellows | P53: 99.98 | Q53: 96.68 | R53: Stephen Rooney, Jackson Sattell | S53: GOD DAMNIT DALVIN(3-10-0) | T53: =IFERROR(abs(H53-K53),0) -> 3.3
A54: =D54&G54&C54 -> 2017SaltyWeek 7 | B54: =D54&J54&C54 -> 2017BuserWeek 7 | C54: ="Week "&E54 -> Week 7 | D54: 2017 | E54: =if(left(N53,4)="Play",substitute(right(N53,3),")",""), if(left(N53,3)="NFL",substitute(right(N53,2)," ",""),E53)) -> 7 | F54: =O54 -> R Saltiel | G54: =VLOOKUP(F54,'Manager Coding'!C:D,2,0) -> Salty | H54: =P54 -> 90.32 | I54: =R54 -> Ed Buser | J54: =VLOOKUP(I54,'Manager Coding'!C:D,2,0) -> Buser | K54: =Q54 -> 83.62 | L54: =if(H54>K54,1,0) -> 1 | M54: =if(K54>H54,1,0) -> 0 | N54: Mixon It Up(7-6-0) | O54: R Saltiel | P54: 90.32 | Q54: 83.62 | R54: Ed Buser | S54: Hunting Szn(8-5-0) | T54: =IFERROR(abs(H54-K54),0) -> 6.7
A55: =D55&G55&C55 -> 2017ShepWeek 7 | B55: =D55&J55&C55 -> 2017PiersonWeek 7 | C55: ="Week "&E55 -> Week 7 | D55: 2017 | E55: =if(left(N54,4)="Play",substitute(right(N54,3),")",""), if(left(N54,3)="NFL",substitute(right(N54,2)," ",""),E54)) -> 7 | F55: =O55 -> Jordan Shepherd | G55: =VLOOKUP(F55,'Manager Coding'!C:D,2,0) -> Shep | H55: =P55 -> 82.96 | I55: =R55 -> Pierson Curtis | J55: =VLOOKUP(I55,'Manager Coding'!C:D,2,0) -> Pierson | K55: =Q55 -> 95.08 | L55: =if(H55>K55,1,0) -> 0 | M55: =if(K55>H55,1,0) -> 1 | N55: Suburban Kings(7-6-0) | O55: Jordan Shepherd | P55: 82.96 | Q55: 95.08 | R55: Pierson Curtis | S55: Aaron It to IR(6-7-0) | T55: =IFERROR(abs(H55-K55),0) -> 12.12
